Workbook

Sheet Como usar
A1: Como usar
A3: Primeira vez (Google Sheets)
A4: 1. Arquivo → Importar → envie este .xlsx → 'Criar nova planilha'.
A5: 2. Extensões → Apps Script → apague o código, cole o conteúdo de Lunaris.gs, salve. Recarregue a planilha.
A6: 3. Menu Genshin → 'Aplicar caixas de seleção e listas' (autorize). Depois Genshin → 'Atualizar dados do Lunaris'.
A7: 4. Opcional: Genshin → 'Atualizar automaticamente todo dia'.
A8: 5. Para as listas virarem 'chips': selecione a célula → Dados → Validação de dados → Avançado → Estilo de exibição: Chip.
A10: Uso normal
A11: • Time: personagem, arma, sets, main stats, raridade de cada peça (caixa marcada = 5★) e nível dos talentos.
A12: • Rotação: uma linha por golpe — a lista mostra só os golpes dos 4 do time (+ Golpes extras).
A13: • Perfis de buff: cada linha da Rotação escolhe um perfil (Todos, Nenhum ou um que você monta) dizendo quais buffs do
A14: time ainda estão ativos naquele trecho (ex.: depois que o Supremo da Iansan acaba).
... A28: • Taxa/dano crit extras valem para a rotação inteira.

Sheet Time
A1: Time e configurações
A2: Amarelo = você escolhe. Caixa marcada em '5★?' = peça 5 estrelas; desmarcada = 4 estrelas.
B3: Slot 1 | C3: Slot 2 | D3: Slot 3 | E3: Slot 4
A4: Personagem | B4: Mavuika | C4: Citlali | D4: Iansan | E4: Bennett
A5: Arma | B5: A Thousand Blazing Suns | C5: Thrilling Tales of Dragon Slayers | D5: Engulfing Lightning | E5: Absolution
A6: Set principal (4 peças) | B6: Obsidian Codex | C6: Instructor | D6: Scroll of the Hero of Cinder City | E6: Noblesse Oblige
A7: Set secundário (opcional → vira 2+2)
A8: Areia (main) | B8: EM | C8: ER | D8: ATK% | E8: ER
A9: Cálice (main) | B9: DMG% elemental | C9: DMG% elemental | D9: ATK% | E9: DMG% elemental
A10: Tiara (main) | B10: CD | C10: CR | D10: CR | E10: CR
A11: Flor 5★? | B11: TRUE | C11: FALSE | D11: TRUE | E11: TRUE
A12: Pena 5★? | B12: TRUE | C12: FALSE | D12: TRUE | E12: TRUE
A13: Areia 5★? | B13: TRUE | C13: TRUE | D13: TRUE | E13: TRUE
A14: Cálice 5★? | B14: TRUE | C14: FALSE | D14: TRUE | E14: TRUE
A15: Tiara 5★? | B15: TRUE | C15: FALSE | D15: TRUE | E15: TRUE
A16: Nível do talento: Ataque normal | B16: 10 | C16: 10 | D16: 10 | E16: 10
A17: Nível do talento: Habilidade | B17: 10 | C17: 10 | D17: 13 | E17: 13
A18: Nível do talento: Supremo | B18: 10 | C18: 10 | D18: 13 | E18: 13
A19: ER mínimo desejado | B19: 1 | C19: 2 | D19: 2 | E19: 2
A20: Rolls totais (vazio = automático) | B20: 40 | C20: 40 | D20: 40 | E20: 40
A21: Rolls em crítico CR+CD (vazio = otimizar) | B21: 20
A22: Configurações gerais | B22: Valor
A23: Nível dos personagens | B23: 90
A24: Nível do inimigo | B24: 100
A25: RES base do inimigo | B25: 0.1
A26: Redução de DEF do inimigo | B26: 0
A27: Rolls mínimos em cada substatus | B27: 2
A28: Duração da rotação (s) | B28: 17.5
A30: Buffs extras (o que não vem automático de personagem/arma/set)
A31: Alvo (personagem ou Todos) | B31: Stat | C31: Valor | D31: É buff do time? (segue o perfil) | E31: Descrição | F31: Rótulo (perfis de buff) | G31: (auxiliar)
A32: Mavuika | B32: ATK% | C32: 0.48 | D32: Sim | E32: TTDS R5 da Citlali (10 s após a troca em 6,7 s) | F32: TTDS | G32: =IF(F32="","_geral",TRIM(F32)) -> TTDS
A33: Mavuika | B33: DMG% | C33: 0.4 | D33: Sim | E33: Scroll da Iansan (12% + 28% Nightsoul) — Pyro/Electro | F33: Scroll | G33: =IF(F33="","_geral",TRIM(F33)) -> Scroll
A34: Bennett | B34: DMG% | C34: 0.4 | D34: Sim | E34: Scroll da Iansan | F34: Scroll | G34: =IF(F34="","_geral",TRIM(F34)) -> Scroll
A35: Iansan | B35: DMG% | C35: 0.4 | D35: Sim | E35: Scroll da Iansan (depois da reação dela) | F35: Scroll | G35: =IF(F35="","_geral",TRIM(F35)) -> Scroll
A36: Mavuika | B36: ATK% | C36: 0.3 | D36: Não | E36: Da planilha original — origem não identificada, confirme | G36: =IF(F36="","_geral",TRIM(F36)) -> _geral
A37: Mavuika | B37: DMG% | C37: 0.25 | D37: Não | E37: Da planilha original — origem não identificada, confirme | G37: =IF(F37="","_geral",TRIM(F37)) -> _geral
A38: Mavuika | B38: DMG% | C38: 0.15 | D38: Não | E38: Da planilha original — origem não identificada, confirme | G38: =IF(F38="","_geral",TRIM(F38)) -> _geral
A39: Citlali | B39: ATK% | C39: 0.3 | D39: Não | E39: Da planilha original — origem não identificada, confirme | G39: =IF(F39="","_geral",TRIM(F39)) -> _geral
D40: Não | G40: =IF(F40="","_geral",TRIM(F40)) -> _geral
D41: Não | G41: =IF(F41="","_geral",TRIM(F41)) -> _geral
D42: Não | G42: =IF(F42="","_geral",TRIM(F42)) -> _geral
D43: Não | G43: =IF(F43="","_geral",TRIM(F43)) -> _geral
D44: Não | G44: =IF(F44="","_geral",TRIM(F44)) -> _geral
D45: Não | G45: =IF(F45="","_geral",TRIM(F45)) -> _geral
D46: Não | G46: =IF(F46="","_geral",TRIM(F46)) -> _geral
D47: Não | G47: =IF(F47="","_geral",TRIM(F47)) -> _geral
D48: Não | G48: =IF(F48="","_geral",TRIM(F48)) -> _geral
D49: Não | G49: =IF(F49="","_geral",TRIM(F49)) -> _geral
D50: Não | G50: =IF(F50="","_geral",TRIM(F50)) -> _geral
D51: Não | G51: =IF(F51="","_geral",TRIM(F51)) -> _geral
A53: Valores fixos (ATK, EM, HP, DEF) em número; o resto em %. Taxa/dano crit extras valem sempre.

Sheet Rotação
A1: Rotação
A2: Preencha só A–E. A lista de golpes mostra os golpes dos 4 do time + os 'Golpes extras'. Desmarque 'Buffs do time' quando os buffs já acabaram.
A4: Golpe | B4: Hits | C4: Reação | D4: Perfil de buffs | E4: Ajuste DMG% (linha) | F4: Golpe extra? | G4: Golpe base | H4: Linha em L_Golpes | I4: Personagem | J4: Slot | K4: Tipo | L4: Talento | M4: Nível | N4: Escala ATK | O4: Escala EM | P4: Escala HP | Q4: Escala DEF | R4: Elemento | S4: Reação efetiva | T4: Perfil (efetivo) | U4: DMG% total | V4: Mult. DEF | W4: Mult. RES | X4: Fator (hits×DMG×DEF×RES) | Y4: Fator × ATK | Z4: Fator × EM | AA4: Fator × HP | AB4: Fator × DEF | AC4: ATK usado | AD4: EM usada | AE4: HP usado | AF4: DEF usada | AG4: Mult. reação | AH4: Dano (sem crit) | AI4: Dano (crit) | AJ4: Dano (média) | AK4: Dano fixo recebido (soma) | AL4: Fator dano fixo | AN4: Notas (livre)
A5: Mavuika - Habilidade: Flamestrider Charged Attack Cyclic DMG | B5: 1 | C5: Derreter | D5: Todos | E5: -0.4 | F5: =IF($A5="","",IF(ISNUMBER(MATCH($A5,'Golpes extras'!$A$2:$A$101,0)),"Sim","Não")) -> Não | G5: {=IF($A5="","",IF($F5="Sim",INDEX('Golpes extras'!$B$2:$B$101,MATCH($A5,'Golpes extras'!$A$2:$A$101,0))&"",$A5))} -> Mavuika - Habilidade: Flamestrider Charged Attack Cyclic DMG | H5: =IF($G5="","",IFERROR(MATCH($G5,L_Golpes!$A$2:$A$6000,0),"")) -> 52 | I5: {=IF($A5="","",IF(ISNUMBER($H5),INDEX(L_Golpes!$B$2:$B$6000,$H5),IF(IFERROR(INDEX('Golpes extras'!$C$2:$C$101,MATCH($A5,'Golpes extras'!$A$2:$A$101,0))&"","")<>"",INDEX('Golpes extras'!$C$2:$C$101,MATCH($A5,'Golpes extras'!$A$2:$A$101,0))&"","golpe?")))} -> Mavuika | J5: =IF(OR($I5="",$I5="golpe?"),"",IFERROR(MATCH($I5,Time!$B$4:$E$4,0),"fora do time")) -> 1 | K5: {=IF(ISNUMBER($J5),IF(IFERROR(INDEX('Golpes extras'!$D$2:$D$101,MATCH($A5,'Golpes extras'!$A$2:$A$101,0))&"","")<>"",INDEX('Golpes extras'!$D$2:$D$101,MATCH($A5,'Golpes extras'!$A$2:$A$101,0))&"",IF(ISNUMBER($H5),INDEX(L_Golpes!$D$2:$D$6000,$H5),"Outro")),"")} -> Carregado | L5: {=IF(ISNUMBER($J5),IF(ISNUMBER($H5),INDEX(L_Golpes!$C$2:$C$6000,$H5),""),"")} -> Habilidade | M5: {=IF(ISNUMBER($J5),IF($L5="Normal",INDEX('Cálculos'!$C$14:$F$14,$J5),IF($L5="Habilidade",INDEX('Cálculos'!$C$15:$F$15,$J5),IF($L5="Supremo",INDEX('Cálculos'!$C$16:$F$16,$J5),""))),"")} -> 10 | N5: {=IF(ISNUMBER($J5),IF(ISNUMBER($H5),INDEX(L_Golpes!$F$2:$T$6000,$H5,MAX(1,MIN(15,$M5))),0)+IF($F5="Sim",N(INDEX('Golpes extras'!$E$2:$E$101,MATCH($A5,'Golpes extras'!$A$2:$A$101,0))),0),"")} -> 1.955 | O5: {=IF(ISNUMBER($J5),IF(ISNUMBER($H5),INDEX(L_Golpes!$U$2:$AI$6000,$H5,MAX(1,MIN(15,$M5))),0)+IF($F5="Sim",N(INDEX('Golpes extras'!$F$2:$F$101,MATCH($A5,'Golpes extras'!$A$2:$A$101,0))),0),"")} -> 0 | P5: {=IF(ISNUMBER($J5),IF(ISNUMBER($H5),INDEX(L_Golpes!$AJ$2:$AX$6000,$H5,MAX(1,MIN(15,$M5))),0)+IF($F5="Sim",N(INDEX('Golpes extras'!$G$2:$G$101,MATCH($A5,'Golpes extras'!$A$2:$A$101,0))),0),"")} -> 0 | Q5: {=IF(ISNUMBER($J5),IF(ISNUMBER($H5),INDEX(L_Golpes!$AY$2:$BM$6000,$H5,MAX(1,MIN(15,$M5))),0)+IF($F5="Sim",N(INDEX('Golpes extras'!$H$2:$H$101,MATCH($A5,'Golpes extras'!$A$2:$A$101,0))),0),"")} -> 0 | R5: {=IF(ISNUMBER($J5),INDEX('Cálculos'!$C$19:$F$19,$J5),"")} -> Pyro | S5: =IF(ISNUMBER($J5),IF(AND($C5="Derreter",OR($R5="Pyro",$R5="Cryo")),"Derreter",IF(AND($C5="Vaporizar",OR($R5="Pyro",$R5="Hydro")),"Vaporizar","Nenhuma")),"") -> Derreter | T5: =IF(ISNUMBER($J5),IF(OR($D5="Não",$D5=FALSE),'Perfis de buff'!$A$8,IF(OR($D5="",$D5="Sim",$D5=TRUE),'Perfis de buff'!$A$4,$D5)),"") -> Todos | U5: {=IF(ISNUMBER($J5),INDEX('Cálculos'!$C$113:$F$113,$J5)+IF($K5="Normal",INDEX('Cálculos'!$C$114:$F$114,$J5),IF($K5="Carregado",INDEX('Cálculos'!$C$115:$F$115,$J5),IF($K5="Habilidade",INDEX('Cálculos'!$C$116:$F$116,$J5),IF($K5="Supremo",INDEX('Cálculos'!$C$117:$F$117,$J5),0))))+INDEX('Cálculos'!$C$143:$F$147,IFERROR(MATCH($T5,'Perfis de buff'!$A$4:$A$8,0),1),$J5)+IF($K5="Normal",INDEX('Cálculos'!$C$148:$F$152,IFERROR(MATCH($T5,'Perfis de buff'!$A$4:$A$8,0),1),$J5),IF($K5="Carregado",INDEX('Cálculos'!$C$153:$F$157,IFERROR(MATCH($T5,'Perfis de buff'!$A$4:$A$8,0),1),$J5),IF($K5="Habilidade",INDEX('Cálculos'!$C$158:$F$162,IFERROR(MATCH($T5,'Perfis de buff'!$A$4:$A$8,0),1),$J5),IF($K5="Supremo",INDEX('Cálculos'!$C$163:$F$167,IFERROR(MATCH($T5,'Perfis de buff'!$A$4:$A$8,0),1),$J5),0))))+N($E5),"")} -> 1.416 | V5: {=IF(ISNUMBER($J5),INDEX('Cálculos'!$C$180:$F$180,$J5),"")} -> 0.48717949 | W5: {=IF(ISNUMBER($J5),INDEX('Cálculos'!$C$182:$F$182,$J5),"")} -> 1.05 | X5: =IF(ISNUMBER($J5),IF($B5="",1,$B5)*(1+$U5)*$V5*$W5,"") -> 1.2358769 | Y5: =IF(ISNUMBER($J5),$X5*$N5,"") -> 2.4161394 | Z5: =IF(ISNUMBER($J5),$X5*$O5,"") -> 0 | AA5: =IF(ISNUMBER($J5),$X5*$P5,"") -> 0 | AB5: =IF(ISNUMBER($J5),$X5*$Q5,"") -> 0 | AC5: {=IF(ISNUMBER($J5),INDEX('Cálculos'!$C$332:$F$336,IFERROR(MATCH($T5,'Perfis de buff'!$A$4:$A$8,0),1),$J5),"")} -> 5791.25 | AD5: {=IF(ISNUMBER($J5),INDEX('Cálculos'!$C$339:$F$343,IFERROR(MATCH($T5,'Perfis de buff'!$A$4:$A$8,0),1),$J5),"")} -> 424 | AE5: {=IF(ISNUMBER($J5),INDEX('Cálculos'!$C$337:$F$337,$J5),"")} -> 19082.648 | AF5: {=IF(ISNUMBER($J5),INDEX('Cálculos'!$C$338:$F$338,$J5),"")} -> 929.208 | AG5: {=IF(ISNUMBER($J5),IF($S5="Derreter",INDEX('Cálculos'!$C$124:$F$124,$J5)*(1+2.78*$AD5/($AD5+1400)+INDEX('Cálculos'!$C$122:$F$122,$J5)),IF($S5="Vaporizar",INDEX('Cálculos'!$C$125:$F$125,$J5)*(1+2.78*$AD5/($AD5+1400)+INDEX('Cálculos'!$C$123:$F$123,$J5)),1)),"")} -> 3.2924561 | AH5: =IF(ISNUMBER($J5),(($AC5*$N5+$AD5*$O5+$AE5*$P5+$AF5*$Q5)*$X5+$AL5)*$AG5,"") -> 46069.585 | AI5: {=IF(ISNUMBER($J5),$AH5*(1+INDEX('Cálculos'!$C$331:$F$331,$J5)),"")} -> 152858.88 | AJ5: {=IF(ISNUMBER($J5),$AH5*(1+MIN(INDEX('Cálculos'!$C$330:$F$330,$J5),1)*INDEX('Cálculos'!$C$331:$F$331,$J5)),"")} -> 151684.2 | AK5: =IF(ISNUMBER($J5),'Fixo (cálculo)'!$AF5,"") -> 0 | AL5: =IF(ISNUMBER($J5),$AK5*(1+$U5)*$V5*$W5,"") -> 0 | AN5: C 6,9 s — antes do Q (sem Fighting Spirit, sem A4)
A6: Mavuika - Supremo (200 FS) | B6: 1 | C6: Derreter | D6: Todos | E6: -0.012 | F6: =IF($A6="","",IF(ISNUMBER(MATCH($A6,'Golpes extras'!$A$2:$A$101,0)),"Sim","Não")) -> Sim | G6: {=IF($A6="","",IF($F6="Sim",INDEX('Golpes extras'!$B$2:$B$101,MATCH($A6,'Golpes extras'!$A$2:$A$101,0))&"",$A6))} -> Mavuika - Supremo: Skill DMG | H6: =IF($G6="","",IFERROR(MATCH($G6,L_Golpes!$A$2:$A$6000,0),"")) -> 55 | I6: {=IF($A6="","",IF(ISNUMBER($H6),INDEX(L_Golpes!$B$2:$B$6000,$H6),IF(IFERROR(INDEX('Golpes extras'!$C$2:$C$101,MATCH($A6,'Golpes extras'!$A$2:$A$101,0))&"","")<>"",INDEX('Golpes extras'!$C$2:$C$101,MATCH($A6,'Golpes extras'!$A$2:$A$101,0))&"","golpe?")))} -> Mavuika | J6: =IF(OR($I6="",$I6="golpe?"),"",IFERROR(MATCH($I6,Time!$B$4:$E$4,0),"fora do time")) -> 1 | K6: {=IF(ISNUMBER($J6),IF(IFERROR(INDEX('Golpes extras'!$D$2:$D$101,MATCH($A6,'Golpes extras'!$A$2:$A$101,0))&"","")<>"",INDEX('Golpes extras'!$D$2:$D$101,MATCH($A6,'Golpes extras'!$A$2:$A$101,0))&"",IF(ISNUMBER($H6),INDEX(L_Golpes!$D$2:$D$6000,$H6),"Outro")),"")} -> Supremo | L6: {=IF(ISNUMBER($J6),IF(ISNUMBER($H6),INDEX(L_Golpes!$C$2:$C$6000,$H6),""),"")} -> Supremo | M6: {=IF(ISNUMBER($J6),IF($L6="Normal",INDEX('Cálculos'!$C$14:$F$14,$J6),IF($L6="Habilidade",INDEX('Cálculos'!$C$15:$F$15,$J6),IF($L6="Supremo",INDEX('Cálculos'!$C$16:$F$16,$J6),""))),"")} -> 10 | N6: {=IF(ISNUMBER($J6),IF(ISNUMBER($H6),INDEX(L_Golpes!$F$2:$T$6000,$H6,MAX(1,MIN(15,$M6))),0)+IF($F6="Sim",N(INDEX('Golpes extras'!$E$2:$E$101,MATCH($A6,'Golpes extras'!$A$2:$A$101,0))),0),"")} -> 13.7664 | O6: {=IF(ISNUMBER($J6),IF(ISNUMBER($H6),INDEX(L_Golpes!$U$2:$AI$6000,$H6,MAX(1,MIN(15,$M6))),0)+IF($F6="Sim",N(INDEX('Golpes extras'!$F$2:$F$101,MATCH($A6,'Golpes extras'!$A$2:$A$101,0))),0),"")} -> 0 | P6: {=IF(ISNUMBER($J6),IF(ISNUMBER($H6),INDEX(L_Golpes!$AJ$2:$AX$6000,$H6,MAX(1,MIN(15,$M6))),0)+IF($F6="Sim",N(INDEX('Golpes extras'!$G$2:$G$101,MATCH($A6,'Golpes extras'!$A$2:$A$101,0))),0),"")} -> 0 | Q6: {=IF(ISNUMBER($J6),IF(ISNUMBER($H6),INDEX(L_Golpes!$AY$2:$BM$6000,$H6,MAX(1,MIN(15,$M6))),0)+IF($F6="Sim",N(INDEX('Golpes extras'!$H$2:$H$101,MATCH($A6,'Golpes extras'!$A$2:$A$101,0))),0),"")} -> 0 | R6: {=IF(ISNUMBER($J6),INDEX('Cálculos'!$C$19:$F$19,$J6),"")} -> Pyro | S6: =IF(ISNUMBER($J6),IF(AND($C6="Derreter",OR($R6="Pyro",$R6="Cryo")),"Derreter",IF(AND($C6="Vaporizar",OR($R6="Pyro",$R6="Hydro")),"Vaporizar","Nenhuma")),"") -> Derreter | T6: =IF(ISNUMBER($J6),IF(OR($D6="Não",$D6=FALSE),'Perfis de buff'!$A$8,IF(OR($D6="",$D6="Sim",$D6=TRUE),'Perfis de buff'!$A$4,$D6)),"") -> Todos | U6: {=IF(ISNUMBER($J6),INDEX('Cálculos'!$C$113:$F$113,$J6)+IF($K6="Normal",INDEX('Cálculos'!$C$114:$F$114,$J6),IF($K6="Carregado",INDEX('Cálculos'!$C$115:$F$115,$J6),IF($K6="Habilidade",INDEX('Cálculos'!$C$116:$F$116,$J6),IF($K6="Supremo",INDEX('Cálculos'!$C$117:$F$117,$J6),0))))+INDEX('Cálculos'!$C$143:$F$147,IFERROR(MATCH($T6,'Perfis de buff'!$A$4:$A$8,0),1),$J6)+IF($K6="Normal",INDEX('Cálculos'!$C$148:$F$152,IFERROR(MATCH($T6,'Perfis de buff'!$A$4:$A$8,0),1),$J6),IF($K6="Carregado",INDEX('Cálculos'!$C$153:$F$157,IFERROR(MATCH($T6,'Perfis de buff'!$A$4:$A$8,0),1),$J6),IF($K6="Habilidade",INDEX('Cálculos'!$C$158:$F$162,IFERROR(MATCH($T6,'Perfis de buff'!$A$4:$A$8,0),1),$J6),IF($K6="Supremo",INDEX('Cálculos'!$C$163:$F$167,IFERROR(MATCH($T6,'Perfis de buff'!$A$4:$A$8,0),1),$J6),0))))+N($E6),"")} -> 1.804 | V6: {=IF(ISNUMBER($J6),INDEX('Cálculos'!$C$180:$F$180,$J6),"")} -> 0.48717949 | W6: {=IF(ISNUMBER($J6),INDEX('Cálculos'!$C$182:$F$182,$J6),"")} -> 1.05 | X6: =IF(ISNUMBER($J6),IF($B6="",1,$B6)*(1+$U6)*$V6*$W6,"") -> 1.4343538 | Y6: =IF(ISNUMBER($J6),$X6*$N6,"") -> 19.745889 | Z6: =IF(ISNUMBER($J6),$X6*$O6,"") -> 0 | AA6: =IF(ISNUMBER($J6),$X6*$P6,"") -> 0 | AB6: =IF(ISNUMBER($J6),$X6*$Q6,"") -> 0 | AC6: {=IF(ISNUMBER($J6),INDEX('Cálculos'!$C$332:$F$336,IFERROR(MATCH($T6,'Perfis de buff'!$A$4:$A$8,0),1),$J6),"")} -> 5791.25 | AD6: {=IF(ISNUMBER($J6),INDEX('Cálculos'!$C$339:$F$343,IFERROR(MATCH($T6,'Perfis de buff'!$A$4:$A$8,0),1),$J6),"")} -> 424 | AE6: {=IF(ISNUMBER($J6),INDEX('Cálculos'!$C$337:$F$337,$J6),"")} -> 19082.648 | AF6: {=IF(ISNUMBER($J6),INDEX('Cálculos'!$C$338:$F$338,$J6),"")} -> 929.208 | AG6: {=IF(ISNUMBER($J6),IF($S6="Derreter",INDEX('Cálculos'!$C$124:$F$124,$J6)*(1+2.78*$AD6/($AD6+1400)+INDEX('Cálculos'!$C$122:$F$122,$J6)),IF($S6="Vaporizar",INDEX('Cálculos'!$C$125:$F$125,$J6)*(1+2.78*$AD6/($AD6+1400)+INDEX('Cálculos'!$C$123:$F$123,$J6)),1)),"")} -> 3.2924561 | AH6: =IF(ISNUMBER($J6),(($AC6*$N6+$AD6*$O6+$AE6*$P6+$AF6*$Q6)*$X6+$AL6)*$AG6,"") -> 376503.48 | AI6: {=IF(ISNUMBER($J6),$AH6*(1+INDEX('Cálculos'!$C$331:$F$331,$J6)),"")} -> 1249238.6 | AJ6: {=IF(ISNUMBER($J6),$AH6*(1+MIN(INDEX('Cálculos'!$C$330:$F$330,$J6),1)*INDEX('Cálculos'!$C$331:$F$331,$J6)),"")} -> 1239638.5 | AK6: =IF(ISNUMBER($J6),'Fixo (cálculo)'!$AF6,"") -> 0 | AL6: =IF(ISNUMBER($J6),$AK6*(1+$U6)*$V6*$W6,"") -> 0 | AN6: 8.0 s · Q 7,4 s
A7: Mavuika - Carregado no Supremo | B7: 1 | C7: Nenhuma | D7: Todos | E7: -0.016 | F7: =IF($A7="","",IF(ISNUMBER(MATCH($A7,'Golpes extras'!$A$2:$A$101,0)),"Sim","Não")) -> Sim | G7: {=IF($A7="","",IF($F7="Sim",INDEX('Golpes extras'!$B$2:$B$101,MATCH($A7,'Golpes extras'!$A$2:$A$101,0))&"",$A7))} -> Mavuika - Habilidade: Flamestrider Charged Attack Cyclic DMG | H7: =IF($G7="","",IFERROR(MATCH($G7,L_Golpes!$A$2:$A$6000,0),"")) -> 52 | I7: {=IF($A7="","",IF(ISNUMBER($H7),INDEX(L_Golpes!$B$2:$B$6000,$H7),IF(IFERROR(INDEX('Golpes extras'!$C$2:$C$101,MATCH($A7,'Golpes extras'!$A$2:$A$101,0))&"","")<>"",INDEX('Golpes extras'!$C$2:$C$101,MATCH($A7,'Golpes extras'!$A$2:$A$101,0))&"","golpe?")))} -> Mavuika | J7: =IF(OR($I7="",$I7="golpe?"),"",IFERROR(MATCH($I7,Time!$B$4:$E$4,0),"fora do time")) -> 1 | K7: {=IF(ISNUMBER($J7),IF(IFERROR(INDEX('Golpes extras'!$D$2:$D$101,MATCH($A7,'Golpes extras'!$A$2:$A$101,0))&"","")<>"",INDEX('Golpes extras'!$D$2:$D$101,MATCH($A7,'Golpes extras'!$A$2:$A$101,0))&"",IF(ISNUMBER($H7),INDEX(L_Golpes!$D$2:$D$6000,$H7),"Outro")),"")} -> Carregado | L7: {=IF(ISNUMBER($J7),IF(ISNUMBER($H7),INDEX(L_Golpes!$C$2:$C$6000,$H7),""),"")} -> Habilidade | M7: {=IF(ISNUMBER($J7),IF($L7="Normal",INDEX('Cálculos'!$C$14:$F$14,$J7),IF($L7="Habilidade",INDEX('Cálculos'!$C$15:$F$15,$J7),IF($L7="Supremo",INDEX('Cálculos'!$C$16:$F$16,$J7),""))),"")} -> 10 | N7: {=IF(ISNUMBER($J7),IF(ISNUMBER($H7),INDEX(L_Golpes!$F$2:$T$6000,$H7,MAX(1,MIN(15,$M7))),0)+IF($F7="Sim",N(INDEX('Golpes extras'!$E$2:$E$101,MATCH($A7,'Golpes extras'!$A$2:$A$101,0))),0),"")} -> 3.995 | O7: {=IF(ISNUMBER($J7),IF(ISNUMBER($H7),INDEX(L_Golpes!$U$2:$AI$6000,$H7,MAX(1,MIN(15,$M7))),0)+IF($F7="Sim",N(INDEX('Golpes extras'!$F$2:$F$101,MATCH($A7,'Golpes extras'!$A$2:$A$101,0))),0),"")} -> 0 | P7: {=IF(ISNUMBER($J7),IF(ISNUMBER($H7),INDEX(L_Golpes!$AJ$2:$AX$6000,$H7,MAX(1,MIN(15,$M7))),0)+IF($F7="Sim",N(INDEX('Golpes extras'!$G$2:$G$101,MATCH($A7,'Golpes extras'!$A$2:$A$101,0))),0),"")} -> 0 | Q7: {=IF(ISNUMBER($J7),IF(ISNUMBER($H7),INDEX(L_Golpes!$AY$2:$BM$6000,$H7,MAX(1,MIN(15,$M7))),0)+IF($F7="Sim",N(INDEX('Golpes extras'!$H$2:$H$101,MATCH($A7,'Golpes extras'!$A$2:$A$101,0))),0),"")} -> 0 | R7: {=IF(ISNUMBER($J7),INDEX('Cálculos'!$C$19:$F$19,$J7),"")} -> Pyro | S7: =IF(ISNUMBER($J7),IF(AND($C7="Derreter",OR($R7="Pyro",$R7="Cryo")),"Derreter",IF(AND($C7="Vaporizar",OR($R7="Pyro",$R7="Hydro")),"Vaporizar","Nenhuma")),"") -> Nenhuma | T7: =IF(ISNUMBER($J7),IF(OR($D7="Não",$D7=FALSE),'Perfis de buff'!$A$8,IF(OR($D7="",$D7="Sim",$D7=TRUE),'Perfis de buff'!$A$4,$D7)),"") -> Todos | U7: {=IF(ISNUMBER($J7),INDEX('Cálculos'!$C$113:$F$113,$J7)+IF($K7="Normal",INDEX('Cálculos'!$C$114:$F$114,$J7),IF($K7="Carregado",INDEX('Cálculos'!$C$115:$F$115,$J7),IF($K7="Habilidade",INDEX('Cálculos'!$C$116:$F$116,$J7),IF($K7="Supremo",INDEX('Cálculos'!$C$117:$F$117,$J7),0))))+INDEX('Cálculos'!$C$143:$F$147,IFERROR(MATCH($T7,'Perfis de buff'!$A$4:$A$8,0),1),$J7)+IF($K7="Normal",INDEX('Cálculos'!$C$148:$F$152,IFERROR(MATCH($T7,'Perfis de buff'!$A$4:$A$8,0),1),$J7),IF($K7="Carregado",INDEX('Cálculos'!$C$153:$F$157,IFERROR(MATCH($T7,'Perfis de buff'!$A$4:$A$8,0),1),$J7),IF($K7="Habilidade",INDEX('Cálculos'!$C$158:$F$162,IFERROR(MATCH($T7,'Perfis de buff'!$A$4:$A$8,0),1),$J7),IF($K7="Supremo",INDEX('Cálculos'!$C$163:$F$167,IFERROR(MATCH($T7,'Perfis de buff'!$A$4:$A$8,0),1),$J7),0))))+N($E7),"")} -> 1.8 | V7: {=IF(ISNUMBER($J7),INDEX('Cálculos'!$C$180:$F$180,$J7),"")} -> 0.48717949 | W7: {=IF(ISNUMBER($J7),INDEX('Cálculos'!$C$182:$F$182,$J7),"")} -> 1.05 | X7: =IF(ISNUMBER($J7),IF($B7="",1,$B7)*(1+$U7)*$V7*$W7,"") -> 1.4323077 | Y7: =IF(ISNUMBER($J7),$X7*$N7,"") -> 5.7220692 | Z7: =IF(ISNUMBER($J7),$X7*$O7,"") -> 0 | AA7: =IF(ISNUMBER($J7),$X7*$P7,"") -> 0 | AB7: =IF(ISNUMBER($J7),$X7*$Q7,"") -> 0 | AC7: {=IF(ISNUMBER($J7),INDEX('Cálculos'!$C$332:$F$336,IFERROR(MATCH($T7,'Perfis de buff'!$A$4:$A$8,0),1),$J7),"")} -> 5791.25 | AD7: {=IF(ISNUMBER($J7),INDEX('Cálculos'!$C$339:$F$343,IFERROR(MATCH($T7,'Perfis de buff'!$A$4:$A$8,0),1),$J7),"")} -> 424 | AE7: {=IF(ISNUMBER($J7),INDEX('Cálculos'!$C$337:$F$337,$J7),"")} -> 19082.648 | AF7: {=IF(ISNUMBER($J7),INDEX('Cálculos'!$C$338:$F$338,$J7),"")} -> 929.208 | AG7: {=IF(ISNUMBER($J7),IF($S7="Derreter",INDEX('Cálculos'!$C$124:$F$124,$J7)*(1+2.78*$AD7/($AD7+1400)+INDEX('Cálculos'!$C$122:$F$122,$J7)),IF($S7="Vaporizar",INDEX('Cálculos'!$C$125:$F$125,$J7)*(1+2.78*$AD7/($AD7+1400)+INDEX('Cálculos'!$C$123:$F$123,$J7)),1)),"")} -> 1 | AH7: =IF(ISNUMBER($J7),(($AC7*$N7+$AD7*$O7+$AE7*$P7+$AF7*$Q7)*$X7+$AL7)*$AG7,"") -> 33137.933 | AI7: {=IF(ISNUMBER($J7),$AH7*(1+INDEX('Cálculos'!$C$331:$F$331,$J7)),"")} -> 109951.66 | AJ7: {=IF(ISNUMBER($J7),$AH7*(1+MIN(INDEX('Cálculos'!$C$330:$F$330,$J7),1)*INDEX('Cálculos'!$C$331:$F$331,$J7)),"")} -> 109106.71 | AK7: =IF(ISNUMBER($J7),'Fixo (cálculo)'!$AF7,"") -> 0 | AL7: =IF(ISNUMBER($J7),$AK7*(1+$U7)*$V7*$W7,"") -> 0 | AN7: 8.2 s · c
A8: Mavuika - Habilidade: Flamestrider Sprint DMG | B8: 1 | C8: Nenhuma | D8: Todos | E8: -0.029 | F8: =IF($A8="","",IF(ISNUMBER(MATCH($A8,'Golpes extras'!$A$2:$A$101,0)),"Sim","Não")) -> Não | G8: {=IF($A8="","",IF($F8="Sim",INDEX('Golpes extras'!$B$2:$B$101,MATCH($A8,'Golpes extras'!$A$2:$A$101,0))&"",$A8))} -> Mavuika - Habilidade: Flamestrider Sprint DMG | H8: =IF($G8="","",IFERROR(MATCH($G8,L_Golpes!$A$2:$A$6000,0),"")) -> 51 | I8: {=IF($A8="","",IF(ISNUMBER($H8),INDEX(L_Golpes!$B$2:$B$6000,$H8),IF(IFERROR(INDEX('Golpes extras'!$C$2:$C$101,MATCH($A8,'Golpes extras'!$A$2:$A$101,0))&"","")<>"",INDEX('Golpes extras'!$C$2:$C$101,MATCH($A8,'Golpes extras'!$A$2:$A$101,0))&"","golpe?")))} -> Mavuika | J8: =IF(OR($I8="",$I8="golpe?"),"",IFERROR(MATCH($I8,Time!$B$4:$E$4,0),"fora do time")) -> 1 | K8: {=IF(ISNUMBER($J8),IF(IFERROR(INDEX('Golpes extras'!$D$2:$D$101,MATCH($A8,'Golpes extras'!$A$2:$A$101,0))&"","")<>"",INDEX('Golpes extras'!$D$2:$D$101,MATCH($A8,'Golpes extras'!$A$2:$A$101,0))&"",IF(ISNUMBER($H8),INDEX(L_Golpes!$D$2:$D$6000,$H8),"Outro")),"")} -> Habilidade | L8: {=IF(ISNUMBER($J8),IF(ISNUMBER($H8),INDEX(L_Golpes!$C$2:$C$6000,$H8),""),"")} -> Habilidade | M8: {=IF(ISNUMBER($J8),IF($L8="Normal",INDEX('Cálculos'!$C$14:$F$14,$J8),IF($L8="Habilidade",INDEX('Cálculos'!$C$15:$F$15,$J8),IF($L8="Supremo",INDEX('Cálculos'!$C$16:$F$16,$J8),""))),"")} -> 10 | N8: {=IF(ISNUMBER($J8),IF(ISNUMBER($H8),INDEX(L_Golpes!$F$2:$T$6000,$H8,MAX(1,MIN(15,$M8))),0)+IF($F8="Sim",N(INDEX('Golpes extras'!$E$2:$E$101,MATCH($A8,'Golpes extras'!$A$2:$A$101,0))),0),"")} -> 1.598 | O8: {=IF(ISNUMBER($J8),IF(ISNUMBER($H8),INDEX(L_Golpes!$U$2:$AI$6000,$H8,MAX(1,MIN(15,$M8))),0)+IF($F8="Sim",N(INDEX('Golpes extras'!$F$2:$F$101,MATCH($A8,'Golpes extras'!$A$2:$A$101,0))),0),"")} -> 0 | P8: {=IF(ISNUMBER($J8),IF(ISNUMBER($H8),INDEX(L_Golpes!$AJ$2:$AX$6000,$H8,MAX(1,MIN(15,$M8))),0)+IF($F8="Sim",N(INDEX('Golpes extras'!$G$2:$G$101,MATCH($A8,'Golpes extras'!$A$2:$A$101,0))),0),"")} -> 0 | Q8: {=IF(ISNUMBER($J8),IF(ISNUMBER($H8),INDEX(L_Golpes!$AY$2:$BM$6000,$H8,MAX(1,MIN(15,$M8))),0)+IF($F8="Sim",N(INDEX('Golpes extras'!$H$2:$H$101,MATCH($A8,'Golpes extras'!$A$2:$A$101,0))),0),"")} -> 0 | R8: {=IF(ISNUMBER($J8),INDEX('Cálculos'!$C$19:$F$19,$J8),"")} -> Pyro | S8: =IF(ISNUMBER($J8),IF(AND($C8="Derreter",OR($R8="Pyro",$R8="Cryo")),"Derreter",IF(AND($C8="Vaporizar",OR($R8="Pyro",$R8="Hydro")),"Vaporizar","Nenhuma")),"") -> Nenhuma | T8: =IF(ISNUMBER($J8),IF(OR($D8="Não",$D8=FALSE),'Perfis de buff'!$A$8,IF(OR($D8="",$D8="Sim",$D8=TRUE),'Perfis de buff'!$A$4,$D8)),"") -> Todos | U8: {=IF(ISNUMBER($J8),INDEX('Cálculos'!$C$113:$F$113,$J8)+IF($K8="Normal",INDEX('Cálculos'!$C$114:$F$114,$J8),IF($K8="Carregado",INDEX('Cálculos'!$C$115:$F$115,$J8),IF($K8="Habilidade",INDEX('Cálculos'!$C$116:$F$116,$J8),IF($K8="Supremo",INDEX('Cálculos'!$C$117:$F$117,$J8),0))))+INDEX('Cálculos'!$C$143:$F$147,IFERROR(MATCH($T8,'Perfis de buff'!$A$4:$A$8,0),1),$J8)+IF($K8="Normal",INDEX('Cálculos'!$C$148:$F$152,IFERROR(MATCH($T8,'Perfis de buff'!$A$4:$A$8,0),1),$J8),IF($K8="Carregado",INDEX('Cálculos'!$C$153:$F$157,IFERROR(MATCH($T8,'Perfis de buff'!$A$4:$A$8,0),1),$J8),IF($K8="Habilidade",INDEX('Cálculos'!$C$158:$F$162,IFERROR(MATCH($T8,'Perfis de buff'!$A$4:$A$8,0),1),$J8),IF($K8="Supremo",INDEX('Cálculos'!$C$163:$F$167,IFERROR(MATCH($T8,'Perfis de buff'!$A$4:$A$8,0),1),$J8),0))))+N($E8),"")} -> 1.787 | V8: {=IF(ISNUMBER($J8),INDEX('Cálculos'!$C$180:$F$180,$J8),"")} -> 0.48717949 | W8: {=IF(ISNUMBER($J8),INDEX('Cálculos'!$C$182:$F$182,$J8),"")} -> 1.05 | X8: =IF(ISNUMBER($J8),IF($B8="",1,$B8)*(1+$U8)*$V8*$W8,"") -> 1.4256577 | Y8: =IF(ISNUMBER($J8),$X8*$N8,"") -> 2.278201 | Z8: =IF(ISNUMBER($J8),$X8*$O8,"") -> 0 | AA8: =IF(ISNUMBER($J8),$X8*$P8,"") -> 0 | AB8: =IF(ISNUMBER($J8),$X8*$Q8,"") -> 0 | AC8: {=IF(ISNUMBER($J8),INDEX('Cálculos'!$C$332:$F$336,IFERROR(MATCH($T8,'Perfis de buff'!$A$4:$A$8,0),1),$J8),"")} -> 5791.25 | AD8: {=IF(ISNUMBER($J8),INDEX('Cálculos'!$C$339:$F$343,IFERROR(MATCH($T8,'Perfis de buff'!$A$4:$A$8,0),1),$J8),"")} -> 424 | AE8: {=IF(ISNUMBER($J8),INDEX('Cálculos'!$C$337:$F$337,$J8),"")} -> 19082.648 | AF8: {=IF(ISNUMBER($J8),INDEX('Cálculos'!$C$338:$F$338,$J8),"")} -> 929.208 | AG8: {=IF(ISNUMBER($J8),IF($S8="Derreter",INDEX('Cálculos'!$C$124:$F$124,$J8)*(1+2.78*$AD8/($AD8+1400)+INDEX('Cálculos'!$C$122:$F$122,$J8)),IF($S8="Vaporizar",INDEX('Cálculos'!$C$125:$F$125,$J8)*(1+2.78*$AD8/($AD8+1400)+INDEX('Cálculos'!$C$123:$F$123,$J8)),1)),"")} -> 1 | AH8: =IF(ISNUMBER($J8),(($AC8*$N8+$AD8*$O8+$AE8*$P8+$AF8*$Q8)*$X8+$AL8)*$AG8,"") -> 13193.631 | AI8: {=IF(ISNUMBER($J8),$AH8*(1+INDEX('Cálculos'!$C$331:$F$331,$J8)),"")} -> 43776.469 | AJ8: {=IF(ISNUMBER($J8),$AH8*(1+MIN(INDEX('Cálculos'!$C$330:$F$330,$J8),1)*INDEX('Cálculos'!$C$331:$F$331,$J8)),"")} -> 43440.058 | AK8: =IF(ISNUMBER($J8),'Fixo (cálculo)'!$AF8,"") -> 0 | AL8: =IF(ISNUMBER($J8),$AK8*(1+$U8)*$V8*$W8,"") -> 0 | AN8: 8.9 s · d
A9: Mavuika - Carregado no Supremo | B9: 1 | C9: Derreter | D9: Todos | E9: -0.042 | F9: =IF($A9="","",IF(ISNUMBER(MATCH($A9,'Golpes extras'!$A$2:$A$101,0)),"Sim","Não")) -> Sim | G9: {=IF($A9="","",IF($F9="Sim",INDEX('Golpes extras'!$B$2:$B$101,MATCH($A9,'Golpes extras'!$A$2:$A$101,0))&"",$A9))} -> Mavuika - Habilidade: Flamestrider Charged Attack Cyclic DMG | H9: =IF($G9="","",IFERROR(MATCH($G9,L_Golpes!$A$2:$A$6000,0),"")) -> 52 | I9: {=IF($A9="","",IF(ISNUMBER($H9),INDEX(L_Golpes!$B$2:$B$6000,$H9),IF(IFERROR(INDEX('Golpes extras'!$C$2:$C$101,MATCH($A9,'Golpes extras'!$A$2:$A$101,0))&"","")<>"",INDEX('Golpes extras'!$C$2:$C$101,MATCH($A9,'Golpes extras'!$A$2:$A$101,0))&"","golpe?")))} -> Mavuika | J9: =IF(OR($I9="",$I9="golpe?"),"",IFERROR(MATCH($I9,Time!$B$4:$E$4,0),"fora do time")) -> 1 | K9: {=IF(ISNUMBER($J9),IF(IFERROR(INDEX('Golpes extras'!$D$2:$D$101,MATCH($A9,'Golpes extras'!$A$2:$A$101,0))&"","")<>"",INDEX('Golpes extras'!$D$2:$D$101,MATCH($A9,'Golpes extras'!$A$2:$A$101,0))&"",IF(ISNUMBER($H9),INDEX(L_Golpes!$D$2:$D$6000,$H9),"Outro")),"")} -> Carregado | L9: {=IF(ISNUMBER($J9),IF(ISNUMBER($H9),INDEX(L_Golpes!$C$2:$C$6000,$H9),""),"")} -> Habilidade | M9: {=IF(ISNUMBER($J9),IF($L9="Normal",INDEX('Cálculos'!$C$14:$F$14,$J9),IF($L9="Habilidade",INDEX('Cálculos'!$C$15:$F$15,$J9),IF($L9="Supremo",INDEX('Cálculos'!$C$16:$F$16,$J9),""))),"")} -> 10 | N9: {=IF(ISNUMBER($J9),IF(ISNUMBER($H9),INDEX(L_Golpes!$F$2:$T$6000,$H9,MAX(1,MIN(15,$M9))),0)+IF($F9="Sim",N(INDEX('Golpes extras'!$E$2:$E$101,MATCH($A9,'Golpes extras'!$A$2:$A$101,0))),0),"")} -> 3.995 | O9: {=IF(ISNUMBER($J9),IF(ISNUMBER($H9),INDEX(L_Golpes!$U$2:$AI$6000,$H9,MAX(1,MIN(15,$M9))),0)+IF($F9="Sim",N(INDEX('Golpes extras'!$F$2:$F$101,MATCH($A9,'Golpes extras'!$A$2:$A$101,0))),0),"")} -> 0 | P9: {=IF(ISNUMBER($J9),IF(ISNUMBER($H9),INDEX(L_Golpes!$AJ$2:$AX$6000,$H9,MAX(1,MIN(15,$M9))),0)+IF($F9="Sim",N(INDEX('Golpes extras'!$G$2:$G$101,MATCH($A9,'Golpes extras'!$A$2:$A$101,0))),0),"")} -> 0 | Q9: {=IF(ISNUMBER($J9),IF(ISNUMBER($H9),INDEX(L_Golpes!$AY$2:$BM$6000,$H9,MAX(1,MIN(15,$M9))),0)+IF($F9="Sim",N(INDEX('Golpes extras'!$H$2:$H$101,MATCH($A9,'Golpes extras'!$A$2:$A$101,0))),0),"")} -> 0 | R9: {=IF(ISNUMBER($J9),INDEX('Cálculos'!$C$19:$F$19,$J9),"")} -> Pyro | S9: =IF(ISNUMBER($J9),IF(AND($C9="Derreter",OR($R9="Pyro",$R9="Cryo")),"Derreter",IF(AND($C9="Vaporizar",OR($R9="Pyro",$R9="Hydro")),"Vaporizar","Nenhuma")),"") -> Derreter | T9: =IF(ISNUMBER($J9),IF(OR($D9="Não",$D9=FALSE),'Perfis de buff'!$A$8,IF(OR($D9="",$D9="Sim",$D9=TRUE),'Perfis de buff'!$A$4,$D9)),"") -> Todos | U9: {=IF(ISNUMBER($J9),INDEX('Cálculos'!$C$113:$F$113,$J9)+IF($K9="Normal",INDEX('Cálculos'!$C$114:$F$114,$J9),IF($K9="Carregado",INDEX('Cálculos'!$C$115:$F$115,$J9),IF($K9="Habilidade",INDEX('Cálculos'!$C$116:$F$116,$J9),IF($K9="Supremo",INDEX('Cálculos'!$C$117:$F$117,$J9),0))))+INDEX('Cálculos'!$C$143:$F$147,IFERROR(MATCH($T9,'Perfis de buff'!$A$4:$A$8,0),1),$J9)+IF($K9="Normal",INDEX('Cálculos'!$C$148:$F$152,IFERROR(MATCH($T9,'Perfis de buff'!$A$4:$A$8,0),1),$J9),IF($K9="Carregado",INDEX('Cálculos'!$C$153:$F$157,IFERROR(MATCH($T9,'Perfis de buff'!$A$4:$A$8,0),1),$J9),IF($K9="Habilidade",INDEX('Cálculos'!$C$158:$F$162,IFERROR(MATCH($T9,'Perfis de buff'!$A$4:$A$8,0),1),$J9),IF($K9="Supremo",INDEX('Cálculos'!$C$163:$F$167,IFERROR(MATCH($T9,'Perfis de buff'!$A$4:$A$8,0),1),$J9),0))))+N($E9),"")} -> 1.774 | V9: {=IF(ISNUMBER($J9),INDEX('Cálculos'!$C$180:$F$180,$J9),"")} -> 0.48717949 | W9: {=IF(ISNUMBER($J9),INDEX('Cálculos'!$C$182:$F$182,$J9),"")} -> 1.05 | X9: =IF(ISNUMBER($J9),IF($B9="",1,$B9)*(1+$U9)*$V9*$W9,"") -> 1.4190077 | Y9: =IF(ISNUMBER($J9),$X9*$N9,"") -> 5.6689357 | Z9: =IF(ISNUMBER($J9),$X9*$O9,"") -> 0 | AA9: =IF(ISNUMBER($J9),$X9*$P9,"") -> 0 | AB9: =IF(ISNUMBER($J9),$X9*$Q9,"") -> 0 | AC9: {=IF(ISNUMBER($J9),INDEX('Cálculos'!$C$332:$F$336,IFERROR(MATCH($T9,'Perfis de buff'!$A$4:$A$8,0),1),$J9),"")} -> 5791.25 | AD9: {=IF(ISNUMBER($J9),INDEX('Cálculos'!$C$339:$F$343,IFERROR(MATCH($T9,'Perfis de buff'!$A$4:$A$8,0),1),$J9),"")} -> 424 | AE9: {=IF(ISNUMBER($J9),INDEX('Cálculos'!$C$337:$F$337,$J9),"")} -> 19082.648 | AF9: {=IF(ISNUMBER($J9),INDEX('Cálculos'!$C$338:$F$338,$J9),"")} -> 929.208 | AG9: {=IF(ISNUMBER($J9),IF($S9="Derreter",INDEX('Cálculos'!$C$124:$F$124,$J9)*(1+2.78*$AD9/($AD9+1400)+INDEX('Cálculos'!$C$122:$F$122,$J9)),IF($S9="Vaporizar",INDEX('Cálculos'!$C$125:$F$125,$J9)*(1+2.78*$AD9/($AD9+1400)+INDEX('Cálculos'!$C$123:$F$123,$J9)),1)),"")} -> 3.2924561 | AH9: =IF(ISNUMBER($J9),(($AC9*$N9+$AD9*$O9+$AE9*$P9+$AF9*$Q9)*$X9+$AL9)*$AG9,"") -> 108092.07 | AI9: {=IF(ISNUMBER($J9),$AH9*(1+INDEX('Cálculos'!$C$331:$F$331,$J9)),"")} -> 358649.5 | AJ9: {=IF(ISNUMBER($J9),$AH9*(1+MIN(INDEX('Cálculos'!$C$330:$F$330,$J9),1)*INDEX('Cálculos'!$C$331:$F$331,$J9)),"")} -> 355893.37 | AK9: =IF(ISNUMBER($J9),'Fixo (cálculo)'!$AF9,"") -> 0 | AL9: =IF(ISNUMBER($J9),$AK9*(1+$U9)*$V9*$W9,"") -> 0 | AN9: 9.5 s · C
A10: Mavuika - Carregado no Supremo | B10: 1 | C10: Nenhuma | D10: Todos | E10: -0.055 | F10: =IF($A10="","",IF(ISNUMBER(MATCH($A10,'Golpes extras'!$A$2:$A$101,0)),"Sim","Não")) -> Sim | G10: {=IF($A10="","",IF($F10="Sim",INDEX('Golpes extras'!$B$2:$B$101,MATCH($A10,'Golpes extras'!$A$2:$A$101,0))&"",$A10))} -> Mavuika - Habilidade: Flamestrider Charged Attack Cyclic DMG | H10: =IF($G10="","",IFERROR(MATCH($G10,L_Golpes!$A$2:$A$6000,0),"")) -> 52 | I10: {=IF($A10="","",IF(ISNUMBER($H10),INDEX(L_Golpes!$B$2:$B$6000,$H10),IF(IFERROR(INDEX('Golpes extras'!$C$2:$C$101,MATCH($A10,'Golpes extras'!$A$2:$A$101,0))&"","")<>"",INDEX('Golpes extras'!$C$2:$C$101,MATCH($A10,'Golpes extras'!$A$2:$A$101,0))&"","golpe?")))} -> Mavuika | J10: =IF(OR($I10="",$I10="golpe?"),"",IFERROR(MATCH($I10,Time!$B$4:$E$4,0),"fora do time")) -> 1 | K10: {=IF(ISNUMBER($J10),IF(IFERROR(INDEX('Golpes extras'!$D$2:$D$101,MATCH($A10,'Golpes extras'!$A$2:$A$101,0))&"","")<>"",INDEX('Golpes extras'!$D$2:$D$101,MATCH($A10,'Golpes extras'!$A$2:$A$101,0))&"",IF(ISNUMBER($H10),INDEX(L_Golpes!$D$2:$D$6000,$H10),"Outro")),"")} -> Carregado | L10: {=IF(ISNUMBER($J10),IF(ISNUMBER($H10),INDEX(L_Golpes!$C$2:$C$6000,$H10),""),"")} -> Habilidade | M10: {=IF(ISNUMBER($J10),IF($L10="Normal",INDEX('Cálculos'!$C$14:$F$14,$J10),IF($L10="Habilidade",INDEX('Cálculos'!$C$15:$F$15,$J10),IF($L10="Supremo",INDEX('Cálculos'!$C$16:$F$16,$J10),""))),"")} -> 10 | N10: {=IF(ISNUMBER($J10),IF(ISNUMBER($H10),INDEX(L_Golpes!$F$2:$T$6000,$H10,MAX(1,MIN(15,$M10))),0)+IF($F10="Sim",N(INDEX('Golpes extras'!$E$2:$E$101,MATCH($A10,'Golpes extras'!$A$2:$A$101,0))),0),"")} -> 3.995 | O10: {=IF(ISNUMBER($J10),IF(ISNUMBER($H10),INDEX(L_Golpes!$U$2:$AI$6000,$H10,MAX(1,MIN(15,$M10))),0)+IF($F10="Sim",N(INDEX('Golpes extras'!$F$2:$F$101,MATCH($A10,'Golpes extras'!$A$2:$A$101,0))),0),"")} -> 0 | P10: {=IF(ISNUMBER($J10),IF(ISNUMBER($H10),INDEX(L_Golpes!$AJ$2:$AX$6000,$H10,MAX(1,MIN(15,$M10))),0)+IF($F10="Sim",N(INDEX('Golpes extras'!$G$2:$G$101,MATCH($A10,'Golpes extras'!$A$2:$A$101,0))),0),"")} -> 0 | Q10: {=IF(ISNUMBER($J10),IF(ISNUMBER($H10),INDEX(L_Golpes!$AY$2:$BM$6000,$H10,MAX(1,MIN(15,$M10))),0)+IF($F10="Sim",N(INDEX('Golpes extras'!$H$2:$H$101,MATCH($A10,'Golpes extras'!$A$2:$A$101,0))),0),"")} -> 0 | R10: {=IF(ISNUMBER($J10),INDEX('Cálculos'!$C$19:$F$19,$J10),"")} -> Pyro | S10: =IF(ISNUMBER($J10),IF(AND($C10="Derreter",OR($R10="Pyro",$R10="Cryo")),"Derreter",IF(AND($C10="Vaporizar",OR($R10="Pyro",$R10="Hydro")),"Vaporizar","Nenhuma")),"") -> Nenhuma | T10: =IF(ISNUMBER($J10),IF(OR($D10="Não",$D10=FALSE),'Perfis de buff'!$A$8,IF(OR($D10="",$D10="Sim",$D10=TRUE),'Perfis de buff'!$A$4,$D10)),"") -> Todos | U10: {=IF(ISNUMBER($J10),INDEX('Cálculos'!$C$113:$F$113,$J10)+IF($K10="Normal",INDEX('Cálculos'!$C$114:$F$114,$J10),IF($K10="Carregado",INDEX('Cálculos'!$C$115:$F$115,$J10),IF($K10="Habilidade",INDEX('Cálculos'!$C$116:$F$116,$J10),IF($K10="Supremo",INDEX('Cálculos'!$C$117:$F$117,$J10),0))))+INDEX('Cálculos'!$C$143:$F$147,IFERROR(MATCH($T10,'Perfis de buff'!$A$4:$A$8,0),1),$J10)+IF($K10="Normal",INDEX('Cálculos'!$C$148:$F$152,IFERROR(MATCH($T10,'Perfis de buff'!$A$4:$A$8,0),1),$J10),IF($K10="Carregado",INDEX('Cálculos'!$C$153:$F$157,IFERROR(MATCH($T10,'Perfis de buff'!$A$4:$A$8,0),1),$J10),IF($K10="Habilidade",INDEX('Cálculos'!$C$158:$F$162,IFERROR(MATCH($T10,'Perfis de buff'!$A$4:$A$8,0),1),$J10),IF($K10="Supremo",INDEX('Cálculos'!$C$163:$F$167,IFERROR(MATCH($T10,'Perfis de buff'!$A$4:$A$8,0),1),$J10),0))))+N($E10),"")} -> 1.761 | V10: {=IF(ISNUMBER($J10),INDEX('Cálculos'!$C$180:$F$180,$J10),"")} -> 0.48717949 | W10: {=IF(ISNUMBER($J10),INDEX('Cálculos'!$C$182:$F$182,$J10),"")} -> 1.05 | X10: =IF(ISNUMBER($J10),IF($B10="",1,$B10)*(1+$U10)*$V10*$W10,"") -> 1.4123577 | Y10: =IF(ISNUMBER($J10),$X10*$N10,"") -> 5.642369 | Z10: =IF(ISNUMBER($J10),$X10*$O10,"") -> 0 | AA10: =IF(ISNUMBER($J10),$X10*$P10,"") -> 0 | AB10: =IF(ISNUMBER($J10),$X10*$Q10,"") -> 0 | AC10: {=IF(ISNUMBER($J10),INDEX('Cálculos'!$C$332:$F$336,IFERROR(MATCH($T10,'Perfis de buff'!$A$4:$A$8,0),1),$J10),"")} -> 5791.25 | AD10: {=IF(ISNUMBER($J10),INDEX('Cálculos'!$C$339:$F$343,IFERROR(MATCH($T10,'Perfis de buff'!$A$4:$A$8,0),1),$J10),"")} -> 424 | AE10: {=IF(ISNUMBER($J10),INDEX('Cálculos'!$C$337:$F$337,$J10),"")} -> 19082.648 | AF10: {=IF(ISNUMBER($J10),INDEX('Cálculos'!$C$338:$F$338,$J10),"")} -> 929.208 | AG10: {=IF(ISNUMBER($J10),IF($S10="Derreter",INDEX('Cálculos'!$C$124:$F$124,$J10)*(1+2.78*$AD10/($AD10+1400)+INDEX('Cálculos'!$C$122:$F$122,$J10)),IF($S10="Vaporizar",INDEX('Cálculos'!$C$125:$F$125,$J10)*(1+2.78*$AD10/($AD10+1400)+INDEX('Cálculos'!$C$123:$F$123,$J10)),1)),"")} -> 1 | AH10: =IF(ISNUMBER($J10),(($AC10*$N10+$AD10*$O10+$AE10*$P10+$AF10*$Q10)*$X10+$AL10)*$AG10,"") -> 32676.369 | AI10: {=IF(ISNUMBER($J10),$AH10*(1+INDEX('Cálculos'!$C$331:$F$331,$J10)),"")} -> 108420.19 | AJ10: {=IF(ISNUMBER($J10),$AH10*(1+MIN(INDEX('Cálculos'!$C$330:$F$330,$J10),1)*INDEX('Cálculos'!$C$331:$F$331,$J10)),"")} -> 107587.01 | AK10: =IF(ISNUMBER($J10),'Fixo (cálculo)'!$AF10,"") -> 0 | AL10: =IF(ISNUMBER($J10),$AK10*(1+$U10)*$V10*$W10,"") -> 0 | AN10: 10.2 s · c
A11: Mavuika - Carregado no Supremo | B11: 1 | C11: Nenhuma | D11: Todos | E11: -0.069 | F11: =IF($A11="","",IF(ISNUMBER(MATCH($A11,'Golpes extras'!$A$2:$A$101,0)),"Sim","Não")) -> Sim | G11: {=IF($A11="","",IF($F11="Sim",INDEX('Golpes extras'!$B$2:$B$101,MATCH($A11,'Golpes extras'!$A$2:$A$101,0))&"",$A11))} -> Mavuika - Habilidade: Flamestrider Charged Attack Cyclic DMG | H11: =IF($G11="","",IFERROR(MATCH($G11,L_Golpes!$A$2:$A$6000,0),"")) -> 52 | I11: {=IF($A11="","",IF(ISNUMBER($H11),INDEX(L_Golpes!$B$2:$B$6000,$H11),IF(IFERROR(INDEX('Golpes extras'!$C$2:$C$101,MATCH($A11,'Golpes extras'!$A$2:$A$101,0))&"","")<>"",INDEX('Golpes extras'!$C$2:$C$101,MATCH($A11,'Golpes extras'!$A$2:$A$101,0))&"","golpe?")))} -> Mavuika | J11: =IF(OR($I11="",$I11="golpe?"),"",IFERROR(MATCH($I11,Time!$B$4:$E$4,0),"fora do time")) -> 1 | K11: {=IF(ISNUMBER($J11),IF(IFERROR(INDEX('Golpes extras'!$D$2:$D$101,MATCH($A11,'Golpes extras'!$A$2:$A$101,0))&"","")<>"",INDEX('Golpes extras'!$D$2:$D$101,MATCH($A11,'Golpes extras'!$A$2:$A$101,0))&"",IF(ISNUMBER($H11),INDEX(L_Golpes!$D$2:$D$6000,$H11),"Outro")),"")} -> Carregado | L11: {=IF(ISNUMBER($J11),IF(ISNUMBER($H11),INDEX(L_Golpes!$C$2:$C$6000,$H11),""),"")} -> Habilidade | M11: {=IF(ISNUMBER($J11),IF($L11="Normal",INDEX('Cálculos'!$C$14:$F$14,$J11),IF($L11="Habilidade",INDEX('Cálculos'!$C$15:$F$15,$J11),IF($L11="Supremo",INDEX('Cálculos'!$C$16:$F$16,$J11),""))),"")} -> 10 | N11: {=IF(ISNUMBER($J11),IF(ISNUMBER($H11),INDEX(L_Golpes!$F$2:$T$6000,$H11,MAX(1,MIN(15,$M11))),0)+IF($F11="Sim",N(INDEX('Golpes extras'!$E$2:$E$101,MATCH($A11,'Golpes extras'!$A$2:$A$101,0))),0),"")} -> 3.995 | O11: {=IF(ISNUMBER($J11),IF(ISNUMBER($H11),INDEX(L_Golpes!$U$2:$AI$6000,$H11,MAX(1,MIN(15,$M11))),0)+IF($F11="Sim",N(INDEX('Golpes extras'!$F$2:$F$101,MATCH($A11,'Golpes extras'!$A$2:$A$101,0))),0),"")} -> 0 | P11: {=IF(ISNUMBER($J11),IF(ISNUMBER($H11),INDEX(L_Golpes!$AJ$2:$AX$6000,$H11,MAX(1,MIN(15,$M11))),0)+IF($F11="Sim",N(INDEX('Golpes extras'!$G$2:$G$101,MATCH($A11,'Golpes extras'!$A$2:$A$101,0))),0),"")} -> 0 | Q11: {=IF(ISNUMBER($J11),IF(ISNUMBER($H11),INDEX(L_Golpes!$AY$2:$BM$6000,$H11,MAX(1,MIN(15,$M11))),0)+IF($F11="Sim",N(INDEX('Golpes extras'!$H$2:$H$101,MATCH($A11,'Golpes extras'!$A$2:$A$101,0))),0),"")} -> 0 | R11: {=IF(ISNUMBER($J11),INDEX('Cálculos'!$C$19:$F$19,$J11),"")} -> Pyro | S11: =IF(ISNUMBER($J11),IF(AND($C11="Derreter",OR($R11="Pyro",$R11="Cryo")),"Derreter",IF(AND($C11="Vaporizar",OR($R11="Pyro",$R11="Hydro")),"Vaporizar","Nenhuma")),"") -> Nenhuma | T11: =IF(ISNUMBER($J11),IF(OR($D11="Não",$D11=FALSE),'Perfis de buff'!$A$8,IF(OR($D11="",$D11="Sim",$D11=TRUE),'Perfis de buff'!$A$4,$D11)),"") -> Todos | U11: {=IF(ISNUMBER($J11),INDEX('Cálculos'!$C$113:$F$113,$J11)+IF($K11="Normal",INDEX('Cálculos'!$C$114:$F$114,$J11),IF($K11="Carregado",INDEX('Cálculos'!$C$115:$F$115,$J11),IF($K11="Habilidade",INDEX('Cálculos'!$C$116:$F$116,$J11),IF($K11="Supremo",INDEX('Cálculos'!$C$117:$F$117,$J11),0))))+INDEX('Cálculos'!$C$143:$F$147,IFERROR(MATCH($T11,'Perfis de buff'!$A$4:$A$8,0),1),$J11)+IF($K11="Normal",INDEX('Cálculos'!$C$148:$F$152,IFERROR(MATCH($T11,'Perfis de buff'!$A$4:$A$8,0),1),$J11),IF($K11="Carregado",INDEX('Cálculos'!$C$153:$F$157,IFERROR(MATCH($T11,'Perfis de buff'!$A$4:$A$8,0),1),$J11),IF($K11="Habilidade",INDEX('Cálculos'!$C$158:$F$162,IFERROR(MATCH($T11,'Perfis de buff'!$A$4:$A$8,0),1),$J11),IF($K11="Supremo",INDEX('Cálculos'!$C$163:$F$167,IFERROR(MATCH($T11,'Perfis de buff'!$A$4:$A$8,0),1),$J11),0))))+N($E11),"")} -> 1.747 | V11: {=IF(ISNUMBER($J11),INDEX('Cálculos'!$C$180:$F$180,$J11),"")} -> 0.48717949 | W11: {=IF(ISNUMBER($J11),INDEX('Cálculos'!$C$182:$F$182,$J11),"")} -> 1.05 | X11: =IF(ISNUMBER($J11),IF($B11="",1,$B11)*(1+$U11)*$V11*$W11,"") -> 1.4051962 | Y11: =IF(ISNUMBER($J11),$X11*$N11,"") -> 5.6137586 | Z11: =IF(ISNUMBER($J11),$X11*$O11,"") -> 0 | AA11: =IF(ISNUMBER($J11),$X11*$P11,"") -> 0 | AB11: =IF(ISNUMBER($J11),$X11*$Q11,"") -> 0 | AC11: {=IF(ISNUMBER($J11),INDEX('Cálculos'!$C$332:$F$336,IFERROR(MATCH($T11,'Perfis de buff'!$A$4:$A$8,0),1),$J11),"")} -> 5791.25 | AD11: {=IF(ISNUMBER($J11),INDEX('Cálculos'!$C$339:$F$343,IFERROR(MATCH($T11,'Perfis de buff'!$A$4:$A$8,0),1),$J11),"")} -> 424 | AE11: {=IF(ISNUMBER($J11),INDEX('Cálculos'!$C$337:$F$337,$J11),"")} -> 19082.648 | AF11: {=IF(ISNUMBER($J11),INDEX('Cálculos'!$C$338:$F$338,$J11),"")} -> 929.208 | AG11: {=IF(ISNUMBER($J11),IF($S11="Derreter",INDEX('Cálculos'!$C$124:$F$124,$J11)*(1+2.78*$AD11/($AD11+1400)+INDEX('Cálculos'!$C$122:$F$122,$J11)),IF($S11="Vaporizar",INDEX('Cálculos'!$C$125:$F$125,$J11)*(1+2.78*$AD11/($AD11+1400)+INDEX('Cálculos'!$C$123:$F$123,$J11)),1)),"")} -> 1 | AH11: =IF(ISNUMBER($J11),(($AC11*$N11+$AD11*$O11+$AE11*$P11+$AF11*$Q11)*$X11+$AL11)*$AG11,"") -> 32510.68 | AI11: {=IF(ISNUMBER($J11),$AH11*(1+INDEX('Cálculos'!$C$331:$F$331,$J11)),"")} -> 107870.44 | AJ11: {=IF(ISNUMBER($J11),$AH11*(1+MIN(INDEX('Cálculos'!$C$330:$F$330,$J11),1)*INDEX('Cálculos'!$C$331:$F$331,$J11)),"")} -> 107041.48 | AK11: =IF(ISNUMBER($J11),'Fixo (cálculo)'!$AF11,"") -> 0 | AL11: =IF(ISNUMBER($J11),$AK11*(1+$U11)*$V11*$W11,"") -> 0 | AN11: 10.8 s · c
A12: Mavuika - Carregado final no Supremo | B12: 1 | C12: Derreter | D12: Todos | E12: -0.082 | F12: =IF($A12="","",IF(ISNUMBER(MATCH($A12,'Golpes extras'!$A$2:$A$101,0)),"Sim","Não")) -> Sim | G12: {=IF($A12="","",IF($F12="Sim",INDEX('Golpes extras'!$B$2:$B$101,MATCH($A12,'Golpes extras'!$A$2:$A$101,0))&"",$A12))} -> Mavuika - Habilidade: Flamestrider Charged Attack Final DMG | H12: =IF($G12="","",IFERROR(MATCH($G12,L_Golpes!$A$2:$A$6000,0),"")) -> 53 | I12: {=IF($A12="","",IF(ISNUMBER($H12),INDEX(L_Golpes!$B$2:$B$6000,$H12),IF(IFERROR(INDEX('Golpes extras'!$C$2:$C$101,MATCH($A12,'Golpes extras'!$A$2:$A$101,0))&"","")<>"",INDEX('Golpes extras'!$C$2:$C$101,MATCH($A12,'Golpes extras'!$A$2:$A$101,0))&"","golpe?")))} -> Mavuika | J12: =IF(OR($I12="",$I12="golpe?"),"",IFERROR(MATCH($I12,Time!$B$4:$E$4,0),"fora do time")) -> 1 | K12: {=IF(ISNUMBER($J12),IF(IFERROR(INDEX('Golpes extras'!$D$2:$D$101,MATCH($A12,'Golpes extras'!$A$2:$A$101,0))&"","")<>"",INDEX('Golpes extras'!$D$2:$D$101,MATCH($A12,'Golpes extras'!$A$2:$A$101,0))&"",IF(ISNUMBER($H12),INDEX(L_Golpes!$D$2:$D$6000,$H12),"Outro")),"")} -> Carregado | L12: {=IF(ISNUMBER($J12),IF(ISNUMBER($H12),INDEX(L_Golpes!$C$2:$C$6000,$H12),""),"")} -> Habilidade | M12: {=IF(ISNUMBER($J12),IF($L12="Normal",INDEX('Cálculos'!$C$14:$F$14,$J12),IF($L12="Habilidade",INDEX('Cálculos'!$C$15:$F$15,$J12),IF($L12="Supremo",INDEX('Cálculos'!$C$16:$F$16,$J12),""))),"")} -> 10 | N12: {=IF(ISNUMBER($J12),IF(ISNUMBER($H12),INDEX(L_Golpes!$F$2:$T$6000,$H12,MAX(1,MIN(15,$M12))),0)+IF($F12="Sim",N(INDEX('Golpes extras'!$E$2:$E$101,MATCH($A12,'Golpes extras'!$A$2:$A$101,0))),0),"")} -> 4.76 | O12: {=IF(ISNUMBER($J12),IF(ISNUMBER($H12),INDEX(L_Golpes!$U$2:$AI$6000,$H12,MAX(1,MIN(15,$M12))),0)+IF($F12="Sim",N(INDEX('Golpes extras'!$F$2:$F$101,MATCH($A12,'Golpes extras'!$A$2:$A$101,0))),0),"")} -> 0 | P12: {=IF(ISNUMBER($J12),IF(ISNUMBER($H12),INDEX(L_Golpes!$AJ$2:$AX$6000,$H12,MAX(1,MIN(15,$M12))),0)+IF($F12="Sim",N(INDEX('Golpes extras'!$G$2:$G$101,MATCH($A12,'Golpes extras'!$A$2:$A$101,0))),0),"")} -> 0 | Q12: {=IF(ISNUMBER($J12),IF(ISNUMBER($H12),INDEX(L_Golpes!$AY$2:$BM$6000,$H12,MAX(1,MIN(15,$M12))),0)+IF($F12="Sim",N(INDEX('Golpes extras'!$H$2:$H$101,MATCH($A12,'Golpes extras'!$A$2:$A$101,0))),0),"")} -> 0 | R12: {=IF(ISNUMBER($J12),INDEX('Cálculos'!$C$19:$F$19,$J12),"")} -> Pyro | S12: =IF(ISNUMBER($J12),IF(AND($C12="Derreter",OR($R12="Pyro",$R12="Cryo")),"Derreter",IF(AND($C12="Vaporizar",OR($R12="Pyro",$R12="Hydro")),"Vaporizar","Nenhuma")),"") -> Derreter | T12: =IF(ISNUMBER($J12),IF(OR($D12="Não",$D12=FALSE),'Perfis de buff'!$A$8,IF(OR($D12="",$D12="Sim",$D12=TRUE),'Perfis de buff'!$A$4,$D12)),"") -> Todos | U12: {=IF(ISNUMBER($J12),INDEX('Cálculos'!$C$113:$F$113,$J12)+IF($K12="Normal",INDEX('Cálculos'!$C$114:$F$114,$J12),IF($K12="Carregado",INDEX('Cálculos'!$C$115:$F$115,$J12),IF($K12="Habilidade",INDEX('Cálculos'!$C$116:$F$116,$J12),IF($K12="Supremo",INDEX('Cálculos'!$C$117:$F$117,$J12),0))))+INDEX('Cálculos'!$C$143:$F$147,IFERROR(MATCH($T12,'Perfis de buff'!$A$4:$A$8,0),1),$J12)+IF($K12="Normal",INDEX('Cálculos'!$C$148:$F$152,IFERROR(MATCH($T12,'Perfis de buff'!$A$4:$A$8,0),1),$J12),IF($K12="Carregado",INDEX('Cálculos'!$C$153:$F$157,IFERROR(MATCH($T12,'Perfis de buff'!$A$4:$A$8,0),1),$J12),IF($K12="Habilidade",INDEX('Cálculos'!$C$158:$F$162,IFERROR(MATCH($T12,'Perfis de buff'!$A$4:$A$8,0),1),$J12),IF($K12="Supremo",INDEX('Cálculos'!$C$163:$F$167,IFERROR(MATCH($T12,'Perfis de buff'!$A$4:$A$8,0),1),$J12),0))))+N($E12),"")} -> 1.734 | V12: {=IF(ISNUMBER($J12),INDEX('Cálculos'!$C$180:$F$180,$J12),"")} -> 0.48717949 | W12: {=IF(ISNUMBER($J12),INDEX('Cálculos'!$C$182:$F$182,$J12),"")} -> 1.05 | X12: =IF(ISNUMBER($J12),IF($B12="",1,$B12)*(1+$U12)*$V12*$W12,"") -> 1.3985462 | Y12: =IF(ISNUMBER($J12),$X12*$N12,"") -> 6.6570797 | Z12: =IF(ISNUMBER($J12),$X12*$O12,"") -> 0 | AA12: =IF(ISNUMBER($J12),$X12*$P12,"") -> 0 | AB12: =IF(ISNUMBER($J12),$X12*$Q12,"") -> 0 | AC12: {=IF(ISNUMBER($J12),INDEX('Cálculos'!$C$332:$F$336,IFERROR(MATCH($T12,'Perfis de buff'!$A$4:$A$8,0),1),$J12),"")} -> 5791.25 | AD12: {=IF(ISNUMBER($J12),INDEX('Cálculos'!$C$339:$F$343,IFERROR(MATCH($T12,'Perfis de buff'!$A$4:$A$8,0),1),$J12),"")} -> 424 | AE12: {=IF(ISNUMBER($J12),INDEX('Cálculos'!$C$337:$F$337,$J12),"")} -> 19082.648 | AF12: {=IF(ISNUMBER($J12),INDEX('Cálculos'!$C$338:$F$338,$J12),"")} -> 929.208 | AG12: {=IF(ISNUMBER($J12),IF($S12="Derreter",INDEX('Cálculos'!$C$124:$F$124,$J12)*(1+2.78*$AD12/($AD12+1400)+INDEX('Cálculos'!$C$122:$F$122,$J12)),IF($S12="Vaporizar",INDEX('Cálculos'!$C$125:$F$125,$J12)*(1+2.78*$AD12/($AD12+1400)+INDEX('Cálculos'!$C$123:$F$123,$J12)),1)),"")} -> 3.2924561 | AH12: =IF(ISNUMBER($J12),(($AC12*$N12+$AD12*$O12+$AE12*$P12+$AF12*$Q12)*$X12+$AL12)*$AG12,"") -> 126933.45 | AI12: {=IF(ISNUMBER($J12),$AH12*(1+INDEX('Cálculos'!$C$331:$F$331,$J12)),"")} -> 421165.17 | AJ12: {=IF(ISNUMBER($J12),$AH12*(1+MIN(INDEX('Cálculos'!$C$330:$F$330,$J12),1)*INDEX('Cálculos'!$C$331:$F$331,$J12)),"")} -> 417928.62 | AK12: =IF(ISNUMBER($J12),'Fixo (cálculo)'!$AF12,"") -> 0 | AL12: =IF(ISNUMBER($J12),$AK12*(1+$U12)*$V12*$W12,"") -> 0 | AN12: 11.5 s · F
A13: Mavuika - Habilidade: Flamestrider Sprint DMG | B13: 1 | C13: Nenhuma | D13: Todos | E13: -0.095 | F13: =IF($A13="","",IF(ISNUMBER(MATCH($A13,'Golpes extras'!$A$2:$A$101,0)),"Sim","Não")) -> Não | G13: {=IF($A13="","",IF($F13="Sim",INDEX('Golpes extras'!$B$2:$B$101,MATCH($A13,'Golpes extras'!$A$2:$A$101,0))&"",$A13))} -> Mavuika - Habilidade: Flamestrider Sprint DMG | H13: =IF($G13="","",IFERROR(MATCH($G13,L_Golpes!$A$2:$A$6000,0),"")) -> 51 | I13: {=IF($A13="","",IF(ISNUMBER($H13),INDEX(L_Golpes!$B$2:$B$6000,$H13),IF(IFERROR(INDEX('Golpes extras'!$C$2:$C$101,MATCH($A13,'Golpes extras'!$A$2:$A$101,0))&"","")<>"",INDEX('Golpes extras'!$C$2:$C$101,MATCH($A13,'Golpes extras'!$A$2:$A$101,0))&"","golpe?")))} -> Mavuika | J13: =IF(OR($I13="",$I13="golpe?"),"",IFERROR(MATCH($I13,Time!$B$4:$E$4,0),"fora do time")) -> 1 | K13: {=IF(ISNUMBER($J13),IF(IFERROR(INDEX('Golpes extras'!$D$2:$D$101,MATCH($A13,'Golpes extras'!$A$2:$A$101,0))&"","")<>"",INDEX('Golpes extras'!$D$2:$D$101,MATCH($A13,'Golpes extras'!$A$2:$A$101,0))&"",IF(ISNUMBER($H13),INDEX(L_Golpes!$D$2:$D$6000,$H13),"Outro")),"")} -> Habilidade | L13: {=IF(ISNUMBER($J13),IF(ISNUMBER($H13),INDEX(L_Golpes!$C$2:$C$6000,$H13),""),"")} -> Habilidade | M13: {=IF(ISNUMBER($J13),IF($L13="Normal",INDEX('Cálculos'!$C$14:$F$14,$J13),IF($L13="Habilidade",INDEX('Cálculos'!$C$15:$F$15,$J13),IF($L13="Supremo",INDEX('Cálculos'!$C$16:$F$16,$J13),""))),"")} -> 10 | N13: {=IF(ISNUMBER($J13),IF(ISNUMBER($H13),INDEX(L_Golpes!$F$2:$T$6000,$H13,MAX(1,MIN(15,$M13))),0)+IF($F13="Sim",N(INDEX('Golpes extras'!$E$2:$E$101,MATCH($A13,'Golpes extras'!$A$2:$A$101,0))),0),"")} -> 1.598 | O13: {=IF(ISNUMBER($J13),IF(ISNUMBER($H13),INDEX(L_Golpes!$U$2:$AI$6000,$H13,MAX(1,MIN(15,$M13))),0)+IF($F13="Sim",N(INDEX('Golpes extras'!$F$2:$F$101,MATCH($A13,'Golpes extras'!$A$2:$A$101,0))),0),"")} -> 0 | P13: {=IF(ISNUMBER($J13),IF(ISNUMBER($H13),INDEX(L_Golpes!$AJ$2:$AX$6000,$H13,MAX(1,MIN(15,$M13))),0)+IF($F13="Sim",N(INDEX('Golpes extras'!$G$2:$G$101,MATCH($A13,'Golpes extras'!$A$2:$A$101,0))),0),"")} -> 0 | Q13: {=IF(ISNUMBER($J13),IF(ISNUMBER($H13),INDEX(L_Golpes!$AY$2:$BM$6000,$H13,MAX(1,MIN(15,$M13))),0)+IF($F13="Sim",N(INDEX('Golpes extras'!$H$2:$H$101,MATCH($A13,'Golpes extras'!$A$2:$A$101,0))),0),"")} -> 0 | R13: {=IF(ISNUMBER($J13),INDEX('Cálculos'!$C$19:$F$19,$J13),"")} -> Pyro | S13: =IF(ISNUMBER($J13),IF(AND($C13="Derreter",OR($R13="Pyro",$R13="Cryo")),"Derreter",IF(AND($C13="Vaporizar",OR($R13="Pyro",$R13="Hydro")),"Vaporizar","Nenhuma")),"") -> Nenhuma | T13: =IF(ISNUMBER($J13),IF(OR($D13="Não",$D13=FALSE),'Perfis de buff'!$A$8,IF(OR($D13="",$D13="Sim",$D13=TRUE),'Perfis de buff'!$A$4,$D13)),"") -> Todos | U13: {=IF(ISNUMBER($J13),INDEX('Cálculos'!$C$113:$F$113,$J13)+IF($K13="Normal",INDEX('Cálculos'!$C$114:$F$114,$J13),IF($K13="Carregado",INDEX('Cálculos'!$C$115:$F$115,$J13),IF($K13="Habilidade",INDEX('Cálculos'!$C$116:$F$116,$J13),IF($K13="Supremo",INDEX('Cálculos'!$C$117:$F$117,$J13),0))))+INDEX('Cálculos'!$C$143:$F$147,IFERROR(MATCH($T13,'Perfis de buff'!$A$4:$A$8,0),1),$J13)+IF($K13="Normal",INDEX('Cálculos'!$C$148:$F$152,IFERROR(MATCH($T13,'Perfis de buff'!$A$4:$A$8,0),1),$J13),IF($K13="Carregado",INDEX('Cálculos'!$C$153:$F$157,IFERROR(MATCH($T13,'Perfis de buff'!$A$4:$A$8,0),1),$J13),IF($K13="Habilidade",INDEX('Cálculos'!$C$158:$F$162,IFERROR(MATCH($T13,'Perfis de buff'!$A$4:$A$8,0),1),$J13),IF($K13="Supremo",INDEX('Cálculos'!$C$163:$F$167,IFERROR(MATCH($T13,'Perfis de buff'!$A$4:$A$8,0),1),$J13),0))))+N($E13),"")} -> 1.721 | V13: {=IF(ISNUMBER($J13),INDEX('Cálculos'!$C$180:$F$180,$J13),"")} -> 0.48717949 | W13: {=IF(ISNUMBER($J13),INDEX('Cálculos'!$C$182:$F$182,$J13),"")} -> 1.05 | X13: =IF(ISNUMBER($J13),IF($B13="",1,$B13)*(1+$U13)*$V13*$W13,"") -> 1.3918962 | Y13: =IF(ISNUMBER($J13),$X13*$N13,"") -> 2.2242501 | Z13: =IF(ISNUMBER($J13),$X13*$O13,"") -> 0 | AA13: =IF(ISNUMBER($J13),$X13*$P13,"") -> 0 | AB13: =IF(ISNUMBER($J13),$X13*$Q13,"") -> 0 | AC13: {=IF(ISNUMBER($J13),INDEX('Cálculos'!$C$332:$F$336,IFERROR(MATCH($T13,'Perfis de buff'!$A$4:$A$8,0),1),$J13),"")} -> 5791.25 | AD13: {=IF(ISNUMBER($J13),INDEX('Cálculos'!$C$339:$F$343,IFERROR(MATCH($T13,'Perfis de buff'!$A$4:$A$8,0),1),$J13),"")} -> 424 | AE13: {=IF(ISNUMBER($J13),INDEX('Cálculos'!$C$337:$F$337,$J13),"")} -> 19082.648 | AF13: {=IF(ISNUMBER($J13),INDEX('Cálculos'!$C$338:$F$338,$J13),"")} -> 929.208 | AG13: {=IF(ISNUMBER($J13),IF($S13="Derreter",INDEX('Cálculos'!$C$124:$F$124,$J13)*(1+2.78*$AD13/($AD13+1400)+INDEX('Cálculos'!$C$122:$F$122,$J13)),IF($S13="Vaporizar",INDEX('Cálculos'!$C$125:$F$125,$J13)*(1+2.78*$AD13/($AD13+1400)+INDEX('Cálculos'!$C$123:$F$123,$J13)),1)),"")} -> 1 | AH13: =IF(ISNUMBER($J13),(($AC13*$N13+$AD13*$O13+$AE13*$P13+$AF13*$Q13)*$X13+$AL13)*$AG13,"") -> 12881.188 | AI13: {=IF(ISNUMBER($J13),$AH13*(1+INDEX('Cálculos'!$C$331:$F$331,$J13)),"")} -> 42739.782 | AJ13: {=IF(ISNUMBER($J13),$AH13*(1+MIN(INDEX('Cálculos'!$C$330:$F$330,$J13),1)*INDEX('Cálculos'!$C$331:$F$331,$J13)),"")} -> 42411.338 | AK13: =IF(ISNUMBER($J13),'Fixo (cálculo)'!$AF13,"") -> 0 | AL13: =IF(ISNUMBER($J13),$AK13*(1+$U13)*$V13*$W13,"") -> 0 | AN13: 12.1 s · [d
A14: Mavuika - Carregado no Supremo | B14: 1 | C14: Nenhuma | D14: Todos | E14: -0.108 | F14: =IF($A14="","",IF(ISNUMBER(MATCH($A14,'Golpes extras'!$A$2:$A$101,0)),"Sim","Não")) -> Sim | G14: {=IF($A14="","",IF($F14="Sim",INDEX('Golpes extras'!$B$2:$B$101,MATCH($A14,'Golpes extras'!$A$2:$A$101,0))&"",$A14))} -> Mavuika - Habilidade: Flamestrider Charged Attack Cyclic DMG | H14: =IF($G14="","",IFERROR(MATCH($G14,L_Golpes!$A$2:$A$6000,0),"")) -> 52 | I14: {=IF($A14="","",IF(ISNUMBER($H14),INDEX(L_Golpes!$B$2:$B$6000,$H14),IF(IFERROR(INDEX('Golpes extras'!$C$2:$C$101,MATCH($A14,'Golpes extras'!$A$2:$A$101,0))&"","")<>"",INDEX('Golpes extras'!$C$2:$C$101,MATCH($A14,'Golpes extras'!$A$2:$A$101,0))&"","golpe?")))} -> Mavuika | J14: =IF(OR($I14="",$I14="golpe?"),"",IFERROR(MATCH($I14,Time!$B$4:$E$4,0),"fora do time")) -> 1 | K14: {=IF(ISNUMBER($J14),IF(IFERROR(INDEX('Golpes extras'!$D$2:$D$101,MATCH($A14,'Golpes extras'!$A$2:$A$101,0))&"","")<>"",INDEX('Golpes extras'!$D$2:$D$101,MATCH($A14,'Golpes extras'!$A$2:$A$101,0))&"",IF(ISNUMBER($H14),INDEX(L_Golpes!$D$2:$D$6000,$H14),"Outro")),"")} -> Carregado | L14: {=IF(ISNUMBER($J14),IF(ISNUMBER($H14),INDEX(L_Golpes!$C$2:$C$6000,$H14),""),"")} -> Habilidade | M14: {=IF(ISNUMBER($J14),IF($L14="Normal",INDEX('Cálculos'!$C$14:$F$14,$J14),IF($L14="Habilidade",INDEX('Cálculos'!$C$15:$F$15,$J14),IF($L14="Supremo",INDEX('Cálculos'!$C$16:$F$16,$J14),""))),"")} -> 10 | N14: {=IF(ISNUMBER($J14),IF(ISNUMBER($H14),INDEX(L_Golpes!$F$2:$T$6000,$H14,MAX(1,MIN(15,$M14))),0)+IF($F14="Sim",N(INDEX('Golpes extras'!$E$2:$E$101,MATCH($A14,'Golpes extras'!$A$2:$A$101,0))),0),"")} -> 3.995 | O14: {=IF(ISNUMBER($J14),IF(ISNUMBER($H14),INDEX(L_Golpes!$U$2:$AI$6000,$H14,MAX(1,MIN(15,$M14))),0)+IF($F14="Sim",N(INDEX('Golpes extras'!$F$2:$F$101,MATCH($A14,'Golpes extras'!$A$2:$A$101,0))),0),"")} -> 0 | P14: {=IF(ISNUMBER($J14),IF(ISNUMBER($H14),INDEX(L_Golpes!$AJ$2:$AX$6000,$H14,MAX(1,MIN(15,$M14))),0)+IF($F14="Sim",N(INDEX('Golpes extras'!$G$2:$G$101,MATCH($A14,'Golpes extras'!$A$2:$A$101,0))),0),"")} -> 0 | Q14: {=IF(ISNUMBER($J14),IF(ISNUMBER($H14),INDEX(L_Golpes!$AY$2:$BM$6000,$H14,MAX(1,MIN(15,$M14))),0)+IF($F14="Sim",N(INDEX('Golpes extras'!$H$2:$H$101,MATCH($A14,'Golpes extras'!$A$2:$A$101,0))),0),"")} -> 0 | R14: {=IF(ISNUMBER($J14),INDEX('Cálculos'!$C$19:$F$19,$J14),"")} -> Pyro | S14: =IF(ISNUMBER($J14),IF(AND($C14="Derreter",OR($R14="Pyro",$R14="Cryo")),"Derreter",IF(AND($C14="Vaporizar",OR($R14="Pyro",$R14="Hydro")),"Vaporizar","Nenhuma")),"") -> Nenhuma | T14: =IF(ISNUMBER($J14),IF(OR($D14="Não",$D14=FALSE),'Perfis de buff'!$A$8,IF(OR($D14="",$D14="Sim",$D14=TRUE),'Perfis de buff'!$A$4,$D14)),"") -> Todos | U14: {=IF(ISNUMBER($J14),INDEX('Cálculos'!$C$113:$F$113,$J14)+IF($K14="Normal",INDEX('Cálculos'!$C$114:$F$114,$J14),IF($K14="Carregado",INDEX('Cálculos'!$C$115:$F$115,$J14),IF($K14="Habilidade",INDEX('Cálculos'!$C$116:$F$116,$J14),IF($K14="Supremo",INDEX('Cálculos'!$C$117:$F$117,$J14),0))))+INDEX('Cálculos'!$C$143:$F$147,IFERROR(MATCH($T14,'Perfis de buff'!$A$4:$A$8,0),1),$J14)+IF($K14="Normal",INDEX('Cálculos'!$C$148:$F$152,IFERROR(MATCH($T14,'Perfis de buff'!$A$4:$A$8,0),1),$J14),IF($K14="Carregado",INDEX('Cálculos'!$C$153:$F$157,IFERROR(MATCH($T14,'Perfis de buff'!$A$4:$A$8,0),1),$J14),IF($K14="Habilidade",INDEX('Cálculos'!$C$158:$F$162,IFERROR(MATCH($T14,'Perfis de buff'!$A$4:$A$8,0),1),$J14),IF($K14="Supremo",INDEX('Cálculos'!$C$163:$F$167,IFERROR(MATCH($T14,'Perfis de buff'!$A$4:$A$8,0),1),$J14),0))))+N($E14),"")} -> 1.708 | V14: {=IF(ISNUMBER($J14),INDEX('Cálculos'!$C$180:$F$180,$J14),"")} -> 0.48717949 | W14: {=IF(ISNUMBER($J14),INDEX('Cálculos'!$C$182:$F$182,$J14),"")} -> 1.05 | X14: =IF(ISNUMBER($J14),IF($B14="",1,$B14)*(1+$U14)*$V14*$W14,"") -> 1.3852462 | Y14: =IF(ISNUMBER($J14),$X14*$N14,"") -> 5.5340584 | Z14: =IF(ISNUMBER($J14),$X14*$O14,"") -> 0 | AA14: =IF(ISNUMBER($J14),$X14*$P14,"") -> 0 | AB14: =IF(ISNUMBER($J14),$X14*$Q14,"") -> 0 | AC14: {=IF(ISNUMBER($J14),INDEX('Cálculos'!$C$332:$F$336,IFERROR(MATCH($T14,'Perfis de buff'!$A$4:$A$8,0),1),$J14),"")} -> 5791.25 | AD14: {=IF(ISNUMBER($J14),INDEX('Cálculos'!$C$339:$F$343,IFERROR(MATCH($T14,'Perfis de buff'!$A$4:$A$8,0),1),$J14),"")} -> 424 | AE14: {=IF(ISNUMBER($J14),INDEX('Cálculos'!$C$337:$F$337,$J14),"")} -> 19082.648 | AF14: {=IF(ISNUMBER($J14),INDEX('Cálculos'!$C$338:$F$338,$J14),"")} -> 929.208 | AG14: {=IF(ISNUMBER($J14),IF($S14="Derreter",INDEX('Cálculos'!$C$124:$F$124,$J14)*(1+2.78*$AD14/($AD14+1400)+INDEX('Cálculos'!$C$122:$F$122,$J14)),IF($S14="Vaporizar",INDEX('Cálculos'!$C$125:$F$125,$J14)*(1+2.78*$AD14/($AD14+1400)+INDEX('Cálculos'!$C$123:$F$123,$J14)),1)),"")} -> 1 | AH14: =IF(ISNUMBER($J14),(($AC14*$N14+$AD14*$O14+$AE14*$P14+$AF14*$Q14)*$X14+$AL14)*$AG14,"") -> 32049.116 | AI14: {=IF(ISNUMBER($J14),$AH14*(1+INDEX('Cálculos'!$C$331:$F$331,$J14)),"")} -> 106338.97 | AJ14: {=IF(ISNUMBER($J14),$AH14*(1+MIN(INDEX('Cálculos'!$C$330:$F$330,$J14),1)*INDEX('Cálculos'!$C$331:$F$331,$J14)),"")} -> 105521.78 | AK14: =IF(ISNUMBER($J14),'Fixo (cálculo)'!$AF14,"") -> 0 | AL14: =IF(ISNUMBER($J14),$AK14*(1+$U14)*$V14*$W14,"") -> 0 | AN14: 12.8 s · c
A15: Mavuika - Carregado final no Supremo | B15: 1 | C15: Derreter | D15: Todos | E15: -0.121 | F15: =IF($A15="","",IF(ISNUMBER(MATCH($A15,'Golpes extras'!$A$2:$A$101,0)),"Sim","Não")) -> Sim | G15: {=IF($A15="","",IF($F15="Sim",INDEX('Golpes extras'!$B$2:$B$101,MATCH($A15,'Golpes extras'!$A$2:$A$101,0))&"",$A15))} -> Mavuika - Habilidade: Flamestrider Charged Attack Final DMG | H15: =IF($G15="","",IFERROR(MATCH($G15,L_Golpes!$A$2:$A$6000,0),"")) -> 53 | I15: {=IF($A15="","",IF(ISNUMBER($H15),INDEX(L_Golpes!$B$2:$B$6000,$H15),IF(IFERROR(INDEX('Golpes extras'!$C$2:$C$101,MATCH($A15,'Golpes extras'!$A$2:$A$101,0))&"","")<>"",INDEX('Golpes extras'!$C$2:$C$101,MATCH($A15,'Golpes extras'!$A$2:$A$101,0))&"","golpe?")))} -> Mavuika | J15: =IF(OR($I15="",$I15="golpe?"),"",IFERROR(MATCH($I15,Time!$B$4:$E$4,0),"fora do time")) -> 1 | K15: {=IF(ISNUMBER($J15),IF(IFERROR(INDEX('Golpes extras'!$D$2:$D$101,MATCH($A15,'Golpes extras'!$A$2:$A$101,0))&"","")<>"",INDEX('Golpes extras'!$D$2:$D$101,MATCH($A15,'Golpes extras'!$A$2:$A$101,0))&"",IF(ISNUMBER($H15),INDEX(L_Golpes!$D$2:$D$6000,$H15),"Outro")),"")} -> Carregado | L15: {=IF(ISNUMBER($J15),IF(ISNUMBER($H15),INDEX(L_Golpes!$C$2:$C$6000,$H15),""),"")} -> Habilidade | M15: {=IF(ISNUMBER($J15),IF($L15="Normal",INDEX('Cálculos'!$C$14:$F$14,$J15),IF($L15="Habilidade",INDEX('Cálculos'!$C$15:$F$15,$J15),IF($L15="Supremo",INDEX('Cálculos'!$C$16:$F$16,$J15),""))),"")} -> 10 | N15: {=IF(ISNUMBER($J15),IF(ISNUMBER($H15),INDEX(L_Golpes!$F$2:$T$6000,$H15,MAX(1,MIN(15,$M15))),0)+IF($F15="Sim",N(INDEX('Golpes extras'!$E$2:$E$101,MATCH($A15,'Golpes extras'!$A$2:$A$101,0))),0),"")} -> 4.76 | O15: {=IF(ISNUMBER($J15),IF(ISNUMBER($H15),INDEX(L_Golpes!$U$2:$AI$6000,$H15,MAX(1,MIN(15,$M15))),0)+IF($F15="Sim",N(INDEX('Golpes extras'!$F$2:$F$101,MATCH($A15,'Golpes extras'!$A$2:$A$101,0))),0),"")} -> 0 | P15: {=IF(ISNUMBER($J15),IF(ISNUMBER($H15),INDEX(L_Golpes!$AJ$2:$AX$6000,$H15,MAX(1,MIN(15,$M15))),0)+IF($F15="Sim",N(INDEX('Golpes extras'!$G$2:$G$101,MATCH($A15,'Golpes extras'!$A$2:$A$101,0))),0),"")} -> 0 | Q15: {=IF(ISNUMBER($J15),IF(ISNUMBER($H15),INDEX(L_Golpes!$AY$2:$BM$6000,$H15,MAX(1,MIN(15,$M15))),0)+IF($F15="Sim",N(INDEX('Golpes extras'!$H$2:$H$101,MATCH($A15,'Golpes extras'!$A$2:$A$101,0))),0),"")} -> 0 | R15: {=IF(ISNUMBER($J15),INDEX('Cálculos'!$C$19:$F$19,$J15),"")} -> Pyro | S15: =IF(ISNUMBER($J15),IF(AND($C15="Derreter",OR($R15="Pyro",$R15="Cryo")),"Derreter",IF(AND($C15="Vaporizar",OR($R15="Pyro",$R15="Hydro")),"Vaporizar","Nenhuma")),"") -> Derreter | T15: =IF(ISNUMBER($J15),IF(OR($D15="Não",$D15=FALSE),'Perfis de buff'!$A$8,IF(OR($D15="",$D15="Sim",$D15=TRUE),'Perfis de buff'!$A$4,$D15)),"") -> Todos | U15: {=IF(ISNUMBER($J15),INDEX('Cálculos'!$C$113:$F$113,$J15)+IF($K15="Normal",INDEX('Cálculos'!$C$114:$F$114,$J15),IF($K15="Carregado",INDEX('Cálculos'!$C$115:$F$115,$J15),IF($K15="Habilidade",INDEX('Cálculos'!$C$116:$F$116,$J15),IF($K15="Supremo",INDEX('Cálculos'!$C$117:$F$117,$J15),0))))+INDEX('Cálculos'!$C$143:$F$147,IFERROR(MATCH($T15,'Perfis de buff'!$A$4:$A$8,0),1),$J15)+IF($K15="Normal",INDEX('Cálculos'!$C$148:$F$152,IFERROR(MATCH($T15,'Perfis de buff'!$A$4:$A$8,0),1),$J15),IF($K15="Carregado",INDEX('Cálculos'!$C$153:$F$157,IFERROR(MATCH($T15,'Perfis de buff'!$A$4:$A$8,0),1),$J15),IF($K15="Habilidade",INDEX('Cálculos'!$C$158:$F$162,IFERROR(MATCH($T15,'Perfis de buff'!$A$4:$A$8,0),1),$J15),IF($K15="Supremo",INDEX('Cálculos'!$C$163:$F$167,IFERROR(MATCH($T15,'Perfis de buff'!$A$4:$A$8,0),1),$J15),0))))+N($E15),"")} -> 1.695 | V15: {=IF(ISNUMBER($J15),INDEX('Cálculos'!$C$180:$F$180,$J15),"")} -> 0.48717949 | W15: {=IF(ISNUMBER($J15),INDEX('Cálculos'!$C$182:$F$182,$J15),"")} -> 1.05 | X15: =IF(ISNUMBER($J15),IF($B15="",1,$B15)*(1+$U15)*$V15*$W15,"") -> 1.3785962 | Y15: =IF(ISNUMBER($J15),$X15*$N15,"") -> 6.5621177 | Z15: =IF(ISNUMBER($J15),$X15*$O15,"") -> 0 | AA15: =IF(ISNUMBER($J15),$X15*$P15,"") -> 0 | AB15: =IF(ISNUMBER($J15),$X15*$Q15,"") -> 0 | AC15: {=IF(ISNUMBER($J15),INDEX('Cálculos'!$C$332:$F$336,IFERROR(MATCH($T15,'Perfis de buff'!$A$4:$A$8,0),1),$J15),"")} -> 5791.25 | AD15: {=IF(ISNUMBER($J15),INDEX('Cálculos'!$C$339:$F$343,IFERROR(MATCH($T15,'Perfis de buff'!$A$4:$A$8,0),1),$J15),"")} -> 424 | AE15: {=IF(ISNUMBER($J15),INDEX('Cálculos'!$C$337:$F$337,$J15),"")} -> 19082.648 | AF15: {=IF(ISNUMBER($J15),INDEX('Cálculos'!$C$338:$F$338,$J15),"")} -> 929.208 | AG15: {=IF(ISNUMBER($J15),IF($S15="Derreter",INDEX('Cálculos'!$C$124:$F$124,$J15)*(1+2.78*$AD15/($AD15+1400)+INDEX('Cálculos'!$C$122:$F$122,$J15)),IF($S15="Vaporizar",INDEX('Cálculos'!$C$125:$F$125,$J15)*(1+2.78*$AD15/($AD15+1400)+INDEX('Cálculos'!$C$123:$F$123,$J15)),1)),"")} -> 3.2924561 | AH15: =IF(ISNUMBER($J15),(($AC15*$N15+$AD15*$O15+$AE15*$P15+$AF15*$Q15)*$X15+$AL15)*$AG15,"") -> 125122.76 | AI15: {=IF(ISNUMBER($J15),$AH15*(1+INDEX('Cálculos'!$C$331:$F$331,$J15)),"")} -> 415157.33 | AJ15: {=IF(ISNUMBER($J15),$AH15*(1+MIN(INDEX('Cálculos'!$C$330:$F$330,$J15),1)*INDEX('Cálculos'!$C$331:$F$331,$J15)),"")} -> 411966.95 | AK15: =IF(ISNUMBER($J15),'Fixo (cálculo)'!$AF15,"") -> 0 | AL15: =IF(ISNUMBER($J15),$AK15*(1+$U15)*$V15*$W15,"") -> 0 | AN15: 13.5 s · F]
A16: Mavuika - Habilidade: Flamestrider Sprint DMG | B16: 1 | C16: Nenhuma | D16: Todos | E16: -0.134 | F16: =IF($A16="","",IF(ISNUMBER(MATCH($A16,'Golpes extras'!$A$2:$A$101,0)),"Sim","Não")) -> Não | G16: {=IF($A16="","",IF($F16="Sim",INDEX('Golpes extras'!$B$2:$B$101,MATCH($A16,'Golpes extras'!$A$2:$A$101,0))&"",$A16))} -> Mavuika - Habilidade: Flamestrider Sprint DMG | H16: =IF($G16="","",IFERROR(MATCH($G16,L_Golpes!$A$2:$A$6000,0),"")) -> 51 | I16: {=IF($A16="","",IF(ISNUMBER($H16),INDEX(L_Golpes!$B$2:$B$6000,$H16),IF(IFERROR(INDEX('Golpes extras'!$C$2:$C$101,MATCH($A16,'Golpes extras'!$A$2:$A$101,0))&"","")<>"",INDEX('Golpes extras'!$C$2:$C$101,MATCH($A16,'Golpes extras'!$A$2:$A$101,0))&"","golpe?")))} -> Mavuika | J16: =IF(OR($I16="",$I16="golpe?"),"",IFERROR(MATCH($I16,Time!$B$4:$E$4,0),"fora do time")) -> 1 | K16: {=IF(ISNUMBER($J16),IF(IFERROR(INDEX('Golpes extras'!$D$2:$D$101,MATCH($A16,'Golpes extras'!$A$2:$A$101,0))&"","")<>"",INDEX('Golpes extras'!$D$2:$D$101,MATCH($A16,'Golpes extras'!$A$2:$A$101,0))&"",IF(ISNUMBER($H16),INDEX(L_Golpes!$D$2:$D$6000,$H16),"Outro")),"")} -> Habilidade | L16: {=IF(ISNUMBER($J16),IF(ISNUMBER($H16),INDEX(L_Golpes!$C$2:$C$6000,$H16),""),"")} -> Habilidade | M16: {=IF(ISNUMBER($J16),IF($L16="Normal",INDEX('Cálculos'!$C$14:$F$14,$J16),IF($L16="Habilidade",INDEX('Cálculos'!$C$15:$F$15,$J16),IF($L16="Supremo",INDEX('Cálculos'!$C$16:$F$16,$J16),""))),"")} -> 10 | N16: {=IF(ISNUMBER($J16),IF(ISNUMBER($H16),INDEX(L_Golpes!$F$2:$T$6000,$H16,MAX(1,MIN(15,$M16))),0)+IF($F16="Sim",N(INDEX('Golpes extras'!$E$2:$E$101,MATCH($A16,'Golpes extras'!$A$2:$A$101,0))),0),"")} -> 1.598 | O16: {=IF(ISNUMBER($J16),IF(ISNUMBER($H16),INDEX(L_Golpes!$U$2:$AI$6000,$H16,MAX(1,MIN(15,$M16))),0)+IF($F16="Sim",N(INDEX('Golpes extras'!$F$2:$F$101,MATCH($A16,'Golpes extras'!$A$2:$A$101,0))),0),"")} -> 0 | P16: {=IF(ISNUMBER($J16),IF(ISNUMBER($H16),INDEX(L_Golpes!$AJ$2:$AX$6000,$H16,MAX(1,MIN(15,$M16))),0)+IF($F16="Sim",N(INDEX('Golpes extras'!$G$2:$G$101,MATCH($A16,'Golpes extras'!$A$2:$A$101,0))),0),"")} -> 0 | Q16: {=IF(ISNUMBER($J16),IF(ISNUMBER($H16),INDEX(L_Golpes!$AY$2:$BM$6000,$H16,MAX(1,MIN(15,$M16))),0)+IF($F16="Sim",N(INDEX('Golpes extras'!$H$2:$H$101,MATCH($A16,'Golpes extras'!$A$2:$A$101,0))),0),"")} -> 0 | R16: {=IF(ISNUMBER($J16),INDEX('Cálculos'!$C$19:$F$19,$J16),"")} -> Pyro | S16: =IF(ISNUMBER($J16),IF(AND($C16="Derreter",OR($R16="Pyro",$R16="Cryo")),"Derreter",IF(AND($C16="Vaporizar",OR($R16="Pyro",$R16="Hydro")),"Vaporizar","Nenhuma")),"") -> Nenhuma | T16: =IF(ISNUMBER($J16),IF(OR($D16="Não",$D16=FALSE),'Perfis de buff'!$A$8,IF(OR($D16="",$D16="Sim",$D16=TRUE),'Perfis de buff'!$A$4,$D16)),"") -> Todos | U16: {=IF(ISNUMBER($J16),INDEX('Cálculos'!$C$113:$F$113,$J16)+IF($K16="Normal",INDEX('Cálculos'!$C$114:$F$114,$J16),IF($K16="Carregado",INDEX('Cálculos'!$C$115:$F$115,$J16),IF($K16="Habilidade",INDEX('Cálculos'!$C$116:$F$116,$J16),IF($K16="Supremo",INDEX('Cálculos'!$C$117:$F$117,$J16),0))))+INDEX('Cálculos'!$C$143:$F$147,IFERROR(MATCH($T16,'Perfis de buff'!$A$4:$A$8,0),1),$J16)+IF($K16="Normal",INDEX('Cálculos'!$C$148:$F$152,IFERROR(MATCH($T16,'Perfis de buff'!$A$4:$A$8,0),1),$J16),IF($K16="Carregado",INDEX('Cálculos'!$C$153:$F$157,IFERROR(MATCH($T16,'Perfis de buff'!$A$4:$A$8,0),1),$J16),IF($K16="Habilidade",INDEX('Cálculos'!$C$158:$F$162,IFERROR(MATCH($T16,'Perfis de buff'!$A$4:$A$8,0),1),$J16),IF($K16="Supremo",INDEX('Cálculos'!$C$163:$F$167,IFERROR(MATCH($T16,'Perfis de buff'!$A$4:$A$8,0),1),$J16),0))))+N($E16),"")} -> 1.682 | V16: {=IF(ISNUMBER($J16),INDEX('Cálculos'!$C$180:$F$180,$J16),"")} -> 0.48717949 | W16: {=IF(ISNUMBER($J16),INDEX('Cálculos'!$C$182:$F$182,$J16),"")} -> 1.05 | X16: =IF(ISNUMBER($J16),IF($B16="",1,$B16)*(1+$U16)*$V16*$W16,"") -> 1.3719462 | Y16: =IF(ISNUMBER($J16),$X16*$N16,"") -> 2.19237 | Z16: =IF(ISNUMBER($J16),$X16*$O16,"") -> 0 | AA16: =IF(ISNUMBER($J16),$X16*$P16,"") -> 0 | AB16: =IF(ISNUMBER($J16),$X16*$Q16,"") -> 0 | AC16: {=IF(ISNUMBER($J16),INDEX('Cálculos'!$C$332:$F$336,IFERROR(MATCH($T16,'Perfis de buff'!$A$4:$A$8,0),1),$J16),"")} -> 5791.25 | AD16: {=IF(ISNUMBER($J16),INDEX('Cálculos'!$C$339:$F$343,IFERROR(MATCH($T16,'Perfis de buff'!$A$4:$A$8,0),1),$J16),"")} -> 424 | AE16: {=IF(ISNUMBER($J16),INDEX('Cálculos'!$C$337:$F$337,$J16),"")} -> 19082.648 | AF16: {=IF(ISNUMBER($J16),INDEX('Cálculos'!$C$338:$F$338,$J16),"")} -> 929.208 | AG16: {=IF(ISNUMBER($J16),IF($S16="Derreter",INDEX('Cálculos'!$C$124:$F$124,$J16)*(1+2.78*$AD16/($AD16+1400)+INDEX('Cálculos'!$C$122:$F$122,$J16)),IF($S16="Vaporizar",INDEX('Cálculos'!$C$125:$F$125,$J16)*(1+2.78*$AD16/($AD16+1400)+INDEX('Cálculos'!$C$123:$F$123,$J16)),1)),"")} -> 1 | AH16: =IF(ISNUMBER($J16),(($AC16*$N16+$AD16*$O16+$AE16*$P16+$AF16*$Q16)*$X16+$AL16)*$AG16,"") -> 12696.562 | AI16: {=IF(ISNUMBER($J16),$AH16*(1+INDEX('Cálculos'!$C$331:$F$331,$J16)),"")} -> 42127.194 | AJ16: {=IF(ISNUMBER($J16),$AH16*(1+MIN(INDEX('Cálculos'!$C$330:$F$330,$J16),1)*INDEX('Cálculos'!$C$331:$F$331,$J16)),"")} -> 41803.457 | AK16: =IF(ISNUMBER($J16),'Fixo (cálculo)'!$AF16,"") -> 0 | AL16: =IF(ISNUMBER($J16),$AK16*(1+$U16)*$V16*$W16,"") -> 0 | AN16: 14.1 s · [d
... A21: Mavuika - Habilidade: Flamestrider Charged Attack Final DMG | B21: 1 | C21: Derreter | D21: Final | E21: -0.2 | F21: =IF($A21="","",IF(ISNUMBER(MATCH($A21,'Golpes extras'!$A$2:$A$101,0)),"Sim","Não")) -> Não | G21: {=IF($A21="","",IF($F21="Sim",INDEX('Golpes extras'!$B$2:$B$101,MATCH($A21,'Golpes extras'!$A$2:$A$101,0))&"",$A21))} -> Mavuika - Habilidade: Flamestrider Charged Attack Final DMG | H21: =IF($G21="","",IFERROR(MATCH($G21,L_Golpes!$A$2:$A$6000,0),"")) -> 53 | I21: {=IF($A21="","",IF(ISNUMBER($H21),INDEX(L_Golpes!$B$2:$B$6000,$H21),IF(IFERROR(INDEX('Golpes extras'!$C$2:$C$101,MATCH($A21,'Golpes extras'!$A$2:$A$101,0))&"","")<>"",INDEX('Golpes extras'!$C$2:$C$101,MATCH($A21,'Golpes extras'!$A$2:$A$101,0))&"","golpe?")))} -> Mavuika | J21: =IF(OR($I21="",$I21="golpe?"),"",IFERROR(MATCH($I21,Time!$B$4:$E$4,0),"fora do time")) -> 1 | K21: {=IF(ISNUMBER($J21),IF(IFERROR(INDEX('Golpes extras'!$D$2:$D$101,MATCH($A21,'Golpes extras'!$A$2:$A$101,0))&"","")<>"",INDEX('Golpes extras'!$D$2:$D$101,MATCH($A21,'Golpes extras'!$A$2:$A$101,0))&"",IF(ISNUMBER($H21),INDEX(L_Golpes!$D$2:$D$6000,$H21),"Outro")),"")} -> Carregado | L21: {=IF(ISNUMBER($J21),IF(ISNUMBER($H21),INDEX(L_Golpes!$C$2:$C$6000,$H21),""),"")} -> Habilidade | M21: {=IF(ISNUMBER($J21),IF($L21="Normal",INDEX('Cálculos'!$C$14:$F$14,$J21),IF($L21="Habilidade",INDEX('Cálculos'!$C$15:$F$15,$J21),IF($L21="Supremo",INDEX('Cálculos'!$C$16:$F$16,$J21),""))),"")} -> 10 | N21: {=IF(ISNUMBER($J21),IF(ISNUMBER($H21),INDEX(L_Golpes!$F$2:$T$6000,$H21,MAX(1,MIN(15,$M21))),0)+IF($F21="Sim",N(INDEX('Golpes extras'!$E$2:$E$101,MATCH($A21,'Golpes extras'!$A$2:$A$101,0))),0),"")} -> 2.72 | O21: {=IF(ISNUMBER($J21),IF(ISNUMBER($H21),INDEX(L_Golpes!$U$2:$AI$6000,$H21,MAX(1,MIN(15,$M21))),0)+IF($F21="Sim",N(INDEX('Golpes extras'!$F$2:$F$101,MATCH($A21,'Golpes extras'!$A$2:$A$101,0))),0),"")} -> 0 | P21: {=IF(ISNUMBER($J21),IF(ISNUMBER($H21),INDEX(L_Golpes!$AJ$2:$AX$6000,$H21,MAX(1,MIN(15,$M21))),0)+IF($F21="Sim",N(INDEX('Golpes extras'!$G$2:$G$101,MATCH($A21,'Golpes extras'!$A$2:$A$101,0))),0),"")} -> 0 | Q21: {=IF(ISNUMBER($J21),IF(ISNUMBER($H21),INDEX(L_Golpes!$AY$2:$BM$6000,$H21,MAX(1,MIN(15,$M21))),0)+IF($F21="Sim",N(INDEX('Golpes extras'!$H$2:$H$101,MATCH($A21,'Golpes extras'!$A$2:$A$101,0))),0),"")} -> 0 | R21: {=IF(ISNUMBER($J21),INDEX('Cálculos'!$C$19:$F$19,$J21),"")} -> Pyro | S21: =IF(ISNUMBER($J21),IF(AND($C21="Derreter",OR($R21="Pyro",$R21="Cryo")),"Derreter",IF(AND($C21="Vaporizar",OR($R21="Pyro",$R21="Hydro")),"Vaporizar","Nenhuma")),"") -> Derreter | T21: =IF(ISNUMBER($J21),IF(OR($D21="Não",$D21=FALSE),'Perfis de buff'!$A$8,IF(OR($D21="",$D21="Sim",$D21=TRUE),'Perfis de buff'!$A$4,$D21)),"") -> Final | U21: {=IF(ISNUMBER($J21),INDEX('Cálculos'!$C$113:$F$113,$J21)+IF($K21="Normal",INDEX('Cálculos'!$C$114:$F$114,$J21),IF($K21="Carregado",INDEX('Cálculos'!$C$115:$F$115,$J21),IF($K21="Habilidade",INDEX('Cálculos'!$C$116:$F$116,$J21),IF($K21="Supremo",INDEX('Cálculos'!$C$117:$F$117,$J21),0))))+INDEX('Cálculos'!$C$143:$F$147,IFERROR(MATCH($T21,'Perfis de buff'!$A$4:$A$8,0),1),$J21)+IF($K21="Normal",INDEX('Cálculos'!$C$148:$F$152,IFERROR(MATCH($T21,'Perfis de buff'!$A$4:$A$8,0),1),$J21),IF($K21="Carregado",INDEX('Cálculos'!$C$153:$F$157,IFERROR(MATCH($T21,'Perfis de buff'!$A$4:$A$8,0),1),$J21),IF($K21="Habilidade",INDEX('Cálculos'!$C$158:$F$162,IFERROR(MATCH($T21,'Perfis de buff'!$A$4:$A$8,0),1),$J21),IF($K21="Supremo",INDEX('Cálculos'!$C$163:$F$167,IFERROR(MATCH($T21,'Perfis de buff'!$A$4:$A$8,0),1),$J21),0))))+N($E21),"")} -> 1.616 | V21: {=IF(ISNUMBER($J21),INDEX('Cálculos'!$C$180:$F$180,$J21),"")} -> 0.48717949 | W21: {=IF(ISNUMBER($J21),INDEX('Cálculos'!$C$182:$F$182,$J21),"")} -> 1.05 | X21: =IF(ISNUMBER($J21),IF($B21="",1,$B21)*(1+$U21)*$V21*$W21,"") -> 1.3381846 | Y21: =IF(ISNUMBER($J21),$X21*$N21,"") -> 3.6398622 | Z21: =IF(ISNUMBER($J21),$X21*$O21,"") -> 0 | AA21: =IF(ISNUMBER($J21),$X21*$P21,"") -> 0 | AB21: =IF(ISNUMBER($J21),$X21*$Q21,"") -> 0 | AC21: {=IF(ISNUMBER($J21),INDEX('Cálculos'!$C$332:$F$336,IFERROR(MATCH($T21,'Perfis de buff'!$A$4:$A$8,0),1),$J21),"")} -> 4233.25 | AD21: {=IF(ISNUMBER($J21),INDEX('Cálculos'!$C$339:$F$343,IFERROR(MATCH($T21,'Perfis de buff'!$A$4:$A$8,0),1),$J21),"")} -> 424 | AE21: {=IF(ISNUMBER($J21),INDEX('Cálculos'!$C$337:$F$337,$J21),"")} -> 19082.648 | AF21: {=IF(ISNUMBER($J21),INDEX('Cálculos'!$C$338:$F$338,$J21),"")} -> 929.208 | AG21: {=IF(ISNUMBER($J21),IF($S21="Derreter",INDEX('Cálculos'!$C$124:$F$124,$J21)*(1+2.78*$AD21/($AD21+1400)+INDEX('Cálculos'!$C$122:$F$122,$J21)),IF($S21="Vaporizar",INDEX('Cálculos'!$C$125:$F$125,$J21)*(1+2.78*$AD21/($AD21+1400)+INDEX('Cálculos'!$C$123:$F$123,$J21)),1)),"")} -> 3.2924561 | AH21: =IF(ISNUMBER($J21),(($AC21*$N21+$AD21*$O21+$AE21*$P21+$AF21*$Q21)*$X21+$AL21)*$AG21,"") -> 50731.634 | AI21: {=IF(ISNUMBER($J21),$AH21*(1+INDEX('Cálculos'!$C$331:$F$331,$J21)),"")} -> 168327.56 | AJ21: {=IF(ISNUMBER($J21),$AH21*(1+MIN(INDEX('Cálculos'!$C$330:$F$330,$J21),1)*INDEX('Cálculos'!$C$331:$F$331,$J21)),"")} -> 167034.01 | AK21: =IF(ISNUMBER($J21),'Fixo (cálculo)'!$AF21,"") -> 0 | AL21: =IF(ISNUMBER($J21),$AK21*(1+$U21)*$V21*$W21,"") -> 0 | AN21: 17.4 s · F]
A22: Citlali - Obsidian Tzitzimitl (+EM) | B22: 1 | C22: Derreter | D22: Todos | F22: =IF($A22="","",IF(ISNUMBER(MATCH($A22,'Golpes extras'!$A$2:$A$101,0)),"Sim","Não")) -> Sim | G22: {=IF($A22="","",IF($F22="Sim",INDEX('Golpes extras'!$B$2:$B$101,MATCH($A22,'Golpes extras'!$A$2:$A$101,0))&"",$A22))} -> Citlali - Habilidade: Obsidian Tzitzimitl DMG | H22: =IF($G22="","",IFERROR(MATCH($G22,L_Golpes!$A$2:$A$6000,0),"")) -> 22 | I22: {=IF($A22="","",IF(ISNUMBER($H22),INDEX(L_Golpes!$B$2:$B$6000,$H22),IF(IFERROR(INDEX('Golpes extras'!$C$2:$C$101,MATCH($A22,'Golpes extras'!$A$2:$A$101,0))&"","")<>"",INDEX('Golpes extras'!$C$2:$C$101,MATCH($A22,'Golpes extras'!$A$2:$A$101,0))&"","golpe?")))} -> Citlali | J22: =IF(OR($I22="",$I22="golpe?"),"",IFERROR(MATCH($I22,Time!$B$4:$E$4,0),"fora do time")) -> 2 | K22: {=IF(ISNUMBER($J22),IF(IFERROR(INDEX('Golpes extras'!$D$2:$D$101,MATCH($A22,'Golpes extras'!$A$2:$A$101,0))&"","")<>"",INDEX('Golpes extras'!$D$2:$D$101,MATCH($A22,'Golpes extras'!$A$2:$A$101,0))&"",IF(ISNUMBER($H22),INDEX(L_Golpes!$D$2:$D$6000,$H22),"Outro")),"")} -> Habilidade | L22: {=IF(ISNUMBER($J22),IF(ISNUMBER($H22),INDEX(L_Golpes!$C$2:$C$6000,$H22),""),"")} -> Habilidade | M22: {=IF(ISNUMBER($J22),IF($L22="Normal",INDEX('Cálculos'!$C$14:$F$14,$J22),IF($L22="Habilidade",INDEX('Cálculos'!$C$15:$F$15,$J22),IF($L22="Supremo",INDEX('Cálculos'!$C$16:$F$16,$J22),""))),"")} -> 10 | N22: {=IF(ISNUMBER($J22),IF(ISNUMBER($H22),INDEX(L_Golpes!$F$2:$T$6000,$H22,MAX(1,MIN(15,$M22))),0)+IF($F22="Sim",N(INDEX('Golpes extras'!$E$2:$E$101,MATCH($A22,'Golpes extras'!$A$2:$A$101,0))),0),"")} -> 1.3133 | O22: {=IF(ISNUMBER($J22),IF(ISNUMBER($H22),INDEX(L_Golpes!$U$2:$AI$6000,$H22,MAX(1,MIN(15,$M22))),0)+IF($F22="Sim",N(INDEX('Golpes extras'!$F$2:$F$101,MATCH($A22,'Golpes extras'!$A$2:$A$101,0))),0),"")} -> 0 | P22: {=IF(ISNUMBER($J22),IF(ISNUMBER($H22),INDEX(L_Golpes!$AJ$2:$AX$6000,$H22,MAX(1,MIN(15,$M22))),0)+IF($F22="Sim",N(INDEX('Golpes extras'!$G$2:$G$101,MATCH($A22,'Golpes extras'!$A$2:$A$101,0))),0),"")} -> 0 | Q22: {=IF(ISNUMBER($J22),IF(ISNUMBER($H22),INDEX(L_Golpes!$AY$2:$BM$6000,$H22,MAX(1,MIN(15,$M22))),0)+IF($F22="Sim",N(INDEX('Golpes extras'!$H$2:$H$101,MATCH($A22,'Golpes extras'!$A$2:$A$101,0))),0),"")} -> 0 | R22: {=IF(ISNUMBER($J22),INDEX('Cálculos'!$C$19:$F$19,$J22),"")} -> Cryo | S22: =IF(ISNUMBER($J22),IF(AND($C22="Derreter",OR($R22="Pyro",$R22="Cryo")),"Derreter",IF(AND($C22="Vaporizar",OR($R22="Pyro",$R22="Hydro")),"Vaporizar","Nenhuma")),"") -> Derreter | T22: =IF(ISNUMBER($J22),IF(OR($D22="Não",$D22=FALSE),'Perfis de buff'!$A$8,IF(OR($D22="",$D22="Sim",$D22=TRUE),'Perfis de buff'!$A$4,$D22)),"") -> Todos | U22: {=IF(ISNUMBER($J22),INDEX('Cálculos'!$C$113:$F$113,$J22)+IF($K22="Normal",INDEX('Cálculos'!$C$114:$F$114,$J22),IF($K22="Carregado",INDEX('Cálculos'!$C$115:$F$115,$J22),IF($K22="Habilidade",INDEX('Cálculos'!$C$116:$F$116,$J22),IF($K22="Supremo",INDEX('Cálculos'!$C$117:$F$117,$J22),0))))+INDEX('Cálculos'!$C$143:$F$147,IFERROR(MATCH($T22,'Perfis de buff'!$A$4:$A$8,0),1),$J22)+IF($K22="Normal",INDEX('Cálculos'!$C$148:$F$152,IFERROR(MATCH($T22,'Perfis de buff'!$A$4:$A$8,0),1),$J22),IF($K22="Carregado",INDEX('Cálculos'!$C$153:$F$157,IFERROR(MATCH($T22,'Perfis de buff'!$A$4:$A$8,0),1),$J22),IF($K22="Habilidade",INDEX('Cálculos'!$C$158:$F$162,IFERROR(MATCH($T22,'Perfis de buff'!$A$4:$A$8,0),1),$J22),IF($K22="Supremo",INDEX('Cálculos'!$C$163:$F$167,IFERROR(MATCH($T22,'Perfis de buff'!$A$4:$A$8,0),1),$J22),0))))+N($E22),"")} -> 0.348 | V22: {=IF(ISNUMBER($J22),INDEX('Cálculos'!$C$180:$F$180,$J22),"")} -> 0.48717949 | W22: {=IF(ISNUMBER($J22),INDEX('Cálculos'!$C$182:$F$182,$J22),"")} -> 0.9 | X22: =IF(ISNUMBER($J22),IF($B22="",1,$B22)*(1+$U22)*$V22*$W22,"") -> 0.59104615 | Y22: =IF(ISNUMBER($J22),$X22*$N22,"") -> 0.77622091 | Z22: =IF(ISNUMBER($J22),$X22*$O22,"") -> 0 | AA22: =IF(ISNUMBER($J22),$X22*$P22,"") -> 0 | AB22: =IF(ISNUMBER($J22),$X22*$Q22,"") -> 0 | AC22: {=IF(ISNUMBER($J22),INDEX('Cálculos'!$C$332:$F$336,IFERROR(MATCH($T22,'Perfis de buff'!$A$4:$A$8,0),1),$J22),"")} -> 3241.7343 | AD22: {=IF(ISNUMBER($J22),INDEX('Cálculos'!$C$339:$F$343,IFERROR(MATCH($T22,'Perfis de buff'!$A$4:$A$8,0),1),$J22),"")} -> 348.49081 | AE22: {=IF(ISNUMBER($J22),INDEX('Cálculos'!$C$337:$F$337,$J22),"")} -> 20708.65 | AF22: {=IF(ISNUMBER($J22),INDEX('Cálculos'!$C$338:$F$338,$J22),"")} -> 876.60154 | AG22: {=IF(ISNUMBER($J22),IF($S22="Derreter",INDEX('Cálculos'!$C$124:$F$124,$J22)*(1+2.78*$AD22/($AD22+1400)+INDEX('Cálculos'!$C$122:$F$122,$J22)),IF($S22="Vaporizar",INDEX('Cálculos'!$C$125:$F$125,$J22)*(1+2.78*$AD22/($AD22+1400)+INDEX('Cálculos'!$C$123:$F$123,$J22)),1)),"")} -> 2.3311206 | AH22: =IF(ISNUMBER($J22),(($AC22*$N22+$AD22*$O22+$AE22*$P22+$AF22*$Q22)*$X22+$AL22)*$AG22,"") -> 5865.8033 | AI22: {=IF(ISNUMBER($J22),$AH22*(1+INDEX('Cálculos'!$C$331:$F$331,$J22)),"")} -> 11430.643 | AJ22: {=IF(ISNUMBER($J22),$AH22*(1+MIN(INDEX('Cálculos'!$C$330:$F$330,$J22),1)*INDEX('Cálculos'!$C$331:$F$331,$J22)),"")} -> 8526.0075 | AK22: =IF(ISNUMBER($J22),'Fixo (cálculo)'!$AF22,"") -> 0 | AL22: =IF(ISNUMBER($J22),$AK22*(1+$U22)*$V22*$W22,"") -> 0 | AN22: Citlali E
A23: Citlali - Frostfall Storm (+EM) | B23: 8 | C23: Nenhuma | D23: Todos | F23: =IF($A23="","",IF(ISNUMBER(MATCH($A23,'Golpes extras'!$A$2:$A$101,0)),"Sim","Não")) -> Sim | G23: {=IF($A23="","",IF($F23="Sim",INDEX('Golpes extras'!$B$2:$B$101,MATCH($A23,'Golpes extras'!$A$2:$A$101,0))&"",$A23))} -> Citlali - Habilidade: Frostfall Storm DMG | H23: =IF($G23="","",IFERROR(MATCH($G23,L_Golpes!$A$2:$A$6000,0),"")) -> 23 | I23: {=IF($A23="","",IF(ISNUMBER($H23),INDEX(L_Golpes!$B$2:$B$6000,$H23),IF(IFERROR(INDEX('Golpes extras'!$C$2:$C$101,MATCH($A23,'Golpes extras'!$A$2:$A$101,0))&"","")<>"",INDEX('Golpes extras'!$C$2:$C$101,MATCH($A23,'Golpes extras'!$A$2:$A$101,0))&"","golpe?")))} -> Citlali | J23: =IF(OR($I23="",$I23="golpe?"),"",IFERROR(MATCH($I23,Time!$B$4:$E$4,0),"fora do time")) -> 2 | K23: {=IF(ISNUMBER($J23),IF(IFERROR(INDEX('Golpes extras'!$D$2:$D$101,MATCH($A23,'Golpes extras'!$A$2:$A$101,0))&"","")<>"",INDEX('Golpes extras'!$D$2:$D$101,MATCH($A23,'Golpes extras'!$A$2:$A$101,0))&"",IF(ISNUMBER($H23),INDEX(L_Golpes!$D$2:$D$6000,$H23),"Outro")),"")} -> Habilidade | L23: {=IF(ISNUMBER($J23),IF(ISNUMBER($H23),INDEX(L_Golpes!$C$2:$C$6000,$H23),""),"")} -> Habilidade | M23: {=IF(ISNUMBER($J23),IF($L23="Normal",INDEX('Cálculos'!$C$14:$F$14,$J23),IF($L23="Habilidade",INDEX('Cálculos'!$C$15:$F$15,$J23),IF($L23="Supremo",INDEX('Cálculos'!$C$16:$F$16,$J23),""))),"")} -> 10 | N23: {=IF(ISNUMBER($J23),IF(ISNUMBER($H23),INDEX(L_Golpes!$F$2:$T$6000,$H23,MAX(1,MIN(15,$M23))),0)+IF($F23="Sim",N(INDEX('Golpes extras'!$E$2:$E$101,MATCH($A23,'Golpes extras'!$A$2:$A$101,0))),0),"")} -> 0.3064 | O23: {=IF(ISNUMBER($J23),IF(ISNUMBER($H23),INDEX(L_Golpes!$U$2:$AI$6000,$H23,MAX(1,MIN(15,$M23))),0)+IF($F23="Sim",N(INDEX('Golpes extras'!$F$2:$F$101,MATCH($A23,'Golpes extras'!$A$2:$A$101,0))),0),"")} -> 0.9 | P23: {=IF(ISNUMBER($J23),IF(ISNUMBER($H23),INDEX(L_Golpes!$AJ$2:$AX$6000,$H23,MAX(1,MIN(15,$M23))),0)+IF($F23="Sim",N(INDEX('Golpes extras'!$G$2:$G$101,MATCH($A23,'Golpes extras'!$A$2:$A$101,0))),0),"")} -> 0 | Q23: {=IF(ISNUMBER($J23),IF(ISNUMBER($H23),INDEX(L_Golpes!$AY$2:$BM$6000,$H23,MAX(1,MIN(15,$M23))),0)+IF($F23="Sim",N(INDEX('Golpes extras'!$H$2:$H$101,MATCH($A23,'Golpes extras'!$A$2:$A$101,0))),0),"")} -> 0 | R23: {=IF(ISNUMBER($J23),INDEX('Cálculos'!$C$19:$F$19,$J23),"")} -> Cryo | S23: =IF(ISNUMBER($J23),IF(AND($C23="Derreter",OR($R23="Pyro",$R23="Cryo")),"Derreter",IF(AND($C23="Vaporizar",OR($R23="Pyro",$R23="Hydro")),"Vaporizar","Nenhuma")),"") -> Nenhuma | T23: =IF(ISNUMBER($J23),IF(OR($D23="Não",$D23=FALSE),'Perfis de buff'!$A$8,IF(OR($D23="",$D23="Sim",$D23=TRUE),'Perfis de buff'!$A$4,$D23)),"") -> Todos | U23: {=IF(ISNUMBER($J23),INDEX('Cálculos'!$C$113:$F$113,$J23)+IF($K23="Normal",INDEX('Cálculos'!$C$114:$F$114,$J23),IF($K23="Carregado",INDEX('Cálculos'!$C$115:$F$115,$J23),IF($K23="Habilidade",INDEX('Cálculos'!$C$116:$F$116,$J23),IF($K23="Supremo",INDEX('Cálculos'!$C$117:$F$117,$J23),0))))+INDEX('Cálculos'!$C$143:$F$147,IFERROR(MATCH($T23,'Perfis de buff'!$A$4:$A$8,0),1),$J23)+IF($K23="Normal",INDEX('Cálculos'!$C$148:$F$152,IFERROR(MATCH($T23,'Perfis de buff'!$A$4:$A$8,0),1),$J23),IF($K23="Carregado",INDEX('Cálculos'!$C$153:$F$157,IFERROR(MATCH($T23,'Perfis de buff'!$A$4:$A$8,0),1),$J23),IF($K23="Habilidade",INDEX('Cálculos'!$C$158:$F$162,IFERROR(MATCH($T23,'Perfis de buff'!$A$4:$A$8,0),1),$J23),IF($K23="Supremo",INDEX('Cálculos'!$C$163:$F$167,IFERROR(MATCH($T23,'Perfis de buff'!$A$4:$A$8,0),1),$J23),0))))+N($E23),"")} -> 0.348 | V23: {=IF(ISNUMBER($J23),INDEX('Cálculos'!$C$180:$F$180,$J23),"")} -> 0.48717949 | W23: {=IF(ISNUMBER($J23),INDEX('Cálculos'!$C$182:$F$182,$J23),"")} -> 0.9 | X23: =IF(ISNUMBER($J23),IF($B23="",1,$B23)*(1+$U23)*$V23*$W23,"") -> 4.7283692 | Y23: =IF(ISNUMBER($J23),$X23*$N23,"") -> 1.4487723 | Z23: =IF(ISNUMBER($J23),$X23*$O23,"") -> 4.2555323 | AA23: =IF(ISNUMBER($J23),$X23*$P23,"") -> 0 | AB23: =IF(ISNUMBER($J23),$X23*$Q23,"") -> 0 | AC23: {=IF(ISNUMBER($J23),INDEX('Cálculos'!$C$332:$F$336,IFERROR(MATCH($T23,'Perfis de buff'!$A$4:$A$8,0),1),$J23),"")} -> 3241.7343 | AD23: {=IF(ISNUMBER($J23),INDEX('Cálculos'!$C$339:$F$343,IFERROR(MATCH($T23,'Perfis de buff'!$A$4:$A$8,0),1),$J23),"")} -> 348.49081 | AE23: {=IF(ISNUMBER($J23),INDEX('Cálculos'!$C$337:$F$337,$J23),"")} -> 20708.65 | AF23: {=IF(ISNUMBER($J23),INDEX('Cálculos'!$C$338:$F$338,$J23),"")} -> 876.60154 | AG23: {=IF(ISNUMBER($J23),IF($S23="Derreter",INDEX('Cálculos'!$C$124:$F$124,$J23)*(1+2.78*$AD23/($AD23+1400)+INDEX('Cálculos'!$C$122:$F$122,$J23)),IF($S23="Vaporizar",INDEX('Cálculos'!$C$125:$F$125,$J23)*(1+2.78*$AD23/($AD23+1400)+INDEX('Cálculos'!$C$123:$F$123,$J23)),1)),"")} -> 1 | AH23: =IF(ISNUMBER($J23),(($AC23*$N23+$AD23*$O23+$AE23*$P23+$AF23*$Q23)*$X23+$AL23)*$AG23,"") -> 6179.5489 | AI23: {=IF(ISNUMBER($J23),$AH23*(1+INDEX('Cálculos'!$C$331:$F$331,$J23)),"")} -> 12042.037 | AJ23: {=IF(ISNUMBER($J23),$AH23*(1+MIN(INDEX('Cálculos'!$C$330:$F$330,$J23),1)*INDEX('Cálculos'!$C$331:$F$331,$J23)),"")} -> 8982.04 | AK23: =IF(ISNUMBER($J23),'Fixo (cálculo)'!$AF23,"") -> 0 | AL23: =IF(ISNUMBER($J23),$AK23*(1+$U23)*$V23*$W23,"") -> 0
A24: Citlali - Ice Storm (+EM) | B24: 1 | C24: Derreter | D24: Todos | F24: =IF($A24="","",IF(ISNUMBER(MATCH($A24,'Golpes extras'!$A$2:$A$101,0)),"Sim","Não")) -> Sim | G24: {=IF($A24="","",IF($F24="Sim",INDEX('Golpes extras'!$B$2:$B$101,MATCH($A24,'Golpes extras'!$A$2:$A$101,0))&"",$A24))} -> Citlali - Supremo: Ice Storm DMG | H24: =IF($G24="","",IFERROR(MATCH($G24,L_Golpes!$A$2:$A$6000,0),"")) -> 24 | I24: {=IF($A24="","",IF(ISNUMBER($H24),INDEX(L_Golpes!$B$2:$B$6000,$H24),IF(IFERROR(INDEX('Golpes extras'!$C$2:$C$101,MATCH($A24,'Golpes extras'!$A$2:$A$101,0))&"","")<>"",INDEX('Golpes extras'!$C$2:$C$101,MATCH($A24,'Golpes extras'!$A$2:$A$101,0))&"","golpe?")))} -> Citlali | J24: =IF(OR($I24="",$I24="golpe?"),"",IFERROR(MATCH($I24,Time!$B$4:$E$4,0),"fora do time")) -> 2 | K24: {=IF(ISNUMBER($J24),IF(IFERROR(INDEX('Golpes extras'!$D$2:$D$101,MATCH($A24,'Golpes extras'!$A$2:$A$101,0))&"","")<>"",INDEX('Golpes extras'!$D$2:$D$101,MATCH($A24,'Golpes extras'!$A$2:$A$101,0))&"",IF(ISNUMBER($H24),INDEX(L_Golpes!$D$2:$D$6000,$H24),"Outro")),"")} -> Supremo | L24: {=IF(ISNUMBER($J24),IF(ISNUMBER($H24),INDEX(L_Golpes!$C$2:$C$6000,$H24),""),"")} -> Supremo | M24: {=IF(ISNUMBER($J24),IF($L24="Normal",INDEX('Cálculos'!$C$14:$F$14,$J24),IF($L24="Habilidade",INDEX('Cálculos'!$C$15:$F$15,$J24),IF($L24="Supremo",INDEX('Cálculos'!$C$16:$F$16,$J24),""))),"")} -> 10 | N24: {=IF(ISNUMBER($J24),IF(ISNUMBER($H24),INDEX(L_Golpes!$F$2:$T$6000,$H24,MAX(1,MIN(15,$M24))),0)+IF($F24="Sim",N(INDEX('Golpes extras'!$E$2:$E$101,MATCH($A24,'Golpes extras'!$A$2:$A$101,0))),0),"")} -> 9.6768 | O24: {=IF(ISNUMBER($J24),IF(ISNUMBER($H24),INDEX(L_Golpes!$U$2:$AI$6000,$H24,MAX(1,MIN(15,$M24))),0)+IF($F24="Sim",N(INDEX('Golpes extras'!$F$2:$F$101,MATCH($A24,'Golpes extras'!$A$2:$A$101,0))),0),"")} -> 12 | P24: {=IF(ISNUMBER($J24),IF(ISNUMBER($H24),INDEX(L_Golpes!$AJ$2:$AX$6000,$H24,MAX(1,MIN(15,$M24))),0)+IF($F24="Sim",N(INDEX('Golpes extras'!$G$2:$G$101,MATCH($A24,'Golpes extras'!$A$2:$A$101,0))),0),"")} -> 0 | Q24: {=IF(ISNUMBER($J24),IF(ISNUMBER($H24),INDEX(L_Golpes!$AY$2:$BM$6000,$H24,MAX(1,MIN(15,$M24))),0)+IF($F24="Sim",N(INDEX('Golpes extras'!$H$2:$H$101,MATCH($A24,'Golpes extras'!$A$2:$A$101,0))),0),"")} -> 0 | R24: {=IF(ISNUMBER($J24),INDEX('Cálculos'!$C$19:$F$19,$J24),"")} -> Cryo | S24: =IF(ISNUMBER($J24),IF(AND($C24="Derreter",OR($R24="Pyro",$R24="Cryo")),"Derreter",IF(AND($C24="Vaporizar",OR($R24="Pyro",$R24="Hydro")),"Vaporizar","Nenhuma")),"") -> Derreter | T24: =IF(ISNUMBER($J24),IF(OR($D24="Não",$D24=FALSE),'Perfis de buff'!$A$8,IF(OR($D24="",$D24="Sim",$D24=TRUE),'Perfis de buff'!$A$4,$D24)),"") -> Todos | U24: {=IF(ISNUMBER($J24),INDEX('Cálculos'!$C$113:$F$113,$J24)+IF($K24="Normal",INDEX('Cálculos'!$C$114:$F$114,$J24),IF($K24="Carregado",INDEX('Cálculos'!$C$115:$F$115,$J24),IF($K24="Habilidade",INDEX('Cálculos'!$C$116:$F$116,$J24),IF($K24="Supremo",INDEX('Cálculos'!$C$117:$F$117,$J24),0))))+INDEX('Cálculos'!$C$143:$F$147,IFERROR(MATCH($T24,'Perfis de buff'!$A$4:$A$8,0),1),$J24)+IF($K24="Normal",INDEX('Cálculos'!$C$148:$F$152,IFERROR(MATCH($T24,'Perfis de buff'!$A$4:$A$8,0),1),$J24),IF($K24="Carregado",INDEX('Cálculos'!$C$153:$F$157,IFERROR(MATCH($T24,'Perfis de buff'!$A$4:$A$8,0),1),$J24),IF($K24="Habilidade",INDEX('Cálculos'!$C$158:$F$162,IFERROR(MATCH($T24,'Perfis de buff'!$A$4:$A$8,0),1),$J24),IF($K24="Supremo",INDEX('Cálculos'!$C$163:$F$167,IFERROR(MATCH($T24,'Perfis de buff'!$A$4:$A$8,0),1),$J24),0))))+N($E24),"")} -> 0.348 | V24: {=IF(ISNUMBER($J24),INDEX('Cálculos'!$C$180:$F$180,$J24),"")} -> 0.48717949 | W24: {=IF(ISNUMBER($J24),INDEX('Cálculos'!$C$182:$F$182,$J24),"")} -> 0.9 | X24: =IF(ISNUMBER($J24),IF($B24="",1,$B24)*(1+$U24)*$V24*$W24,"") -> 0.59104615 | Y24: =IF(ISNUMBER($J24),$X24*$N24,"") -> 5.7194354 | Z24: =IF(ISNUMBER($J24),$X24*$O24,"") -> 7.0925538 | AA24: =IF(ISNUMBER($J24),$X24*$P24,"") -> 0 | AB24: =IF(ISNUMBER($J24),$X24*$Q24,"") -> 0 | AC24: {=IF(ISNUMBER($J24),INDEX('Cálculos'!$C$332:$F$336,IFERROR(MATCH($T24,'Perfis de buff'!$A$4:$A$8,0),1),$J24),"")} -> 3241.7343 | AD24: {=IF(ISNUMBER($J24),INDEX('Cálculos'!$C$339:$F$343,IFERROR(MATCH($T24,'Perfis de buff'!$A$4:$A$8,0),1),$J24),"")} -> 348.49081 | AE24: {=IF(ISNUMBER($J24),INDEX('Cálculos'!$C$337:$F$337,$J24),"")} -> 20708.65 | AF24: {=IF(ISNUMBER($J24),INDEX('Cálculos'!$C$338:$F$338,$J24),"")} -> 876.60154 | AG24: {=IF(ISNUMBER($J24),IF($S24="Derreter",INDEX('Cálculos'!$C$124:$F$124,$J24)*(1+2.78*$AD24/($AD24+1400)+INDEX('Cálculos'!$C$122:$F$122,$J24)),IF($S24="Vaporizar",INDEX('Cálculos'!$C$125:$F$125,$J24)*(1+2.78*$AD24/($AD24+1400)+INDEX('Cálculos'!$C$123:$F$123,$J24)),1)),"")} -> 2.3311206 | AH24: =IF(ISNUMBER($J24),(($AC24*$N24+$AD24*$O24+$AE24*$P24+$AF24*$Q24)*$X24+$AL24)*$AG24,"") -> 48982.858 | AI24: {=IF(ISNUMBER($J24),$AH24*(1+INDEX('Cálculos'!$C$331:$F$331,$J24)),"")} -> 95452.498 | AJ24: {=IF(ISNUMBER($J24),$AH24*(1+MIN(INDEX('Cálculos'!$C$330:$F$330,$J24),1)*INDEX('Cálculos'!$C$331:$F$331,$J24)),"")} -> 71197.104 | AK24: =IF(ISNUMBER($J24),'Fixo (cálculo)'!$AF24,"") -> 0 | AL24: =IF(ISNUMBER($J24),$AK24*(1+$U24)*$V24*$W24,"") -> 0 | AN24: Citlali Q
A25: Citlali - Supremo: Spiritvessel Skull DMG | B25: 2 | C25: Nenhuma | D25: Todos | F25: =IF($A25="","",IF(ISNUMBER(MATCH($A25,'Golpes extras'!$A$2:$A$101,0)),"Sim","Não")) -> Não | G25: {=IF($A25="","",IF($F25="Sim",INDEX('Golpes extras'!$B$2:$B$101,MATCH($A25,'Golpes extras'!$A$2:$A$101,0))&"",$A25))} -> Citlali - Supremo: Spiritvessel Skull DMG | H25: =IF($G25="","",IFERROR(MATCH($G25,L_Golpes!$A$2:$A$6000,0),"")) -> 25 | I25: {=IF($A25="","",IF(ISNUMBER($H25),INDEX(L_Golpes!$B$2:$B$6000,$H25),IF(IFERROR(INDEX('Golpes extras'!$C$2:$C$101,MATCH($A25,'Golpes extras'!$A$2:$A$101,0))&"","")<>"",INDEX('Golpes extras'!$C$2:$C$101,MATCH($A25,'Golpes extras'!$A$2:$A$101,0))&"","golpe?")))} -> Citlali | J25: =IF(OR($I25="",$I25="golpe?"),"",IFERROR(MATCH($I25,Time!$B$4:$E$4,0),"fora do time")) -> 2 | K25: {=IF(ISNUMBER($J25),IF(IFERROR(INDEX('Golpes extras'!$D$2:$D$101,MATCH($A25,'Golpes extras'!$A$2:$A$101,0))&"","")<>"",INDEX('Golpes extras'!$D$2:$D$101,MATCH($A25,'Golpes extras'!$A$2:$A$101,0))&"",IF(ISNUMBER($H25),INDEX(L_Golpes!$D$2:$D$6000,$H25),"Outro")),"")} -> Supremo | L25: {=IF(ISNUMBER($J25),IF(ISNUMBER($H25),INDEX(L_Golpes!$C$2:$C$6000,$H25),""),"")} -> Supremo | M25: {=IF(ISNUMBER($J25),IF($L25="Normal",INDEX('Cálculos'!$C$14:$F$14,$J25),IF($L25="Habilidade",INDEX('Cálculos'!$C$15:$F$15,$J25),IF($L25="Supremo",INDEX('Cálculos'!$C$16:$F$16,$J25),""))),"")} -> 10 | N25: {=IF(ISNUMBER($J25),IF(ISNUMBER($H25),INDEX(L_Golpes!$F$2:$T$6000,$H25,MAX(1,MIN(15,$M25))),0)+IF($F25="Sim",N(INDEX('Golpes extras'!$E$2:$E$101,MATCH($A25,'Golpes extras'!$A$2:$A$101,0))),0),"")} -> 2.4192 | O25: {=IF(ISNUMBER($J25),IF(ISNUMBER($H25),INDEX(L_Golpes!$U$2:$AI$6000,$H25,MAX(1,MIN(15,$M25))),0)+IF($F25="Sim",N(INDEX('Golpes extras'!$F$2:$F$101,MATCH($A25,'Golpes extras'!$A$2:$A$101,0))),0),"")} -> 0 | P25: {=IF(ISNUMBER($J25),IF(ISNUMBER($H25),INDEX(L_Golpes!$AJ$2:$AX$6000,$H25,MAX(1,MIN(15,$M25))),0)+IF($F25="Sim",N(INDEX('Golpes extras'!$G$2:$G$101,MATCH($A25,'Golpes extras'!$A$2:$A$101,0))),0),"")} -> 0 | Q25: {=IF(ISNUMBER($J25),IF(ISNUMBER($H25),INDEX(L_Golpes!$AY$2:$BM$6000,$H25,MAX(1,MIN(15,$M25))),0)+IF($F25="Sim",N(INDEX('Golpes extras'!$H$2:$H$101,MATCH($A25,'Golpes extras'!$A$2:$A$101,0))),0),"")} -> 0 | R25: {=IF(ISNUMBER($J25),INDEX('Cálculos'!$C$19:$F$19,$J25),"")} -> Cryo | S25: =IF(ISNUMBER($J25),IF(AND($C25="Derreter",OR($R25="Pyro",$R25="Cryo")),"Derreter",IF(AND($C25="Vaporizar",OR($R25="Pyro",$R25="Hydro")),"Vaporizar","Nenhuma")),"") -> Nenhuma | T25: =IF(ISNUMBER($J25),IF(OR($D25="Não",$D25=FALSE),'Perfis de buff'!$A$8,IF(OR($D25="",$D25="Sim",$D25=TRUE),'Perfis de buff'!$A$4,$D25)),"") -> Todos | U25: {=IF(ISNUMBER($J25),INDEX('Cálculos'!$C$113:$F$113,$J25)+IF($K25="Normal",INDEX('Cálculos'!$C$114:$F$114,$J25),IF($K25="Carregado",INDEX('Cálculos'!$C$115:$F$115,$J25),IF($K25="Habilidade",INDEX('Cálculos'!$C$116:$F$116,$J25),IF($K25="Supremo",INDEX('Cálculos'!$C$117:$F$117,$J25),0))))+INDEX('Cálculos'!$C$143:$F$147,IFERROR(MATCH($T25,'Perfis de buff'!$A$4:$A$8,0),1),$J25)+IF($K25="Normal",INDEX('Cálculos'!$C$148:$F$152,IFERROR(MATCH($T25,'Perfis de buff'!$A$4:$A$8,0),1),$J25),IF($K25="Carregado",INDEX('Cálculos'!$C$153:$F$157,IFERROR(MATCH($T25,'Perfis de buff'!$A$4:$A$8,0),1),$J25),IF($K25="Habilidade",INDEX('Cálculos'!$C$158:$F$162,IFERROR(MATCH($T25,'Perfis de buff'!$A$4:$A$8,0),1),$J25),IF($K25="Supremo",INDEX('Cálculos'!$C$163:$F$167,IFERROR(MATCH($T25,'Perfis de buff'!$A$4:$A$8,0),1),$J25),0))))+N($E25),"")} -> 0.348 | V25: {=IF(ISNUMBER($J25),INDEX('Cálculos'!$C$180:$F$180,$J25),"")} -> 0.48717949 | W25: {=IF(ISNUMBER($J25),INDEX('Cálculos'!$C$182:$F$182,$J25),"")} -> 0.9 | X25: =IF(ISNUMBER($J25),IF($B25="",1,$B25)*(1+$U25)*$V25*$W25,"") -> 1.1820923 | Y25: =IF(ISNUMBER($J25),$X25*$N25,"") -> 2.8597177 | Z25: =IF(ISNUMBER($J25),$X25*$O25,"") -> 0 | AA25: =IF(ISNUMBER($J25),$X25*$P25,"") -> 0 | AB25: =IF(ISNUMBER($J25),$X25*$Q25,"") -> 0 | AC25: {=IF(ISNUMBER($J25),INDEX('Cálculos'!$C$332:$F$336,IFERROR(MATCH($T25,'Perfis de buff'!$A$4:$A$8,0),1),$J25),"")} -> 3241.7343 | AD25: {=IF(ISNUMBER($J25),INDEX('Cálculos'!$C$339:$F$343,IFERROR(MATCH($T25,'Perfis de buff'!$A$4:$A$8,0),1),$J25),"")} -> 348.49081 | AE25: {=IF(ISNUMBER($J25),INDEX('Cálculos'!$C$337:$F$337,$J25),"")} -> 20708.65 | AF25: {=IF(ISNUMBER($J25),INDEX('Cálculos'!$C$338:$F$338,$J25),"")} -> 876.60154 | AG25: {=IF(ISNUMBER($J25),IF($S25="Derreter",INDEX('Cálculos'!$C$124:$F$124,$J25)*(1+2.78*$AD25/($AD25+1400)+INDEX('Cálculos'!$C$122:$F$122,$J25)),IF($S25="Vaporizar",INDEX('Cálculos'!$C$125:$F$125,$J25)*(1+2.78*$AD25/($AD25+1400)+INDEX('Cálculos'!$C$123:$F$123,$J25)),1)),"")} -> 1 | AH25: =IF(ISNUMBER($J25),(($AC25*$N25+$AD25*$O25+$AE25*$P25+$AF25*$Q25)*$X25+$AL25)*$AG25,"") -> 9270.4451 | AI25: {=IF(ISNUMBER($J25),$AH25*(1+INDEX('Cálculos'!$C$331:$F$331,$J25)),"")} -> 18065.241 | AJ25: {=IF(ISNUMBER($J25),$AH25*(1+MIN(INDEX('Cálculos'!$C$330:$F$330,$J25),1)*INDEX('Cálculos'!$C$331:$F$331,$J25)),"")} -> 13474.69 | AK25: =IF(ISNUMBER($J25),'Fixo (cálculo)'!$AF25,"") -> 0 | AL25: =IF(ISNUMBER($J25),$AK25*(1+$U25)*$V25*$W25,"") -> 0
A26: Iansan - Habilidade: Skill DMG | B26: 1 | C26: Nenhuma | D26: Iansan (início) | F26: =IF($A26="","",IF(ISNUMBER(MATCH($A26,'Golpes extras'!$A$2:$A$101,0)),"Sim","Não")) -> Não | G26: {=IF($A26="","",IF($F26="Sim",INDEX('Golpes extras'!$B$2:$B$101,MATCH($A26,'Golpes extras'!$A$2:$A$101,0))&"",$A26))} -> Iansan - Habilidade: Skill DMG | H26: =IF($G26="","",IFERROR(MATCH($G26,L_Golpes!$A$2:$A$6000,0),"")) -> 34 | I26: {=IF($A26="","",IF(ISNUMBER($H26),INDEX(L_Golpes!$B$2:$B$6000,$H26),IF(IFERROR(INDEX('Golpes extras'!$C$2:$C$101,MATCH($A26,'Golpes extras'!$A$2:$A$101,0))&"","")<>"",INDEX('Golpes extras'!$C$2:$C$101,MATCH($A26,'Golpes extras'!$A$2:$A$101,0))&"","golpe?")))} -> Iansan | J26: =IF(OR($I26="",$I26="golpe?"),"",IFERROR(MATCH($I26,Time!$B$4:$E$4,0),"fora do time")) -> 3 | K26: {=IF(ISNUMBER($J26),IF(IFERROR(INDEX('Golpes extras'!$D$2:$D$101,MATCH($A26,'Golpes extras'!$A$2:$A$101,0))&"","")<>"",INDEX('Golpes extras'!$D$2:$D$101,MATCH($A26,'Golpes extras'!$A$2:$A$101,0))&"",IF(ISNUMBER($H26),INDEX(L_Golpes!$D$2:$D$6000,$H26),"Outro")),"")} -> Habilidade | L26: {=IF(ISNUMBER($J26),IF(ISNUMBER($H26),INDEX(L_Golpes!$C$2:$C$6000,$H26),""),"")} -> Habilidade | M26: {=IF(ISNUMBER($J26),IF($L26="Normal",INDEX('Cálculos'!$C$14:$F$14,$J26),IF($L26="Habilidade",INDEX('Cálculos'!$C$15:$F$15,$J26),IF($L26="Supremo",INDEX('Cálculos'!$C$16:$F$16,$J26),""))),"")} -> 13 | N26: {=IF(ISNUMBER($J26),IF(ISNUMBER($H26),INDEX(L_Golpes!$F$2:$T$6000,$H26,MAX(1,MIN(15,$M26))),0)+IF($F26="Sim",N(INDEX('Golpes extras'!$E$2:$E$101,MATCH($A26,'Golpes extras'!$A$2:$A$101,0))),0),"")} -> 6.086 | O26: {=IF(ISNUMBER($J26),IF(ISNUMBER($H26),INDEX(L_Golpes!$U$2:$AI$6000,$H26,MAX(1,MIN(15,$M26))),0)+IF($F26="Sim",N(INDEX('Golpes extras'!$F$2:$F$101,MATCH($A26,'Golpes extras'!$A$2:$A$101,0))),0),"")} -> 0 | P26: {=IF(ISNUMBER($J26),IF(ISNUMBER($H26),INDEX(L_Golpes!$AJ$2:$AX$6000,$H26,MAX(1,MIN(15,$M26))),0)+IF($F26="Sim",N(INDEX('Golpes extras'!$G$2:$G$101,MATCH($A26,'Golpes extras'!$A$2:$A$101,0))),0),"")} -> 0 | Q26: {=IF(ISNUMBER($J26),IF(ISNUMBER($H26),INDEX(L_Golpes!$AY$2:$BM$6000,$H26,MAX(1,MIN(15,$M26))),0)+IF($F26="Sim",N(INDEX('Golpes extras'!$H$2:$H$101,MATCH($A26,'Golpes extras'!$A$2:$A$101,0))),0),"")} -> 0 | R26: {=IF(ISNUMBER($J26),INDEX('Cálculos'!$C$19:$F$19,$J26),"")} -> Electro | S26: =IF(ISNUMBER($J26),IF(AND($C26="Derreter",OR($R26="Pyro",$R26="Cryo")),"Derreter",IF(AND($C26="Vaporizar",OR($R26="Pyro",$R26="Hydro")),"Vaporizar","Nenhuma")),"") -> Nenhuma | T26: =IF(ISNUMBER($J26),IF(OR($D26="Não",$D26=FALSE),'Perfis de buff'!$A$8,IF(OR($D26="",$D26="Sim",$D26=TRUE),'Perfis de buff'!$A$4,$D26)),"") -> Iansan (início) | U26: {=IF(ISNUMBER($J26),INDEX('Cálculos'!$C$113:$F$113,$J26)+IF($K26="Normal",INDEX('Cálculos'!$C$114:$F$114,$J26),IF($K26="Carregado",INDEX('Cálculos'!$C$115:$F$115,$J26),IF($K26="Habilidade",INDEX('Cálculos'!$C$116:$F$116,$J26),IF($K26="Supremo",INDEX('Cálculos'!$C$117:$F$117,$J26),0))))+INDEX('Cálculos'!$C$143:$F$147,IFERROR(MATCH($T26,'Perfis de buff'!$A$4:$A$8,0),1),$J26)+IF($K26="Normal",INDEX('Cálculos'!$C$148:$F$152,IFERROR(MATCH($T26,'Perfis de buff'!$A$4:$A$8,0),1),$J26),IF($K26="Carregado",INDEX('Cálculos'!$C$153:$F$157,IFERROR(MATCH($T26,'Perfis de buff'!$A$4:$A$8,0),1),$J26),IF($K26="Habilidade",INDEX('Cálculos'!$C$158:$F$162,IFERROR(MATCH($T26,'Perfis de buff'!$A$4:$A$8,0),1),$J26),IF($K26="Supremo",INDEX('Cálculos'!$C$163:$F$167,IFERROR(MATCH($T26,'Perfis de buff'!$A$4:$A$8,0),1),$J26),0))))+N($E26),"")} -> 0 | V26: {=IF(ISNUMBER($J26),INDEX('Cálculos'!$C$180:$F$180,$J26),"")} -> 0.48717949 | W26: {=IF(ISNUMBER($J26),INDEX('Cálculos'!$C$182:$F$182,$J26),"")} -> 0.9 | X26: =IF(ISNUMBER($J26),IF($B26="",1,$B26)*(1+$U26)*$V26*$W26,"") -> 0.43846154 | Y26: =IF(ISNUMBER($J26),$X26*$N26,"") -> 2.6684769 | Z26: =IF(ISNUMBER($J26),$X26*$O26,"") -> 0 | AA26: =IF(ISNUMBER($J26),$X26*$P26,"") -> 0 | AB26: =IF(ISNUMBER($J26),$X26*$Q26,"") -> 0 | AC26: {=IF(ISNUMBER($J26),INDEX('Cálculos'!$C$332:$F$336,IFERROR(MATCH($T26,'Perfis de buff'!$A$4:$A$8,0),1),$J26),"")} -> 2782.0062 | AD26: {=IF(ISNUMBER($J26),INDEX('Cálculos'!$C$339:$F$343,IFERROR(MATCH($T26,'Perfis de buff'!$A$4:$A$8,0),1),$J26),"")} -> 39 | AE26: {=IF(ISNUMBER($J26),INDEX('Cálculos'!$C$337:$F$337,$J26),"")} -> 17000.043 | AF26: {=IF(ISNUMBER($J26),INDEX('Cálculos'!$C$338:$F$338,$J26),"")} -> 756.112 | AG26: {=IF(ISNUMBER($J26),IF($S26="Derreter",INDEX('Cálculos'!$C$124:$F$124,$J26)*(1+2.78*$AD26/($AD26+1400)+INDEX('Cálculos'!$C$122:$F$122,$J26)),IF($S26="Vaporizar",INDEX('Cálculos'!$C$125:$F$125,$J26)*(1+2.78*$AD26/($AD26+1400)+INDEX('Cálculos'!$C$123:$F$123,$J26)),1)),"")} -> 1 | AH26: =IF(ISNUMBER($J26),(($AC26*$N26+$AD26*$O26+$AE26*$P26+$AF26*$Q26)*$X26+$AL26)*$AG26,"") -> 7423.7193 | AI26: {=IF(ISNUMBER($J26),$AH26*(1+INDEX('Cálculos'!$C$331:$F$331,$J26)),"")} -> 16035.234 | AJ26: {=IF(ISNUMBER($J26),$AH26*(1+MIN(INDEX('Cálculos'!$C$330:$F$330,$J26),1)*INDEX('Cálculos'!$C$331:$F$331,$J26)),"")} -> 12521.736 | AK26: =IF(ISNUMBER($J26),'Fixo (cálculo)'!$AF26,"") -> 0 | AL26: =IF(ISNUMBER($J26),$AK26*(1+$U26)*$V26*$W26,"") -> 0 | AN26: Iansan E (antes do Bennett)
A27: Iansan - Supremo: Skill DMG | B27: 1 | C27: Nenhuma | D27: Iansan (início) | F27: =IF($A27="","",IF(ISNUMBER(MATCH($A27,'Golpes extras'!$A$2:$A$101,0)),"Sim","Não")) -> Não | G27: {=IF($A27="","",IF($F27="Sim",INDEX('Golpes extras'!$B$2:$B$101,MATCH($A27,'Golpes extras'!$A$2:$A$101,0))&"",$A27))} -> Iansan - Supremo: Skill DMG | H27: =IF($G27="","",IFERROR(MATCH($G27,L_Golpes!$A$2:$A$6000,0),"")) -> 35 | I27: {=IF($A27="","",IF(ISNUMBER($H27),INDEX(L_Golpes!$B$2:$B$6000,$H27),IF(IFERROR(INDEX('Golpes extras'!$C$2:$C$101,MATCH($A27,'Golpes extras'!$A$2:$A$101,0))&"","")<>"",INDEX('Golpes extras'!$C$2:$C$101,MATCH($A27,'Golpes extras'!$A$2:$A$101,0))&"","golpe?")))} -> Iansan | J27: =IF(OR($I27="",$I27="golpe?"),"",IFERROR(MATCH($I27,Time!$B$4:$E$4,0),"fora do time")) -> 3 | K27: {=IF(ISNUMBER($J27),IF(IFERROR(INDEX('Golpes extras'!$D$2:$D$101,MATCH($A27,'Golpes extras'!$A$2:$A$101,0))&"","")<>"",INDEX('Golpes extras'!$D$2:$D$101,MATCH($A27,'Golpes extras'!$A$2:$A$101,0))&"",IF(ISNUMBER($H27),INDEX(L_Golpes!$D$2:$D$6000,$H27),"Outro")),"")} -> Supremo | L27: {=IF(ISNUMBER($J27),IF(ISNUMBER($H27),INDEX(L_Golpes!$C$2:$C$6000,$H27),""),"")} -> Supremo | M27: {=IF(ISNUMBER($J27),IF($L27="Normal",INDEX('Cálculos'!$C$14:$F$14,$J27),IF($L27="Habilidade",INDEX('Cálculos'!$C$15:$F$15,$J27),IF($L27="Supremo",INDEX('Cálculos'!$C$16:$F$16,$J27),""))),"")} -> 13 | N27: {=IF(ISNUMBER($J27),IF(ISNUMBER($H27),INDEX(L_Golpes!$F$2:$T$6000,$H27,MAX(1,MIN(15,$M27))),0)+IF($F27="Sim",N(INDEX('Golpes extras'!$E$2:$E$101,MATCH($A27,'Golpes extras'!$A$2:$A$101,0))),0),"")} -> 9.146 | O27: {=IF(ISNUMBER($J27),IF(ISNUMBER($H27),INDEX(L_Golpes!$U$2:$AI$6000,$H27,MAX(1,MIN(15,$M27))),0)+IF($F27="Sim",N(INDEX('Golpes extras'!$F$2:$F$101,MATCH($A27,'Golpes extras'!$A$2:$A$101,0))),0),"")} -> 0 | P27: {=IF(ISNUMBER($J27),IF(ISNUMBER($H27),INDEX(L_Golpes!$AJ$2:$AX$6000,$H27,MAX(1,MIN(15,$M27))),0)+IF($F27="Sim",N(INDEX('Golpes extras'!$G$2:$G$101,MATCH($A27,'Golpes extras'!$A$2:$A$101,0))),0),"")} -> 0 | Q27: {=IF(ISNUMBER($J27),IF(ISNUMBER($H27),INDEX(L_Golpes!$AY$2:$BM$6000,$H27,MAX(1,MIN(15,$M27))),0)+IF($F27="Sim",N(INDEX('Golpes extras'!$H$2:$H$101,MATCH($A27,'Golpes extras'!$A$2:$A$101,0))),0),"")} -> 0 | R27: {=IF(ISNUMBER($J27),INDEX('Cálculos'!$C$19:$F$19,$J27),"")} -> Electro | S27: =IF(ISNUMBER($J27),IF(AND($C27="Derreter",OR($R27="Pyro",$R27="Cryo")),"Derreter",IF(AND($C27="Vaporizar",OR($R27="Pyro",$R27="Hydro")),"Vaporizar","Nenhuma")),"") -> Nenhuma | T27: =IF(ISNUMBER($J27),IF(OR($D27="Não",$D27=FALSE),'Perfis de buff'!$A$8,IF(OR($D27="",$D27="Sim",$D27=TRUE),'Perfis de buff'!$A$4,$D27)),"") -> Iansan (início) | U27: {=IF(ISNUMBER($J27),INDEX('Cálculos'!$C$113:$F$113,$J27)+IF($K27="Normal",INDEX('Cálculos'!$C$114:$F$114,$J27),IF($K27="Carregado",INDEX('Cálculos'!$C$115:$F$115,$J27),IF($K27="Habilidade",INDEX('Cálculos'!$C$116:$F$116,$J27),IF($K27="Supremo",INDEX('Cálculos'!$C$117:$F$117,$J27),0))))+INDEX('Cálculos'!$C$143:$F$147,IFERROR(MATCH($T27,'Perfis de buff'!$A$4:$A$8,0),1),$J27)+IF($K27="Normal",INDEX('Cálculos'!$C$148:$F$152,IFERROR(MATCH($T27,'Perfis de buff'!$A$4:$A$8,0),1),$J27),IF($K27="Carregado",INDEX('Cálculos'!$C$153:$F$157,IFERROR(MATCH($T27,'Perfis de buff'!$A$4:$A$8,0),1),$J27),IF($K27="Habilidade",INDEX('Cálculos'!$C$158:$F$162,IFERROR(MATCH($T27,'Perfis de buff'!$A$4:$A$8,0),1),$J27),IF($K27="Supremo",INDEX('Cálculos'!$C$163:$F$167,IFERROR(MATCH($T27,'Perfis de buff'!$A$4:$A$8,0),1),$J27),0))))+N($E27),"")} -> 0 | V27: {=IF(ISNUMBER($J27),INDEX('Cálculos'!$C$180:$F$180,$J27),"")} -> 0.48717949 | W27: {=IF(ISNUMBER($J27),INDEX('Cálculos'!$C$182:$F$182,$J27),"")} -> 0.9 | X27: =IF(ISNUMBER($J27),IF($B27="",1,$B27)*(1+$U27)*$V27*$W27,"") -> 0.43846154 | Y27: =IF(ISNUMBER($J27),$X27*$N27,"") -> 4.0101692 | Z27: =IF(ISNUMBER($J27),$X27*$O27,"") -> 0 | AA27: =IF(ISNUMBER($J27),$X27*$P27,"") -> 0 | AB27: =IF(ISNUMBER($J27),$X27*$Q27,"") -> 0 | AC27: {=IF(ISNUMBER($J27),INDEX('Cálculos'!$C$332:$F$336,IFERROR(MATCH($T27,'Perfis de buff'!$A$4:$A$8,0),1),$J27),"")} -> 2782.0062 | AD27: {=IF(ISNUMBER($J27),INDEX('Cálculos'!$C$339:$F$343,IFERROR(MATCH($T27,'Perfis de buff'!$A$4:$A$8,0),1),$J27),"")} -> 39 | AE27: {=IF(ISNUMBER($J27),INDEX('Cálculos'!$C$337:$F$337,$J27),"")} -> 17000.043 | AF27: {=IF(ISNUMBER($J27),INDEX('Cálculos'!$C$338:$F$338,$J27),"")} -> 756.112 | AG27: {=IF(ISNUMBER($J27),IF($S27="Derreter",INDEX('Cálculos'!$C$124:$F$124,$J27)*(1+2.78*$AD27/($AD27+1400)+INDEX('Cálculos'!$C$122:$F$122,$J27)),IF($S27="Vaporizar",INDEX('Cálculos'!$C$125:$F$125,$J27)*(1+2.78*$AD27/($AD27+1400)+INDEX('Cálculos'!$C$123:$F$123,$J27)),1)),"")} -> 1 | AH27: =IF(ISNUMBER($J27),(($AC27*$N27+$AD27*$O27+$AE27*$P27+$AF27*$Q27)*$X27+$AL27)*$AG27,"") -> 11156.316 | AI27: {=IF(ISNUMBER($J27),$AH27*(1+INDEX('Cálculos'!$C$331:$F$331,$J27)),"")} -> 24097.642 | AJ27: {=IF(ISNUMBER($J27),$AH27*(1+MIN(INDEX('Cálculos'!$C$330:$F$330,$J27),1)*INDEX('Cálculos'!$C$331:$F$331,$J27)),"")} -> 18817.581 | AK27: =IF(ISNUMBER($J27),'Fixo (cálculo)'!$AF27,"") -> 0 | AL27: =IF(ISNUMBER($J27),$AK27*(1+$U27)*$V27*$W27,"") -> 0 | AN27: Iansan Q
A28: Bennett - Supremo: Skill DMG | B28: 1 | C28: Nenhuma | D28: Todos | F28: =IF($A28="","",IF(ISNUMBER(MATCH($A28,'Golpes extras'!$A$2:$A$101,0)),"Sim","Não")) -> Não | G28: {=IF($A28="","",IF($F28="Sim",INDEX('Golpes extras'!$B$2:$B$101,MATCH($A28,'Golpes extras'!$A$2:$A$101,0))&"",$A28))} -> Bennett - Supremo: Skill DMG | H28: =IF($G28="","",IFERROR(MATCH($G28,L_Golpes!$A$2:$A$6000,0),"")) -> 14 | I28: {=IF($A28="","",IF(ISNUMBER($H28),INDEX(L_Golpes!$B$2:$B$6000,$H28),IF(IFERROR(INDEX('Golpes extras'!$C$2:$C$101,MATCH($A28,'Golpes extras'!$A$2:$A$101,0))&"","")<>"",INDEX('Golpes extras'!$C$2:$C$101,MATCH($A28,'Golpes extras'!$A$2:$A$101,0))&"","golpe?")))} -> Bennett | J28: =IF(OR($I28="",$I28="golpe?"),"",IFERROR(MATCH($I28,Time!$B$4:$E$4,0),"fora do time")) -> 4 | K28: {=IF(ISNUMBER($J28),IF(IFERROR(INDEX('Golpes extras'!$D$2:$D$101,MATCH($A28,'Golpes extras'!$A$2:$A$101,0))&"","")<>"",INDEX('Golpes extras'!$D$2:$D$101,MATCH($A28,'Golpes extras'!$A$2:$A$101,0))&"",IF(ISNUMBER($H28),INDEX(L_Golpes!$D$2:$D$6000,$H28),"Outro")),"")} -> Supremo | L28: {=IF(ISNUMBER($J28),IF(ISNUMBER($H28),INDEX(L_Golpes!$C$2:$C$6000,$H28),""),"")} -> Supremo | M28: {=IF(ISNUMBER($J28),IF($L28="Normal",INDEX('Cálculos'!$C$14:$F$14,$J28),IF($L28="Habilidade",INDEX('Cálculos'!$C$15:$F$15,$J28),IF($L28="Supremo",INDEX('Cálculos'!$C$16:$F$16,$J28),""))),"")} -> 13 | N28: {=IF(ISNUMBER($J28),IF(ISNUMBER($H28),INDEX(L_Golpes!$F$2:$T$6000,$H28,MAX(1,MIN(15,$M28))),0)+IF($F28="Sim",N(INDEX('Golpes extras'!$E$2:$E$101,MATCH($A28,'Golpes extras'!$A$2:$A$101,0))),0),"")} -> 4.947 | O28: {=IF(ISNUMBER($J28),IF(ISNUMBER($H28),INDEX(L_Golpes!$U$2:$AI$6000,$H28,MAX(1,MIN(15,$M28))),0)+IF($F28="Sim",N(INDEX('Golpes extras'!$F$2:$F$101,MATCH($A28,'Golpes extras'!$A$2:$A$101,0))),0),"")} -> 0 | P28: {=IF(ISNUMBER($J28),IF(ISNUMBER($H28),INDEX(L_Golpes!$AJ$2:$AX$6000,$H28,MAX(1,MIN(15,$M28))),0)+IF($F28="Sim",N(INDEX('Golpes extras'!$G$2:$G$101,MATCH($A28,'Golpes extras'!$A$2:$A$101,0))),0),"")} -> 0 | Q28: {=IF(ISNUMBER($J28),IF(ISNUMBER($H28),INDEX(L_Golpes!$AY$2:$BM$6000,$H28,MAX(1,MIN(15,$M28))),0)+IF($F28="Sim",N(INDEX('Golpes extras'!$H$2:$H$101,MATCH($A28,'Golpes extras'!$A$2:$A$101,0))),0),"")} -> 0 | R28: {=IF(ISNUMBER($J28),INDEX('Cálculos'!$C$19:$F$19,$J28),"")} -> Pyro | S28: =IF(ISNUMBER($J28),IF(AND($C28="Derreter",OR($R28="Pyro",$R28="Cryo")),"Derreter",IF(AND($C28="Vaporizar",OR($R28="Pyro",$R28="Hydro")),"Vaporizar","Nenhuma")),"") -> Nenhuma | T28: =IF(ISNUMBER($J28),IF(OR($D28="Não",$D28=FALSE),'Perfis de buff'!$A$8,IF(OR($D28="",$D28="Sim",$D28=TRUE),'Perfis de buff'!$A$4,$D28)),"") -> Todos | U28: {=IF(ISNUMBER($J28),INDEX('Cálculos'!$C$113:$F$113,$J28)+IF($K28="Normal",INDEX('Cálculos'!$C$114:$F$114,$J28),IF($K28="Carregado",INDEX('Cálculos'!$C$115:$F$115,$J28),IF($K28="Habilidade",INDEX('Cálculos'!$C$116:$F$116,$J28),IF($K28="Supremo",INDEX('Cálculos'!$C$117:$F$117,$J28),0))))+INDEX('Cálculos'!$C$143:$F$147,IFERROR(MATCH($T28,'Perfis de buff'!$A$4:$A$8,0),1),$J28)+IF($K28="Normal",INDEX('Cálculos'!$C$148:$F$152,IFERROR(MATCH($T28,'Perfis de buff'!$A$4:$A$8,0),1),$J28),IF($K28="Carregado",INDEX('Cálculos'!$C$153:$F$157,IFERROR(MATCH($T28,'Perfis de buff'!$A$4:$A$8,0),1),$J28),IF($K28="Habilidade",INDEX('Cálculos'!$C$158:$F$162,IFERROR(MATCH($T28,'Perfis de buff'!$A$4:$A$8,0),1),$J28),IF($K28="Supremo",INDEX('Cálculos'!$C$163:$F$167,IFERROR(MATCH($T28,'Perfis de buff'!$A$4:$A$8,0),1),$J28),0))))+N($E28),"")} -> 1.066 | V28: {=IF(ISNUMBER($J28),INDEX('Cálculos'!$C$180:$F$180,$J28),"")} -> 0.48717949 | W28: {=IF(ISNUMBER($J28),INDEX('Cálculos'!$C$182:$F$182,$J28),"")} -> 1.05 | X28: =IF(ISNUMBER($J28),IF($B28="",1,$B28)*(1+$U28)*$V28*$W28,"") -> 1.0568385 | Y28: =IF(ISNUMBER($J28),$X28*$N28,"") -> 5.2281799 | Z28: =IF(ISNUMBER($J28),$X28*$O28,"") -> 0 | AA28: =IF(ISNUMBER($J28),$X28*$P28,"") -> 0 | AB28: =IF(ISNUMBER($J28),$X28*$Q28,"") -> 0 | AC28: {=IF(ISNUMBER($J28),INDEX('Cálculos'!$C$332:$F$336,IFERROR(MATCH($T28,'Perfis de buff'!$A$4:$A$8,0),1),$J28),"")} -> 3700.235 | AD28: {=IF(ISNUMBER($J28),INDEX('Cálculos'!$C$339:$F$343,IFERROR(MATCH($T28,'Perfis de buff'!$A$4:$A$8,0),1),$J28),"")} -> 159 | AE28: {=IF(ISNUMBER($J28),INDEX('Cálculos'!$C$337:$F$337,$J28),"")} -> 18912.303 | AF28: {=IF(ISNUMBER($J28),INDEX('Cálculos'!$C$338:$F$338,$J28),"")} -> 905.604 | AG28: {=IF(ISNUMBER($J28),IF($S28="Derreter",INDEX('Cálculos'!$C$124:$F$124,$J28)*(1+2.78*$AD28/($AD28+1400)+INDEX('Cálculos'!$C$122:$F$122,$J28)),IF($S28="Vaporizar",INDEX('Cálculos'!$C$125:$F$125,$J28)*(1+2.78*$AD28/($AD28+1400)+INDEX('Cálculos'!$C$123:$F$123,$J28)),1)),"")} -> 1 | AH28: =IF(ISNUMBER($J28),(($AC28*$N28+$AD28*$O28+$AE28*$P28+$AF28*$Q28)*$X28+$AL28)*$AG28,"") -> 19345.494 | AI28: {=IF(ISNUMBER($J28),$AH28*(1+INDEX('Cálculos'!$C$331:$F$331,$J28)),"")} -> 51633.124 | AJ28: {=IF(ISNUMBER($J28),$AH28*(1+MIN(INDEX('Cálculos'!$C$330:$F$330,$J28),1)*INDEX('Cálculos'!$C$331:$F$331,$J28)),"")} -> 45918.213 | AK28: =IF(ISNUMBER($J28),'Fixo (cálculo)'!$AF28,"") -> 0 | AL28: =IF(ISNUMBER($J28),$AK28*(1+$U28)*$V28*$W28,"") -> 0 | AN28: Bennett Q
D29: Todos | F29: =IF($A29="","",IF(ISNUMBER(MATCH($A29,'Golpes extras'!$A$2:$A$101,0)),"Sim","Não")) | G29: {=IF($A29="","",IF($F29="Sim",INDEX('Golpes extras'!$B$2:$B$101,MATCH($A29,'Golpes extras'!$A$2:$A$101,0))&"",$A29))} | H29: =IF($G29="","",IFERROR(MATCH($G29,L_Golpes!$A$2:$A$6000,0),"")) | I29: {=IF($A29="","",IF(ISNUMBER($H29),INDEX(L_Golpes!$B$2:$B$6000,$H29),IF(IFERROR(INDEX('Golpes extras'!$C$2:$C$101,MATCH($A29,'Golpes extras'!$A$2:$A$101,0))&"","")<>"",INDEX('Golpes extras'!$C$2:$C$101,MATCH($A29,'Golpes extras'!$A$2:$A$101,0))&"","golpe?")))} | J29: =IF(OR($I29="",$I29="golpe?"),"",IFERROR(MATCH($I29,Time!$B$4:$E$4,0),"fora do time")) | K29: {=IF(ISNUMBER($J29),IF(IFERROR(INDEX('Golpes extras'!$D$2:$D$101,MATCH($A29,'Golpes extras'!$A$2:$A$101,0))&"","")<>"",INDEX('Golpes extras'!$D$2:$D$101,MATCH($A29,'Golpes extras'!$A$2:$A$101,0))&"",IF(ISNUMBER($H29),INDEX(L_Golpes!$D$2:$D$6000,$H29),"Outro")),"")} | L29: {=IF(ISNUMBER($J29),IF(ISNUMBER($H29),INDEX(L_Golpes!$C$2:$C$6000,$H29),""),"")} | M29: {=IF(ISNUMBER($J29),IF($L29="Normal",INDEX('Cálculos'!$C$14:$F$14,$J29),IF($L29="Habilidade",INDEX('Cálculos'!$C$15:$F$15,$J29),IF($L29="Supremo",INDEX('Cálculos'!$C$16:$F$16,$J29),""))),"")} | N29: {=IF(ISNUMBER($J29),IF(ISNUMBER($H29),INDEX(L_Golpes!$F$2:$T$6000,$H29,MAX(1,MIN(15,$M29))),0)+IF($F29="Sim",N(INDEX('Golpes extras'!$E$2:$E$101,MATCH($A29,'Golpes extras'!$A$2:$A$101,0))),0),"")} | O29: {=IF(ISNUMBER($J29),IF(ISNUMBER($H29),INDEX(L_Golpes!$U$2:$AI$6000,$H29,MAX(1,MIN(15,$M29))),0)+IF($F29="Sim",N(INDEX('Golpes extras'!$F$2:$F$101,MATCH($A29,'Golpes extras'!$A$2:$A$101,0))),0),"")} | P29: {=IF(ISNUMBER($J29),IF(ISNUMBER($H29),INDEX(L_Golpes!$AJ$2:$AX$6000,$H29,MAX(1,MIN(15,$M29))),0)+IF($F29="Sim",N(INDEX('Golpes extras'!$G$2:$G$101,MATCH($A29,'Golpes extras'!$A$2:$A$101,0))),0),"")} | Q29: {=IF(ISNUMBER($J29),IF(ISNUMBER($H29),INDEX(L_Golpes!$AY$2:$BM$6000,$H29,MAX(1,MIN(15,$M29))),0)+IF($F29="Sim",N(INDEX('Golpes extras'!$H$2:$H$101,MATCH($A29,'Golpes extras'!$A$2:$A$101,0))),0),"")} | R29: {=IF(ISNUMBER($J29),INDEX('Cálculos'!$C$19:$F$19,$J29),"")} | S29: =IF(ISNUMBER($J29),IF(AND($C29="Derreter",OR($R29="Pyro",$R29="Cryo")),"Derreter",IF(AND($C29="Vaporizar",OR($R29="Pyro",$R29="Hydro")),"Vaporizar","Nenhuma")),"") | T29: =IF(ISNUMBER($J29),IF(OR($D29="Não",$D29=FALSE),'Perfis de buff'!$A$8,IF(OR($D29="",$D29="Sim",$D29=TRUE),'Perfis de buff'!$A$4,$D29)),"") | U29: {=IF(ISNUMBER($J29),INDEX('Cálculos'!$C$113:$F$113,$J29)+IF($K29="Normal",INDEX('Cálculos'!$C$114:$F$114,$J29),IF($K29="Carregado",INDEX('Cálculos'!$C$115:$F$115,$J29),IF($K29="Habilidade",INDEX('Cálculos'!$C$116:$F$116,$J29),IF($K29="Supremo",INDEX('Cálculos'!$C$117:$F$117,$J29),0))))+INDEX('Cálculos'!$C$143:$F$147,IFERROR(MATCH($T29,'Perfis de buff'!$A$4:$A$8,0),1),$J29)+IF($K29="Normal",INDEX('Cálculos'!$C$148:$F$152,IFERROR(MATCH($T29,'Perfis de buff'!$A$4:$A$8,0),1),$J29),IF($K29="Carregado",INDEX('Cálculos'!$C$153:$F$157,IFERROR(MATCH($T29,'Perfis de buff'!$A$4:$A$8,0),1),$J29),IF($K29="Habilidade",INDEX('Cálculos'!$C$158:$F$162,IFERROR(MATCH($T29,'Perfis de buff'!$A$4:$A$8,0),1),$J29),IF($K29="Supremo",INDEX('Cálculos'!$C$163:$F$167,IFERROR(MATCH($T29,'Perfis de buff'!$A$4:$A$8,0),1),$J29),0))))+N($E29),"")} | V29: {=IF(ISNUMBER($J29),INDEX('Cálculos'!$C$180:$F$180,$J29),"")} | W29: {=IF(ISNUMBER($J29),INDEX('Cálculos'!$C$182:$F$182,$J29),"")} | X29: =IF(ISNUMBER($J29),IF($B29="",1,$B29)*(1+$U29)*$V29*$W29,"") | Y29: =IF(ISNUMBER($J29),$X29*$N29,"") | Z29: =IF(ISNUMBER($J29),$X29*$O29,"") | AA29: =IF(ISNUMBER($J29),$X29*$P29,"") | AB29: =IF(ISNUMBER($J29),$X29*$Q29,"") | AC29: {=IF(ISNUMBER($J29),INDEX('Cálculos'!$C$332:$F$336,IFERROR(MATCH($T29,'Perfis de buff'!$A$4:$A$8,0),1),$J29),"")} | AD29: {=IF(ISNUMBER($J29),INDEX('Cálculos'!$C$339:$F$343,IFERROR(MATCH($T29,'Perfis de buff'!$A$4:$A$8,0),1),$J29),"")} | AE29: {=IF(ISNUMBER($J29),INDEX('Cálculos'!$C$337:$F$337,$J29),"")} | AF29: {=IF(ISNUMBER($J29),INDEX('Cálculos'!$C$338:$F$338,$J29),"")} | AG29: {=IF(ISNUMBER($J29),IF($S29="Derreter",INDEX('Cálculos'!$C$124:$F$124,$J29)*(1+2.78*$AD29/($AD29+1400)+INDEX('Cálculos'!$C$122:$F$122,$J29)),IF($S29="Vaporizar",INDEX('Cálculos'!$C$125:$F$125,$J29)*(1+2.78*$AD29/($AD29+1400)+INDEX('Cálculos'!$C$123:$F$123,$J29)),1)),"")} | AH29: =IF(ISNUMBER($J29),(($AC29*$N29+$AD29*$O29+$AE29*$P29+$AF29*$Q29)*$X29+$AL29)*$AG29,"") | AI29: {=IF(ISNUMBER($J29),$AH29*(1+INDEX('Cálculos'!$C$331:$F$331,$J29)),"")} | AJ29: {=IF(ISNUMBER($J29),$AH29*(1+MIN(INDEX('Cálculos'!$C$330:$F$330,$J29),1)*INDEX('Cálculos'!$C$331:$F$331,$J29)),"")} | AK29: =IF(ISNUMBER($J29),'Fixo (cálculo)'!$AF29,"") | AL29: =IF(ISNUMBER($J29),$AK29*(1+$U29)*$V29*$W29,"")
D30: Todos | F30: =IF($A30="","",IF(ISNUMBER(MATCH($A30,'Golpes extras'!$A$2:$A$101,0)),"Sim","Não")) | G30: {=IF($A30="","",IF($F30="Sim",INDEX('Golpes extras'!$B$2:$B$101,MATCH($A30,'Golpes extras'!$A$2:$A$101,0))&"",$A30))} | H30: =IF($G30="","",IFERROR(MATCH($G30,L_Golpes!$A$2:$A$6000,0),"")) | I30: {=IF($A30="","",IF(ISNUMBER($H30),INDEX(L_Golpes!$B$2:$B$6000,$H30),IF(IFERROR(INDEX('Golpes extras'!$C$2:$C$101,MATCH($A30,'Golpes extras'!$A$2:$A$101,0))&"","")<>"",INDEX('Golpes extras'!$C$2:$C$101,MATCH($A30,'Golpes extras'!$A$2:$A$101,0))&"","golpe?")))} | J30: =IF(OR($I30="",$I30="golpe?"),"",IFERROR(MATCH($I30,Time!$B$4:$E$4,0),"fora do time")) | K30: {=IF(ISNUMBER($J30),IF(IFERROR(INDEX('Golpes extras'!$D$2:$D$101,MATCH($A30,'Golpes extras'!$A$2:$A$101,0))&"","")<>"",INDEX('Golpes extras'!$D$2:$D$101,MATCH($A30,'Golpes extras'!$A$2:$A$101,0))&"",IF(ISNUMBER($H30),INDEX(L_Golpes!$D$2:$D$6000,$H30),"Outro")),"")} | L30: {=IF(ISNUMBER($J30),IF(ISNUMBER($H30),INDEX(L_Golpes!$C$2:$C$6000,$H30),""),"")} | M30: {=IF(ISNUMBER($J30),IF($L30="Normal",INDEX('Cálculos'!$C$14:$F$14,$J30),IF($L30="Habilidade",INDEX('Cálculos'!$C$15:$F$15,$J30),IF($L30="Supremo",INDEX('Cálculos'!$C$16:$F$16,$J30),""))),"")} | N30: {=IF(ISNUMBER($J30),IF(ISNUMBER($H30),INDEX(L_Golpes!$F$2:$T$6000,$H30,MAX(1,MIN(15,$M30))),0)+IF($F30="Sim",N(INDEX('Golpes extras'!$E$2:$E$101,MATCH($A30,'Golpes extras'!$A$2:$A$101,0))),0),"")} | O30: {=IF(ISNUMBER($J30),IF(ISNUMBER($H30),INDEX(L_Golpes!$U$2:$AI$6000,$H30,MAX(1,MIN(15,$M30))),0)+IF($F30="Sim",N(INDEX('Golpes extras'!$F$2:$F$101,MATCH($A30,'Golpes extras'!$A$2:$A$101,0))),0),"")} | P30: {=IF(ISNUMBER($J30),IF(ISNUMBER($H30),INDEX(L_Golpes!$AJ$2:$AX$6000,$H30,MAX(1,MIN(15,$M30))),0)+IF($F30="Sim",N(INDEX('Golpes extras'!$G$2:$G$101,MATCH($A30,'Golpes extras'!$A$2:$A$101,0))),0),"")} | Q30: {=IF(ISNUMBER($J30),IF(ISNUMBER($H30),INDEX(L_Golpes!$AY$2:$BM$6000,$H30,MAX(1,MIN(15,$M30))),0)+IF($F30="Sim",N(INDEX('Golpes extras'!$H$2:$H$101,MATCH($A30,'Golpes extras'!$A$2:$A$101,0))),0),"")} | R30: {=IF(ISNUMBER($J30),INDEX('Cálculos'!$C$19:$F$19,$J30),"")} | S30: =IF(ISNUMBER($J30),IF(AND($C30="Derreter",OR($R30="Pyro",$R30="Cryo")),"Derreter",IF(AND($C30="Vaporizar",OR($R30="Pyro",$R30="Hydro")),"Vaporizar","Nenhuma")),"") | T30: =IF(ISNUMBER($J30),IF(OR($D30="Não",$D30=FALSE),'Perfis de buff'!$A$8,IF(OR($D30="",$D30="Sim",$D30=TRUE),'Perfis de buff'!$A$4,$D30)),"") | U30: {=IF(ISNUMBER($J30),INDEX('Cálculos'!$C$113:$F$113,$J30)+IF($K30="Normal",INDEX('Cálculos'!$C$114:$F$114,$J30),IF($K30="Carregado",INDEX('Cálculos'!$C$115:$F$115,$J30),IF($K30="Habilidade",INDEX('Cálculos'!$C$116:$F$116,$J30),IF($K30="Supremo",INDEX('Cálculos'!$C$117:$F$117,$J30),0))))+INDEX('Cálculos'!$C$143:$F$147,IFERROR(MATCH($T30,'Perfis de buff'!$A$4:$A$8,0),1),$J30)+IF($K30="Normal",INDEX('Cálculos'!$C$148:$F$152,IFERROR(MATCH($T30,'Perfis de buff'!$A$4:$A$8,0),1),$J30),IF($K30="Carregado",INDEX('Cálculos'!$C$153:$F$157,IFERROR(MATCH($T30,'Perfis de buff'!$A$4:$A$8,0),1),$J30),IF($K30="Habilidade",INDEX('Cálculos'!$C$158:$F$162,IFERROR(MATCH($T30,'Perfis de buff'!$A$4:$A$8,0),1),$J30),IF($K30="Supremo",INDEX('Cálculos'!$C$163:$F$167,IFERROR(MATCH($T30,'Perfis de buff'!$A$4:$A$8,0),1),$J30),0))))+N($E30),"")} | V30: {=IF(ISNUMBER($J30),INDEX('Cálculos'!$C$180:$F$180,$J30),"")} | W30: {=IF(ISNUMBER($J30),INDEX('Cálculos'!$C$182:$F$182,$J30),"")} | X30: =IF(ISNUMBER($J30),IF($B30="",1,$B30)*(1+$U30)*$V30*$W30,"") | Y30: =IF(ISNUMBER($J30),$X30*$N30,"") | Z30: =IF(ISNUMBER($J30),$X30*$O30,"") | AA30: =IF(ISNUMBER($J30),$X30*$P30,"") | AB30: =IF(ISNUMBER($J30),$X30*$Q30,"") | AC30: {=IF(ISNUMBER($J30),INDEX('Cálculos'!$C$332:$F$336,IFERROR(MATCH($T30,'Perfis de buff'!$A$4:$A$8,0),1),$J30),"")} | AD30: {=IF(ISNUMBER($J30),INDEX('Cálculos'!$C$339:$F$343,IFERROR(MATCH($T30,'Perfis de buff'!$A$4:$A$8,0),1),$J30),"")} | AE30: {=IF(ISNUMBER($J30),INDEX('Cálculos'!$C$337:$F$337,$J30),"")} | AF30: {=IF(ISNUMBER($J30),INDEX('Cálculos'!$C$338:$F$338,$J30),"")} | AG30: {=IF(ISNUMBER($J30),IF($S30="Derreter",INDEX('Cálculos'!$C$124:$F$124,$J30)*(1+2.78*$AD30/($AD30+1400)+INDEX('Cálculos'!$C$122:$F$122,$J30)),IF($S30="Vaporizar",INDEX('Cálculos'!$C$125:$F$125,$J30)*(1+2.78*$AD30/($AD30+1400)+INDEX('Cálculos'!$C$123:$F$123,$J30)),1)),"")} | AH30: =IF(ISNUMBER($J30),(($AC30*$N30+$AD30*$O30+$AE30*$P30+$AF30*$Q30)*$X30+$AL30)*$AG30,"") | AI30: {=IF(ISNUMBER($J30),$AH30*(1+INDEX('Cálculos'!$C$331:$F$331,$J30)),"")} | AJ30: {=IF(ISNUMBER($J30),$AH30*(1+MIN(INDEX('Cálculos'!$C$330:$F$330,$J30),1)*INDEX('Cálculos'!$C$331:$F$331,$J30)),"")} | AK30: =IF(ISNUMBER($J30),'Fixo (cálculo)'!$AF30,"") | AL30: =IF(ISNUMBER($J30),$AK30*(1+$U30)*$V30*$W30,"")
D31: Todos | F31: =IF($A31="","",IF(ISNUMBER(MATCH($A31,'Golpes extras'!$A$2:$A$101,0)),"Sim","Não")) | G31: {=IF($A31="","",IF($F31="Sim",INDEX('Golpes extras'!$B$2:$B$101,MATCH($A31,'Golpes extras'!$A$2:$A$101,0))&"",$A31))} | H31: =IF($G31="","",IFERROR(MATCH($G31,L_Golpes!$A$2:$A$6000,0),"")) | I31: {=IF($A31="","",IF(ISNUMBER($H31),INDEX(L_Golpes!$B$2:$B$6000,$H31),IF(IFERROR(INDEX('Golpes extras'!$C$2:$C$101,MATCH($A31,'Golpes extras'!$A$2:$A$101,0))&"","")<>"",INDEX('Golpes extras'!$C$2:$C$101,MATCH($A31,'Golpes extras'!$A$2:$A$101,0))&"","golpe?")))} | J31: =IF(OR($I31="",$I31="golpe?"),"",IFERROR(MATCH($I31,Time!$B$4:$E$4,0),"fora do time")) | K31: {=IF(ISNUMBER($J31),IF(IFERROR(INDEX('Golpes extras'!$D$2:$D$101,MATCH($A31,'Golpes extras'!$A$2:$A$101,0))&"","")<>"",INDEX('Golpes extras'!$D$2:$D$101,MATCH($A31,'Golpes extras'!$A$2:$A$101,0))&"",IF(ISNUMBER($H31),INDEX(L_Golpes!$D$2:$D$6000,$H31),"Outro")),"")} | L31: {=IF(ISNUMBER($J31),IF(ISNUMBER($H31),INDEX(L_Golpes!$C$2:$C$6000,$H31),""),"")} | M31: {=IF(ISNUMBER($J31),IF($L31="Normal",INDEX('Cálculos'!$C$14:$F$14,$J31),IF($L31="Habilidade",INDEX('Cálculos'!$C$15:$F$15,$J31),IF($L31="Supremo",INDEX('Cálculos'!$C$16:$F$16,$J31),""))),"")} | N31: {=IF(ISNUMBER($J31),IF(ISNUMBER($H31),INDEX(L_Golpes!$F$2:$T$6000,$H31,MAX(1,MIN(15,$M31))),0)+IF($F31="Sim",N(INDEX('Golpes extras'!$E$2:$E$101,MATCH($A31,'Golpes extras'!$A$2:$A$101,0))),0),"")} | O31: {=IF(ISNUMBER($J31),IF(ISNUMBER($H31),INDEX(L_Golpes!$U$2:$AI$6000,$H31,MAX(1,MIN(15,$M31))),0)+IF($F31="Sim",N(INDEX('Golpes extras'!$F$2:$F$101,MATCH($A31,'Golpes extras'!$A$2:$A$101,0))),0),"")} | P31: {=IF(ISNUMBER($J31),IF(ISNUMBER($H31),INDEX(L_Golpes!$AJ$2:$AX$6000,$H31,MAX(1,MIN(15,$M31))),0)+IF($F31="Sim",N(INDEX('Golpes extras'!$G$2:$G$101,MATCH($A31,'Golpes extras'!$A$2:$A$101,0))),0),"")} | Q31: {=IF(ISNUMBER($J31),IF(ISNUMBER($H31),INDEX(L_Golpes!$AY$2:$BM$6000,$H31,MAX(1,MIN(15,$M31))),0)+IF($F31="Sim",N(INDEX('Golpes extras'!$H$2:$H$101,MATCH($A31,'Golpes extras'!$A$2:$A$101,0))),0),"")} | R31: {=IF(ISNUMBER($J31),INDEX('Cálculos'!$C$19:$F$19,$J31),"")} | S31: =IF(ISNUMBER($J31),IF(AND($C31="Derreter",OR($R31="Pyro",$R31="Cryo")),"Derreter",IF(AND($C31="Vaporizar",OR($R31="Pyro",$R31="Hydro")),"Vaporizar","Nenhuma")),"") | T31: =IF(ISNUMBER($J31),IF(OR($D31="Não",$D31=FALSE),'Perfis de buff'!$A$8,IF(OR($D31="",$D31="Sim",$D31=TRUE),'Perfis de buff'!$A$4,$D31)),"") | U31: {=IF(ISNUMBER($J31),INDEX('Cálculos'!$C$113:$F$113,$J31)+IF($K31="Normal",INDEX('Cálculos'!$C$114:$F$114,$J31),IF($K31="Carregado",INDEX('Cálculos'!$C$115:$F$115,$J31),IF($K31="Habilidade",INDEX('Cálculos'!$C$116:$F$116,$J31),IF($K31="Supremo",INDEX('Cálculos'!$C$117:$F$117,$J31),0))))+INDEX('Cálculos'!$C$143:$F$147,IFERROR(MATCH($T31,'Perfis de buff'!$A$4:$A$8,0),1),$J31)+IF($K31="Normal",INDEX('Cálculos'!$C$148:$F$152,IFERROR(MATCH($T31,'Perfis de buff'!$A$4:$A$8,0),1),$J31),IF($K31="Carregado",INDEX('Cálculos'!$C$153:$F$157,IFERROR(MATCH($T31,'Perfis de buff'!$A$4:$A$8,0),1),$J31),IF($K31="Habilidade",INDEX('Cálculos'!$C$158:$F$162,IFERROR(MATCH($T31,'Perfis de buff'!$A$4:$A$8,0),1),$J31),IF($K31="Supremo",INDEX('Cálculos'!$C$163:$F$167,IFERROR(MATCH($T31,'Perfis de buff'!$A$4:$A$8,0),1),$J31),0))))+N($E31),"")} | V31: {=IF(ISNUMBER($J31),INDEX('Cálculos'!$C$180:$F$180,$J31),"")} | W31: {=IF(ISNUMBER($J31),INDEX('Cálculos'!$C$182:$F$182,$J31),"")} | X31: =IF(ISNUMBER($J31),IF($B31="",1,$B31)*(1+$U31)*$V31*$W31,"") | Y31: =IF(ISNUMBER($J31),$X31*$N31,"") | Z31: =IF(ISNUMBER($J31),$X31*$O31,"") | AA31: =IF(ISNUMBER($J31),$X31*$P31,"") | AB31: =IF(ISNUMBER($J31),$X31*$Q31,"") | AC31: {=IF(ISNUMBER($J31),INDEX('Cálculos'!$C$332:$F$336,IFERROR(MATCH($T31,'Perfis de buff'!$A$4:$A$8,0),1),$J31),"")} | AD31: {=IF(ISNUMBER($J31),INDEX('Cálculos'!$C$339:$F$343,IFERROR(MATCH($T31,'Perfis de buff'!$A$4:$A$8,0),1),$J31),"")} | AE31: {=IF(ISNUMBER($J31),INDEX('Cálculos'!$C$337:$F$337,$J31),"")} | AF31: {=IF(ISNUMBER($J31),INDEX('Cálculos'!$C$338:$F$338,$J31),"")} | AG31: {=IF(ISNUMBER($J31),IF($S31="Derreter",INDEX('Cálculos'!$C$124:$F$124,$J31)*(1+2.78*$AD31/($AD31+1400)+INDEX('Cálculos'!$C$122:$F$122,$J31)),IF($S31="Vaporizar",INDEX('Cálculos'!$C$125:$F$125,$J31)*(1+2.78*$AD31/($AD31+1400)+INDEX('Cálculos'!$C$123:$F$123,$J31)),1)),"")} | AH31: =IF(ISNUMBER($J31),(($AC31*$N31+$AD31*$O31+$AE31*$P31+$AF31*$Q31)*$X31+$AL31)*$AG31,"") | AI31: {=IF(ISNUMBER($J31),$AH31*(1+INDEX('Cálculos'!$C$331:$F$331,$J31)),"")} | AJ31: {=IF(ISNUMBER($J31),$AH31*(1+MIN(INDEX('Cálculos'!$C$330:$F$330,$J31),1)*INDEX('Cálculos'!$C$331:$F$331,$J31)),"")} | AK31: =IF(ISNUMBER($J31),'Fixo (cálculo)'!$AF31,"") | AL31: =IF(ISNUMBER($J31),$AK31*(1+$U31)*$V31*$W31,"")
D32: Todos | F32: =IF($A32="","",IF(ISNUMBER(MATCH($A32,'Golpes extras'!$A$2:$A$101,0)),"Sim","Não")) | G32: {=IF($A32="","",IF($F32="Sim",INDEX('Golpes extras'!$B$2:$B$101,MATCH($A32,'Golpes extras'!$A$2:$A$101,0))&"",$A32))} | H32: =IF($G32="","",IFERROR(MATCH($G32,L_Golpes!$A$2:$A$6000,0),"")) | I32: {=IF($A32="","",IF(ISNUMBER($H32),INDEX(L_Golpes!$B$2:$B$6000,$H32),IF(IFERROR(INDEX('Golpes extras'!$C$2:$C$101,MATCH($A32,'Golpes extras'!$A$2:$A$101,0))&"","")<>"",INDEX('Golpes extras'!$C$2:$C$101,MATCH($A32,'Golpes extras'!$A$2:$A$101,0))&"","golpe?")))} | J32: =IF(OR($I32="",$I32="golpe?"),"",IFERROR(MATCH($I32,Time!$B$4:$E$4,0),"fora do time")) | K32: {=IF(ISNUMBER($J32),IF(IFERROR(INDEX('Golpes extras'!$D$2:$D$101,MATCH($A32,'Golpes extras'!$A$2:$A$101,0))&"","")<>"",INDEX('Golpes extras'!$D$2:$D$101,MATCH($A32,'Golpes extras'!$A$2:$A$101,0))&"",IF(ISNUMBER($H32),INDEX(L_Golpes!$D$2:$D$6000,$H32),"Outro")),"")} | L32: {=IF(ISNUMBER($J32),IF(ISNUMBER($H32),INDEX(L_Golpes!$C$2:$C$6000,$H32),""),"")} | M32: {=IF(ISNUMBER($J32),IF($L32="Normal",INDEX('Cálculos'!$C$14:$F$14,$J32),IF($L32="Habilidade",INDEX('Cálculos'!$C$15:$F$15,$J32),IF($L32="Supremo",INDEX('Cálculos'!$C$16:$F$16,$J32),""))),"")} | N32: {=IF(ISNUMBER($J32),IF(ISNUMBER($H32),INDEX(L_Golpes!$F$2:$T$6000,$H32,MAX(1,MIN(15,$M32))),0)+IF($F32="Sim",N(INDEX('Golpes extras'!$E$2:$E$101,MATCH($A32,'Golpes extras'!$A$2:$A$101,0))),0),"")} | O32: {=IF(ISNUMBER($J32),IF(ISNUMBER($H32),INDEX(L_Golpes!$U$2:$AI$6000,$H32,MAX(1,MIN(15,$M32))),0)+IF($F32="Sim",N(INDEX('Golpes extras'!$F$2:$F$101,MATCH($A32,'Golpes extras'!$A$2:$A$101,0))),0),"")} | P32: {=IF(ISNUMBER($J32),IF(ISNUMBER($H32),INDEX(L_Golpes!$AJ$2:$AX$6000,$H32,MAX(1,MIN(15,$M32))),0)+IF($F32="Sim",N(INDEX('Golpes extras'!$G$2:$G$101,MATCH($A32,'Golpes extras'!$A$2:$A$101,0))),0),"")} | Q32: {=IF(ISNUMBER($J32),IF(ISNUMBER($H32),INDEX(L_Golpes!$AY$2:$BM$6000,$H32,MAX(1,MIN(15,$M32))),0)+IF($F32="Sim",N(INDEX('Golpes extras'!$H$2:$H$101,MATCH($A32,'Golpes extras'!$A$2:$A$101,0))),0),"")} | R32: {=IF(ISNUMBER($J32),INDEX('Cálculos'!$C$19:$F$19,$J32),"")} | S32: =IF(ISNUMBER($J32),IF(AND($C32="Derreter",OR($R32="Pyro",$R32="Cryo")),"Derreter",IF(AND($C32="Vaporizar",OR($R32="Pyro",$R32="Hydro")),"Vaporizar","Nenhuma")),"") | T32: =IF(ISNUMBER($J32),IF(OR($D32="Não",$D32=FALSE),'Perfis de buff'!$A$8,IF(OR($D32="",$D32="Sim",$D32=TRUE),'Perfis de buff'!$A$4,$D32)),"") | U32: {=IF(ISNUMBER($J32),INDEX('Cálculos'!$C$113:$F$113,$J32)+IF($K32="Normal",INDEX('Cálculos'!$C$114:$F$114,$J32),IF($K32="Carregado",INDEX('Cálculos'!$C$115:$F$115,$J32),IF($K32="Habilidade",INDEX('Cálculos'!$C$116:$F$116,$J32),IF($K32="Supremo",INDEX('Cálculos'!$C$117:$F$117,$J32),0))))+INDEX('Cálculos'!$C$143:$F$147,IFERROR(MATCH($T32,'Perfis de buff'!$A$4:$A$8,0),1),$J32)+IF($K32="Normal",INDEX('Cálculos'!$C$148:$F$152,IFERROR(MATCH($T32,'Perfis de buff'!$A$4:$A$8,0),1),$J32),IF($K32="Carregado",INDEX('Cálculos'!$C$153:$F$157,IFERROR(MATCH($T32,'Perfis de buff'!$A$4:$A$8,0),1),$J32),IF($K32="Habilidade",INDEX('Cálculos'!$C$158:$F$162,IFERROR(MATCH($T32,'Perfis de buff'!$A$4:$A$8,0),1),$J32),IF($K32="Supremo",INDEX('Cálculos'!$C$163:$F$167,IFERROR(MATCH($T32,'Perfis de buff'!$A$4:$A$8,0),1),$J32),0))))+N($E32),"")} | V32: {=IF(ISNUMBER($J32),INDEX('Cálculos'!$C$180:$F$180,$J32),"")} | W32: {=IF(ISNUMBER($J32),INDEX('Cálculos'!$C$182:$F$182,$J32),"")} | X32: =IF(ISNUMBER($J32),IF($B32="",1,$B32)*(1+$U32)*$V32*$W32,"") | Y32: =IF(ISNUMBER($J32),$X32*$N32,"") | Z32: =IF(ISNUMBER($J32),$X32*$O32,"") | AA32: =IF(ISNUMBER($J32),$X32*$P32,"") | AB32: =IF(ISNUMBER($J32),$X32*$Q32,"") | AC32: {=IF(ISNUMBER($J32),INDEX('Cálculos'!$C$332:$F$336,IFERROR(MATCH($T32,'Perfis de buff'!$A$4:$A$8,0),1),$J32),"")} | AD32: {=IF(ISNUMBER($J32),INDEX('Cálculos'!$C$339:$F$343,IFERROR(MATCH($T32,'Perfis de buff'!$A$4:$A$8,0),1),$J32),"")} | AE32: {=IF(ISNUMBER($J32),INDEX('Cálculos'!$C$337:$F$337,$J32),"")} | AF32: {=IF(ISNUMBER($J32),INDEX('Cálculos'!$C$338:$F$338,$J32),"")} | AG32: {=IF(ISNUMBER($J32),IF($S32="Derreter",INDEX('Cálculos'!$C$124:$F$124,$J32)*(1+2.78*$AD32/($AD32+1400)+INDEX('Cálculos'!$C$122:$F$122,$J32)),IF($S32="Vaporizar",INDEX('Cálculos'!$C$125:$F$125,$J32)*(1+2.78*$AD32/($AD32+1400)+INDEX('Cálculos'!$C$123:$F$123,$J32)),1)),"")} | AH32: =IF(ISNUMBER($J32),(($AC32*$N32+$AD32*$O32+$AE32*$P32+$AF32*$Q32)*$X32+$AL32)*$AG32,"") | AI32: {=IF(ISNUMBER($J32),$AH32*(1+INDEX('Cálculos'!$C$331:$F$331,$J32)),"")} | AJ32: {=IF(ISNUMBER($J32),$AH32*(1+MIN(INDEX('Cálculos'!$C$330:$F$330,$J32),1)*INDEX('Cálculos'!$C$331:$F$331,$J32)),"")} | AK32: =IF(ISNUMBER($J32),'Fixo (cálculo)'!$AF32,"") | AL32: =IF(ISNUMBER($J32),$AK32*(1+$U32)*$V32*$W32,"")
D33: Todos | F33: =IF($A33="","",IF(ISNUMBER(MATCH($A33,'Golpes extras'!$A$2:$A$101,0)),"Sim","Não")) | G33: {=IF($A33="","",IF($F33="Sim",INDEX('Golpes extras'!$B$2:$B$101,MATCH($A33,'Golpes extras'!$A$2:$A$101,0))&"",$A33))} | H33: =IF($G33="","",IFERROR(MATCH($G33,L_Golpes!$A$2:$A$6000,0),"")) | I33: {=IF($A33="","",IF(ISNUMBER($H33),INDEX(L_Golpes!$B$2:$B$6000,$H33),IF(IFERROR(INDEX('Golpes extras'!$C$2:$C$101,MATCH($A33,'Golpes extras'!$A$2:$A$101,0))&"","")<>"",INDEX('Golpes extras'!$C$2:$C$101,MATCH($A33,'Golpes extras'!$A$2:$A$101,0))&"","golpe?")))} | J33: =IF(OR($I33="",$I33="golpe?"),"",IFERROR(MATCH($I33,Time!$B$4:$E$4,0),"fora do time")) | K33: {=IF(ISNUMBER($J33),IF(IFERROR(INDEX('Golpes extras'!$D$2:$D$101,MATCH($A33,'Golpes extras'!$A$2:$A$101,0))&"","")<>"",INDEX('Golpes extras'!$D$2:$D$101,MATCH($A33,'Golpes extras'!$A$2:$A$101,0))&"",IF(ISNUMBER($H33),INDEX(L_Golpes!$D$2:$D$6000,$H33),"Outro")),"")} | L33: {=IF(ISNUMBER($J33),IF(ISNUMBER($H33),INDEX(L_Golpes!$C$2:$C$6000,$H33),""),"")} | M33: {=IF(ISNUMBER($J33),IF($L33="Normal",INDEX('Cálculos'!$C$14:$F$14,$J33),IF($L33="Habilidade",INDEX('Cálculos'!$C$15:$F$15,$J33),IF($L33="Supremo",INDEX('Cálculos'!$C$16:$F$16,$J33),""))),"")} | N33: {=IF(ISNUMBER($J33),IF(ISNUMBER($H33),INDEX(L_Golpes!$F$2:$T$6000,$H33,MAX(1,MIN(15,$M33))),0)+IF($F33="Sim",N(INDEX('Golpes extras'!$E$2:$E$101,MATCH($A33,'Golpes extras'!$A$2:$A$101,0))),0),"")} | O33: {=IF(ISNUMBER($J33),IF(ISNUMBER($H33),INDEX(L_Golpes!$U$2:$AI$6000,$H33,MAX(1,MIN(15,$M33))),0)+IF($F33="Sim",N(INDEX('Golpes extras'!$F$2:$F$101,MATCH($A33,'Golpes extras'!$A$2:$A$101,0))),0),"")} | P33: {=IF(ISNUMBER($J33),IF(ISNUMBER($H33),INDEX(L_Golpes!$AJ$2:$AX$6000,$H33,MAX(1,MIN(15,$M33))),0)+IF($F33="Sim",N(INDEX('Golpes extras'!$G$2:$G$101,MATCH($A33,'Golpes extras'!$A$2:$A$101,0))),0),"")} | Q33: {=IF(ISNUMBER($J33),IF(ISNUMBER($H33),INDEX(L_Golpes!$AY$2:$BM$6000,$H33,MAX(1,MIN(15,$M33))),0)+IF($F33="Sim",N(INDEX('Golpes extras'!$H$2:$H$101,MATCH($A33,'Golpes extras'!$A$2:$A$101,0))),0),"")} | R33: {=IF(ISNUMBER($J33),INDEX('Cálculos'!$C$19:$F$19,$J33),"")} | S33: =IF(ISNUMBER($J33),IF(AND($C33="Derreter",OR($R33="Pyro",$R33="Cryo")),"Derreter",IF(AND($C33="Vaporizar",OR($R33="Pyro",$R33="Hydro")),"Vaporizar","Nenhuma")),"") | T33: =IF(ISNUMBER($J33),IF(OR($D33="Não",$D33=FALSE),'Perfis de buff'!$A$8,IF(OR($D33="",$D33="Sim",$D33=TRUE),'Perfis de buff'!$A$4,$D33)),"") | U33: {=IF(ISNUMBER($J33),INDEX('Cálculos'!$C$113:$F$113,$J33)+IF($K33="Normal",INDEX('Cálculos'!$C$114:$F$114,$J33),IF($K33="Carregado",INDEX('Cálculos'!$C$115:$F$115,$J33),IF($K33="Habilidade",INDEX('Cálculos'!$C$116:$F$116,$J33),IF($K33="Supremo",INDEX('Cálculos'!$C$117:$F$117,$J33),0))))+INDEX('Cálculos'!$C$143:$F$147,IFERROR(MATCH($T33,'Perfis de buff'!$A$4:$A$8,0),1),$J33)+IF($K33="Normal",INDEX('Cálculos'!$C$148:$F$152,IFERROR(MATCH($T33,'Perfis de buff'!$A$4:$A$8,0),1),$J33),IF($K33="Carregado",INDEX('Cálculos'!$C$153:$F$157,IFERROR(MATCH($T33,'Perfis de buff'!$A$4:$A$8,0),1),$J33),IF($K33="Habilidade",INDEX('Cálculos'!$C$158:$F$162,IFERROR(MATCH($T33,'Perfis de buff'!$A$4:$A$8,0),1),$J33),IF($K33="Supremo",INDEX('Cálculos'!$C$163:$F$167,IFERROR(MATCH($T33,'Perfis de buff'!$A$4:$A$8,0),1),$J33),0))))+N($E33),"")} | V33: {=IF(ISNUMBER($J33),INDEX('Cálculos'!$C$180:$F$180,$J33),"")} | W33: {=IF(ISNUMBER($J33),INDEX('Cálculos'!$C$182:$F$182,$J33),"")} | X33: =IF(ISNUMBER($J33),IF($B33="",1,$B33)*(1+$U33)*$V33*$W33,"") | Y33: =IF(ISNUMBER($J33),$X33*$N33,"") | Z33: =IF(ISNUMBER($J33),$X33*$O33,"") | AA33: =IF(ISNUMBER($J33),$X33*$P33,"") | AB33: =IF(ISNUMBER($J33),$X33*$Q33,"") | AC33: {=IF(ISNUMBER($J33),INDEX('Cálculos'!$C$332:$F$336,IFERROR(MATCH($T33,'Perfis de buff'!$A$4:$A$8,0),1),$J33),"")} | AD33: {=IF(ISNUMBER($J33),INDEX('Cálculos'!$C$339:$F$343,IFERROR(MATCH($T33,'Perfis de buff'!$A$4:$A$8,0),1),$J33),"")} | AE33: {=IF(ISNUMBER($J33),INDEX('Cálculos'!$C$337:$F$337,$J33),"")} | AF33: {=IF(ISNUMBER($J33),INDEX('Cálculos'!$C$338:$F$338,$J33),"")} | AG33: {=IF(ISNUMBER($J33),IF($S33="Derreter",INDEX('Cálculos'!$C$124:$F$124,$J33)*(1+2.78*$AD33/($AD33+1400)+INDEX('Cálculos'!$C$122:$F$122,$J33)),IF($S33="Vaporizar",INDEX('Cálculos'!$C$125:$F$125,$J33)*(1+2.78*$AD33/($AD33+1400)+INDEX('Cálculos'!$C$123:$F$123,$J33)),1)),"")} | AH33: =IF(ISNUMBER($J33),(($AC33*$N33+$AD33*$O33+$AE33*$P33+$AF33*$Q33)*$X33+$AL33)*$AG33,"") | AI33: {=IF(ISNUMBER($J33),$AH33*(1+INDEX('Cálculos'!$C$331:$F$331,$J33)),"")} | AJ33: {=IF(ISNUMBER($J33),$AH33*(1+MIN(INDEX('Cálculos'!$C$330:$F$330,$J33),1)*INDEX('Cálculos'!$C$331:$F$331,$J33)),"")} | AK33: =IF(ISNUMBER($J33),'Fixo (cálculo)'!$AF33,"") | AL33: =IF(ISNUMBER($J33),$AK33*(1+$U33)*$V33*$W33,"")
D34: Todos | F34: =IF($A34="","",IF(ISNUMBER(MATCH($A34,'Golpes extras'!$A$2:$A$101,0)),"Sim","Não")) | G34: {=IF($A34="","",IF($F34="Sim",INDEX('Golpes extras'!$B$2:$B$101,MATCH($A34,'Golpes extras'!$A$2:$A$101,0))&"",$A34))} | H34: =IF($G34="","",IFERROR(MATCH($G34,L_Golpes!$A$2:$A$6000,0),"")) | I34: {=IF($A34="","",IF(ISNUMBER($H34),INDEX(L_Golpes!$B$2:$B$6000,$H34),IF(IFERROR(INDEX('Golpes extras'!$C$2:$C$101,MATCH($A34,'Golpes extras'!$A$2:$A$101,0))&"","")<>"",INDEX('Golpes extras'!$C$2:$C$101,MATCH($A34,'Golpes extras'!$A$2:$A$101,0))&"","golpe?")))} | J34: =IF(OR($I34="",$I34="golpe?"),"",IFERROR(MATCH($I34,Time!$B$4:$E$4,0),"fora do time")) | K34: {=IF(ISNUMBER($J34),IF(IFERROR(INDEX('Golpes extras'!$D$2:$D$101,MATCH($A34,'Golpes extras'!$A$2:$A$101,0))&"","")<>"",INDEX('Golpes extras'!$D$2:$D$101,MATCH($A34,'Golpes extras'!$A$2:$A$101,0))&"",IF(ISNUMBER($H34),INDEX(L_Golpes!$D$2:$D$6000,$H34),"Outro")),"")} | L34: {=IF(ISNUMBER($J34),IF(ISNUMBER($H34),INDEX(L_Golpes!$C$2:$C$6000,$H34),""),"")} | M34: {=IF(ISNUMBER($J34),IF($L34="Normal",INDEX('Cálculos'!$C$14:$F$14,$J34),IF($L34="Habilidade",INDEX('Cálculos'!$C$15:$F$15,$J34),IF($L34="Supremo",INDEX('Cálculos'!$C$16:$F$16,$J34),""))),"")} | N34: {=IF(ISNUMBER($J34),IF(ISNUMBER($H34),INDEX(L_Golpes!$F$2:$T$6000,$H34,MAX(1,MIN(15,$M34))),0)+IF($F34="Sim",N(INDEX('Golpes extras'!$E$2:$E$101,MATCH($A34,'Golpes extras'!$A$2:$A$101,0))),0),"")} | O34: {=IF(ISNUMBER($J34),IF(ISNUMBER($H34),INDEX(L_Golpes!$U$2:$AI$6000,$H34,MAX(1,MIN(15,$M34))),0)+IF($F34="Sim",N(INDEX('Golpes extras'!$F$2:$F$101,MATCH($A34,'Golpes extras'!$A$2:$A$101,0))),0),"")} | P34: {=IF(ISNUMBER($J34),IF(ISNUMBER($H34),INDEX(L_Golpes!$AJ$2:$AX$6000,$H34,MAX(1,MIN(15,$M34))),0)+IF($F34="Sim",N(INDEX('Golpes extras'!$G$2:$G$101,MATCH($A34,'Golpes extras'!$A$2:$A$101,0))),0),"")} | Q34: {=IF(ISNUMBER($J34),IF(ISNUMBER($H34),INDEX(L_Golpes!$AY$2:$BM$6000,$H34,MAX(1,MIN(15,$M34))),0)+IF($F34="Sim",N(INDEX('Golpes extras'!$H$2:$H$101,MATCH($A34,'Golpes extras'!$A$2:$A$101,0))),0),"")} | R34: {=IF(ISNUMBER($J34),INDEX('Cálculos'!$C$19:$F$19,$J34),"")} | S34: =IF(ISNUMBER($J34),IF(AND($C34="Derreter",OR($R34="Pyro",$R34="Cryo")),"Derreter",IF(AND($C34="Vaporizar",OR($R34="Pyro",$R34="Hydro")),"Vaporizar","Nenhuma")),"") | T34: =IF(ISNUMBER($J34),IF(OR($D34="Não",$D34=FALSE),'Perfis de buff'!$A$8,IF(OR($D34="",$D34="Sim",$D34=TRUE),'Perfis de buff'!$A$4,$D34)),"") | U34: {=IF(ISNUMBER($J34),INDEX('Cálculos'!$C$113:$F$113,$J34)+IF($K34="Normal",INDEX('Cálculos'!$C$114:$F$114,$J34),IF($K34="Carregado",INDEX('Cálculos'!$C$115:$F$115,$J34),IF($K34="Habilidade",INDEX('Cálculos'!$C$116:$F$116,$J34),IF($K34="Supremo",INDEX('Cálculos'!$C$117:$F$117,$J34),0))))+INDEX('Cálculos'!$C$143:$F$147,IFERROR(MATCH($T34,'Perfis de buff'!$A$4:$A$8,0),1),$J34)+IF($K34="Normal",INDEX('Cálculos'!$C$148:$F$152,IFERROR(MATCH($T34,'Perfis de buff'!$A$4:$A$8,0),1),$J34),IF($K34="Carregado",INDEX('Cálculos'!$C$153:$F$157,IFERROR(MATCH($T34,'Perfis de buff'!$A$4:$A$8,0),1),$J34),IF($K34="Habilidade",INDEX('Cálculos'!$C$158:$F$162,IFERROR(MATCH($T34,'Perfis de buff'!$A$4:$A$8,0),1),$J34),IF($K34="Supremo",INDEX('Cálculos'!$C$163:$F$167,IFERROR(MATCH($T34,'Perfis de buff'!$A$4:$A$8,0),1),$J34),0))))+N($E34),"")} | V34: {=IF(ISNUMBER($J34),INDEX('Cálculos'!$C$180:$F$180,$J34),"")} | W34: {=IF(ISNUMBER($J34),INDEX('Cálculos'!$C$182:$F$182,$J34),"")} | X34: =IF(ISNUMBER($J34),IF($B34="",1,$B34)*(1+$U34)*$V34*$W34,"") | Y34: =IF(ISNUMBER($J34),$X34*$N34,"") | Z34: =IF(ISNUMBER($J34),$X34*$O34,"") | AA34: =IF(ISNUMBER($J34),$X34*$P34,"") | AB34: =IF(ISNUMBER($J34),$X34*$Q34,"") | AC34: {=IF(ISNUMBER($J34),INDEX('Cálculos'!$C$332:$F$336,IFERROR(MATCH($T34,'Perfis de buff'!$A$4:$A$8,0),1),$J34),"")} | AD34: {=IF(ISNUMBER($J34),INDEX('Cálculos'!$C$339:$F$343,IFERROR(MATCH($T34,'Perfis de buff'!$A$4:$A$8,0),1),$J34),"")} | AE34: {=IF(ISNUMBER($J34),INDEX('Cálculos'!$C$337:$F$337,$J34),"")} | AF34: {=IF(ISNUMBER($J34),INDEX('Cálculos'!$C$338:$F$338,$J34),"")} | AG34: {=IF(ISNUMBER($J34),IF($S34="Derreter",INDEX('Cálculos'!$C$124:$F$124,$J34)*(1+2.78*$AD34/($AD34+1400)+INDEX('Cálculos'!$C$122:$F$122,$J34)),IF($S34="Vaporizar",INDEX('Cálculos'!$C$125:$F$125,$J34)*(1+2.78*$AD34/($AD34+1400)+INDEX('Cálculos'!$C$123:$F$123,$J34)),1)),"")} | AH34: =IF(ISNUMBER($J34),(($AC34*$N34+$AD34*$O34+$AE34*$P34+$AF34*$Q34)*$X34+$AL34)*$AG34,"") | AI34: {=IF(ISNUMBER($J34),$AH34*(1+INDEX('Cálculos'!$C$331:$F$331,$J34)),"")} | AJ34: {=IF(ISNUMBER($J34),$AH34*(1+MIN(INDEX('Cálculos'!$C$330:$F$330,$J34),1)*INDEX('Cálculos'!$C$331:$F$331,$J34)),"")} | AK34: =IF(ISNUMBER($J34),'Fixo (cálculo)'!$AF34,"") | AL34: =IF(ISNUMBER($J34),$AK34*(1+$U34)*$V34*$W34,"")
D35: Todos | F35: =IF($A35="","",IF(ISNUMBER(MATCH($A35,'Golpes extras'!$A$2:$A$101,0)),"Sim","Não")) | G35: {=IF($A35="","",IF($F35="Sim",INDEX('Golpes extras'!$B$2:$B$101,MATCH($A35,'Golpes extras'!$A$2:$A$101,0))&"",$A35))} | H35: =IF($G35="","",IFERROR(MATCH($G35,L_Golpes!$A$2:$A$6000,0),"")) | I35: {=IF($A35="","",IF(ISNUMBER($H35),INDEX(L_Golpes!$B$2:$B$6000,$H35),IF(IFERROR(INDEX('Golpes extras'!$C$2:$C$101,MATCH($A35,'Golpes extras'!$A$2:$A$101,0))&"","")<>"",INDEX('Golpes extras'!$C$2:$C$101,MATCH($A35,'Golpes extras'!$A$2:$A$101,0))&"","golpe?")))} | J35: =IF(OR($I35="",$I35="golpe?"),"",IFERROR(MATCH($I35,Time!$B$4:$E$4,0),"fora do time")) | K35: {=IF(ISNUMBER($J35),IF(IFERROR(INDEX('Golpes extras'!$D$2:$D$101,MATCH($A35,'Golpes extras'!$A$2:$A$101,0))&"","")<>"",INDEX('Golpes extras'!$D$2:$D$101,MATCH($A35,'Golpes extras'!$A$2:$A$101,0))&"",IF(ISNUMBER($H35),INDEX(L_Golpes!$D$2:$D$6000,$H35),"Outro")),"")} | L35: {=IF(ISNUMBER($J35),IF(ISNUMBER($H35),INDEX(L_Golpes!$C$2:$C$6000,$H35),""),"")} | M35: {=IF(ISNUMBER($J35),IF($L35="Normal",INDEX('Cálculos'!$C$14:$F$14,$J35),IF($L35="Habilidade",INDEX('Cálculos'!$C$15:$F$15,$J35),IF($L35="Supremo",INDEX('Cálculos'!$C$16:$F$16,$J35),""))),"")} | N35: {=IF(ISNUMBER($J35),IF(ISNUMBER($H35),INDEX(L_Golpes!$F$2:$T$6000,$H35,MAX(1,MIN(15,$M35))),0)+IF($F35="Sim",N(INDEX('Golpes extras'!$E$2:$E$101,MATCH($A35,'Golpes extras'!$A$2:$A$101,0))),0),"")} | O35: {=IF(ISNUMBER($J35),IF(ISNUMBER($H35),INDEX(L_Golpes!$U$2:$AI$6000,$H35,MAX(1,MIN(15,$M35))),0)+IF($F35="Sim",N(INDEX('Golpes extras'!$F$2:$F$101,MATCH($A35,'Golpes extras'!$A$2:$A$101,0))),0),"")} | P35: {=IF(ISNUMBER($J35),IF(ISNUMBER($H35),INDEX(L_Golpes!$AJ$2:$AX$6000,$H35,MAX(1,MIN(15,$M35))),0)+IF($F35="Sim",N(INDEX('Golpes extras'!$G$2:$G$101,MATCH($A35,'Golpes extras'!$A$2:$A$101,0))),0),"")} | Q35: {=IF(ISNUMBER($J35),IF(ISNUMBER($H35),INDEX(L_Golpes!$AY$2:$BM$6000,$H35,MAX(1,MIN(15,$M35))),0)+IF($F35="Sim",N(INDEX('Golpes extras'!$H$2:$H$101,MATCH($A35,'Golpes extras'!$A$2:$A$101,0))),0),"")} | R35: {=IF(ISNUMBER($J35),INDEX('Cálculos'!$C$19:$F$19,$J35),"")} | S35: =IF(ISNUMBER($J35),IF(AND($C35="Derreter",OR($R35="Pyro",$R35="Cryo")),"Derreter",IF(AND($C35="Vaporizar",OR($R35="Pyro",$R35="Hydro")),"Vaporizar","Nenhuma")),"") | T35: =IF(ISNUMBER($J35),IF(OR($D35="Não",$D35=FALSE),'Perfis de buff'!$A$8,IF(OR($D35="",$D35="Sim",$D35=TRUE),'Perfis de buff'!$A$4,$D35)),"") | U35: {=IF(ISNUMBER($J35),INDEX('Cálculos'!$C$113:$F$113,$J35)+IF($K35="Normal",INDEX('Cálculos'!$C$114:$F$114,$J35),IF($K35="Carregado",INDEX('Cálculos'!$C$115:$F$115,$J35),IF($K35="Habilidade",INDEX('Cálculos'!$C$116:$F$116,$J35),IF($K35="Supremo",INDEX('Cálculos'!$C$117:$F$117,$J35),0))))+INDEX('Cálculos'!$C$143:$F$147,IFERROR(MATCH($T35,'Perfis de buff'!$A$4:$A$8,0),1),$J35)+IF($K35="Normal",INDEX('Cálculos'!$C$148:$F$152,IFERROR(MATCH($T35,'Perfis de buff'!$A$4:$A$8,0),1),$J35),IF($K35="Carregado",INDEX('Cálculos'!$C$153:$F$157,IFERROR(MATCH($T35,'Perfis de buff'!$A$4:$A$8,0),1),$J35),IF($K35="Habilidade",INDEX('Cálculos'!$C$158:$F$162,IFERROR(MATCH($T35,'Perfis de buff'!$A$4:$A$8,0),1),$J35),IF($K35="Supremo",INDEX('Cálculos'!$C$163:$F$167,IFERROR(MATCH($T35,'Perfis de buff'!$A$4:$A$8,0),1),$J35),0))))+N($E35),"")} | V35: {=IF(ISNUMBER($J35),INDEX('Cálculos'!$C$180:$F$180,$J35),"")} | W35: {=IF(ISNUMBER($J35),INDEX('Cálculos'!$C$182:$F$182,$J35),"")} | X35: =IF(ISNUMBER($J35),IF($B35="",1,$B35)*(1+$U35)*$V35*$W35,"") | Y35: =IF(ISNUMBER($J35),$X35*$N35,"") | Z35: =IF(ISNUMBER($J35),$X35*$O35,"") | AA35: =IF(ISNUMBER($J35),$X35*$P35,"") | AB35: =IF(ISNUMBER($J35),$X35*$Q35,"") | AC35: {=IF(ISNUMBER($J35),INDEX('Cálculos'!$C$332:$F$336,IFERROR(MATCH($T35,'Perfis de buff'!$A$4:$A$8,0),1),$J35),"")} | AD35: {=IF(ISNUMBER($J35),INDEX('Cálculos'!$C$339:$F$343,IFERROR(MATCH($T35,'Perfis de buff'!$A$4:$A$8,0),1),$J35),"")} | AE35: {=IF(ISNUMBER($J35),INDEX('Cálculos'!$C$337:$F$337,$J35),"")} | AF35: {=IF(ISNUMBER($J35),INDEX('Cálculos'!$C$338:$F$338,$J35),"")} | AG35: {=IF(ISNUMBER($J35),IF($S35="Derreter",INDEX('Cálculos'!$C$124:$F$124,$J35)*(1+2.78*$AD35/($AD35+1400)+INDEX('Cálculos'!$C$122:$F$122,$J35)),IF($S35="Vaporizar",INDEX('Cálculos'!$C$125:$F$125,$J35)*(1+2.78*$AD35/($AD35+1400)+INDEX('Cálculos'!$C$123:$F$123,$J35)),1)),"")} | AH35: =IF(ISNUMBER($J35),(($AC35*$N35+$AD35*$O35+$AE35*$P35+$AF35*$Q35)*$X35+$AL35)*$AG35,"") | AI35: {=IF(ISNUMBER($J35),$AH35*(1+INDEX('Cálculos'!$C$331:$F$331,$J35)),"")} | AJ35: {=IF(ISNUMBER($J35),$AH35*(1+MIN(INDEX('Cálculos'!$C$330:$F$330,$J35),1)*INDEX('Cálculos'!$C$331:$F$331,$J35)),"")} | AK35: =IF(ISNUMBER($J35),'Fixo (cálculo)'!$AF35,"") | AL35: =IF(ISNUMBER($J35),$AK35*(1+$U35)*$V35*$W35,"")
D36: Todos | F36: =IF($A36="","",IF(ISNUMBER(MATCH($A36,'Golpes extras'!$A$2:$A$101,0)),"Sim","Não")) | G36: {=IF($A36="","",IF($F36="Sim",INDEX('Golpes extras'!$B$2:$B$101,MATCH($A36,'Golpes extras'!$A$2:$A$101,0))&"",$A36))} | H36: =IF($G36="","",IFERROR(MATCH($G36,L_Golpes!$A$2:$A$6000,0),"")) | I36: {=IF($A36="","",IF(ISNUMBER($H36),INDEX(L_Golpes!$B$2:$B$6000,$H36),IF(IFERROR(INDEX('Golpes extras'!$C$2:$C$101,MATCH($A36,'Golpes extras'!$A$2:$A$101,0))&"","")<>"",INDEX('Golpes extras'!$C$2:$C$101,MATCH($A36,'Golpes extras'!$A$2:$A$101,0))&"","golpe?")))} | J36: =IF(OR($I36="",$I36="golpe?"),"",IFERROR(MATCH($I36,Time!$B$4:$E$4,0),"fora do time")) | K36: {=IF(ISNUMBER($J36),IF(IFERROR(INDEX('Golpes extras'!$D$2:$D$101,MATCH($A36,'Golpes extras'!$A$2:$A$101,0))&"","")<>"",INDEX('Golpes extras'!$D$2:$D$101,MATCH($A36,'Golpes extras'!$A$2:$A$101,0))&"",IF(ISNUMBER($H36),INDEX(L_Golpes!$D$2:$D$6000,$H36),"Outro")),"")} | L36: {=IF(ISNUMBER($J36),IF(ISNUMBER($H36),INDEX(L_Golpes!$C$2:$C$6000,$H36),""),"")} | M36: {=IF(ISNUMBER($J36),IF($L36="Normal",INDEX('Cálculos'!$C$14:$F$14,$J36),IF($L36="Habilidade",INDEX('Cálculos'!$C$15:$F$15,$J36),IF($L36="Supremo",INDEX('Cálculos'!$C$16:$F$16,$J36),""))),"")} | N36: {=IF(ISNUMBER($J36),IF(ISNUMBER($H36),INDEX(L_Golpes!$F$2:$T$6000,$H36,MAX(1,MIN(15,$M36))),0)+IF($F36="Sim",N(INDEX('Golpes extras'!$E$2:$E$101,MATCH($A36,'Golpes extras'!$A$2:$A$101,0))),0),"")} | O36: {=IF(ISNUMBER($J36),IF(ISNUMBER($H36),INDEX(L_Golpes!$U$2:$AI$6000,$H36,MAX(1,MIN(15,$M36))),0)+IF($F36="Sim",N(INDEX('Golpes extras'!$F$2:$F$101,MATCH($A36,'Golpes extras'!$A$2:$A$101,0))),0),"")} | P36: {=IF(ISNUMBER($J36),IF(ISNUMBER($H36),INDEX(L_Golpes!$AJ$2:$AX$6000,$H36,MAX(1,MIN(15,$M36))),0)+IF($F36="Sim",N(INDEX('Golpes extras'!$G$2:$G$101,MATCH($A36,'Golpes extras'!$A$2:$A$101,0))),0),"")} | Q36: {=IF(ISNUMBER($J36),IF(ISNUMBER($H36),INDEX(L_Golpes!$AY$2:$BM$6000,$H36,MAX(1,MIN(15,$M36))),0)+IF($F36="Sim",N(INDEX('Golpes extras'!$H$2:$H$101,MATCH($A36,'Golpes extras'!$A$2:$A$101,0))),0),"")} | R36: {=IF(ISNUMBER($J36),INDEX('Cálculos'!$C$19:$F$19,$J36),"")} | S36: =IF(ISNUMBER($J36),IF(AND($C36="Derreter",OR($R36="Pyro",$R36="Cryo")),"Derreter",IF(AND($C36="Vaporizar",OR($R36="Pyro",$R36="Hydro")),"Vaporizar","Nenhuma")),"") | T36: =IF(ISNUMBER($J36),IF(OR($D36="Não",$D36=FALSE),'Perfis de buff'!$A$8,IF(OR($D36="",$D36="Sim",$D36=TRUE),'Perfis de buff'!$A$4,$D36)),"") | U36: {=IF(ISNUMBER($J36),INDEX('Cálculos'!$C$113:$F$113,$J36)+IF($K36="Normal",INDEX('Cálculos'!$C$114:$F$114,$J36),IF($K36="Carregado",INDEX('Cálculos'!$C$115:$F$115,$J36),IF($K36="Habilidade",INDEX('Cálculos'!$C$116:$F$116,$J36),IF($K36="Supremo",INDEX('Cálculos'!$C$117:$F$117,$J36),0))))+INDEX('Cálculos'!$C$143:$F$147,IFERROR(MATCH($T36,'Perfis de buff'!$A$4:$A$8,0),1),$J36)+IF($K36="Normal",INDEX('Cálculos'!$C$148:$F$152,IFERROR(MATCH($T36,'Perfis de buff'!$A$4:$A$8,0),1),$J36),IF($K36="Carregado",INDEX('Cálculos'!$C$153:$F$157,IFERROR(MATCH($T36,'Perfis de buff'!$A$4:$A$8,0),1),$J36),IF($K36="Habilidade",INDEX('Cálculos'!$C$158:$F$162,IFERROR(MATCH($T36,'Perfis de buff'!$A$4:$A$8,0),1),$J36),IF($K36="Supremo",INDEX('Cálculos'!$C$163:$F$167,IFERROR(MATCH($T36,'Perfis de buff'!$A$4:$A$8,0),1),$J36),0))))+N($E36),"")} | V36: {=IF(ISNUMBER($J36),INDEX('Cálculos'!$C$180:$F$180,$J36),"")} | W36: {=IF(ISNUMBER($J36),INDEX('Cálculos'!$C$182:$F$182,$J36),"")} | X36: =IF(ISNUMBER($J36),IF($B36="",1,$B36)*(1+$U36)*$V36*$W36,"") | Y36: =IF(ISNUMBER($J36),$X36*$N36,"") | Z36: =IF(ISNUMBER($J36),$X36*$O36,"") | AA36: =IF(ISNUMBER($J36),$X36*$P36,"") | AB36: =IF(ISNUMBER($J36),$X36*$Q36,"") | AC36: {=IF(ISNUMBER($J36),INDEX('Cálculos'!$C$332:$F$336,IFERROR(MATCH($T36,'Perfis de buff'!$A$4:$A$8,0),1),$J36),"")} | AD36: {=IF(ISNUMBER($J36),INDEX('Cálculos'!$C$339:$F$343,IFERROR(MATCH($T36,'Perfis de buff'!$A$4:$A$8,0),1),$J36),"")} | AE36: {=IF(ISNUMBER($J36),INDEX('Cálculos'!$C$337:$F$337,$J36),"")} | AF36: {=IF(ISNUMBER($J36),INDEX('Cálculos'!$C$338:$F$338,$J36),"")} | AG36: {=IF(ISNUMBER($J36),IF($S36="Derreter",INDEX('Cálculos'!$C$124:$F$124,$J36)*(1+2.78*$AD36/($AD36+1400)+INDEX('Cálculos'!$C$122:$F$122,$J36)),IF($S36="Vaporizar",INDEX('Cálculos'!$C$125:$F$125,$J36)*(1+2.78*$AD36/($AD36+1400)+INDEX('Cálculos'!$C$123:$F$123,$J36)),1)),"")} | AH36: =IF(ISNUMBER($J36),(($AC36*$N36+$AD36*$O36+$AE36*$P36+$AF36*$Q36)*$X36+$AL36)*$AG36,"") | AI36: {=IF(ISNUMBER($J36),$AH36*(1+INDEX('Cálculos'!$C$331:$F$331,$J36)),"")} | AJ36: {=IF(ISNUMBER($J36),$AH36*(1+MIN(INDEX('Cálculos'!$C$330:$F$330,$J36),1)*INDEX('Cálculos'!$C$331:$F$331,$J36)),"")} | AK36: =IF(ISNUMBER($J36),'Fixo (cálculo)'!$AF36,"") | AL36: =IF(ISNUMBER($J36),$AK36*(1+$U36)*$V36*$W36,"")
D37: Todos | F37: =IF($A37="","",IF(ISNUMBER(MATCH($A37,'Golpes extras'!$A$2:$A$101,0)),"Sim","Não")) | G37: {=IF($A37="","",IF($F37="Sim",INDEX('Golpes extras'!$B$2:$B$101,MATCH($A37,'Golpes extras'!$A$2:$A$101,0))&"",$A37))} | H37: =IF($G37="","",IFERROR(MATCH($G37,L_Golpes!$A$2:$A$6000,0),"")) | I37: {=IF($A37="","",IF(ISNUMBER($H37),INDEX(L_Golpes!$B$2:$B$6000,$H37),IF(IFERROR(INDEX('Golpes extras'!$C$2:$C$101,MATCH($A37,'Golpes extras'!$A$2:$A$101,0))&"","")<>"",INDEX('Golpes extras'!$C$2:$C$101,MATCH($A37,'Golpes extras'!$A$2:$A$101,0))&"","golpe?")))} | J37: =IF(OR($I37="",$I37="golpe?"),"",IFERROR(MATCH($I37,Time!$B$4:$E$4,0),"fora do time")) | K37: {=IF(ISNUMBER($J37),IF(IFERROR(INDEX('Golpes extras'!$D$2:$D$101,MATCH($A37,'Golpes extras'!$A$2:$A$101,0))&"","")<>"",INDEX('Golpes extras'!$D$2:$D$101,MATCH($A37,'Golpes extras'!$A$2:$A$101,0))&"",IF(ISNUMBER($H37),INDEX(L_Golpes!$D$2:$D$6000,$H37),"Outro")),"")} | L37: {=IF(ISNUMBER($J37),IF(ISNUMBER($H37),INDEX(L_Golpes!$C$2:$C$6000,$H37),""),"")} | M37: {=IF(ISNUMBER($J37),IF($L37="Normal",INDEX('Cálculos'!$C$14:$F$14,$J37),IF($L37="Habilidade",INDEX('Cálculos'!$C$15:$F$15,$J37),IF($L37="Supremo",INDEX('Cálculos'!$C$16:$F$16,$J37),""))),"")} | N37: {=IF(ISNUMBER($J37),IF(ISNUMBER($H37),INDEX(L_Golpes!$F$2:$T$6000,$H37,MAX(1,MIN(15,$M37))),0)+IF($F37="Sim",N(INDEX('Golpes extras'!$E$2:$E$101,MATCH($A37,'Golpes extras'!$A$2:$A$101,0))),0),"")} | O37: {=IF(ISNUMBER($J37),IF(ISNUMBER($H37),INDEX(L_Golpes!$U$2:$AI$6000,$H37,MAX(1,MIN(15,$M37))),0)+IF($F37="Sim",N(INDEX('Golpes extras'!$F$2:$F$101,MATCH($A37,'Golpes extras'!$A$2:$A$101,0))),0),"")} | P37: {=IF(ISNUMBER($J37),IF(ISNUMBER($H37),INDEX(L_Golpes!$AJ$2:$AX$6000,$H37,MAX(1,MIN(15,$M37))),0)+IF($F37="Sim",N(INDEX('Golpes extras'!$G$2:$G$101,MATCH($A37,'Golpes extras'!$A$2:$A$101,0))),0),"")} | Q37: {=IF(ISNUMBER($J37),IF(ISNUMBER($H37),INDEX(L_Golpes!$AY$2:$BM$6000,$H37,MAX(1,MIN(15,$M37))),0)+IF($F37="Sim",N(INDEX('Golpes extras'!$H$2:$H$101,MATCH($A37,'Golpes extras'!$A$2:$A$101,0))),0),"")} | R37: {=IF(ISNUMBER($J37),INDEX('Cálculos'!$C$19:$F$19,$J37),"")} | S37: =IF(ISNUMBER($J37),IF(AND($C37="Derreter",OR($R37="Pyro",$R37="Cryo")),"Derreter",IF(AND($C37="Vaporizar",OR($R37="Pyro",$R37="Hydro")),"Vaporizar","Nenhuma")),"") | T37: =IF(ISNUMBER($J37),IF(OR($D37="Não",$D37=FALSE),'Perfis de buff'!$A$8,IF(OR($D37="",$D37="Sim",$D37=TRUE),'Perfis de buff'!$A$4,$D37)),"") | U37: {=IF(ISNUMBER($J37),INDEX('Cálculos'!$C$113:$F$113,$J37)+IF($K37="Normal",INDEX('Cálculos'!$C$114:$F$114,$J37),IF($K37="Carregado",INDEX('Cálculos'!$C$115:$F$115,$J37),IF($K37="Habilidade",INDEX('Cálculos'!$C$116:$F$116,$J37),IF($K37="Supremo",INDEX('Cálculos'!$C$117:$F$117,$J37),0))))+INDEX('Cálculos'!$C$143:$F$147,IFERROR(MATCH($T37,'Perfis de buff'!$A$4:$A$8,0),1),$J37)+IF($K37="Normal",INDEX('Cálculos'!$C$148:$F$152,IFERROR(MATCH($T37,'Perfis de buff'!$A$4:$A$8,0),1),$J37),IF($K37="Carregado",INDEX('Cálculos'!$C$153:$F$157,IFERROR(MATCH($T37,'Perfis de buff'!$A$4:$A$8,0),1),$J37),IF($K37="Habilidade",INDEX('Cálculos'!$C$158:$F$162,IFERROR(MATCH($T37,'Perfis de buff'!$A$4:$A$8,0),1),$J37),IF($K37="Supremo",INDEX('Cálculos'!$C$163:$F$167,IFERROR(MATCH($T37,'Perfis de buff'!$A$4:$A$8,0),1),$J37),0))))+N($E37),"")} | V37: {=IF(ISNUMBER($J37),INDEX('Cálculos'!$C$180:$F$180,$J37),"")} | W37: {=IF(ISNUMBER($J37),INDEX('Cálculos'!$C$182:$F$182,$J37),"")} | X37: =IF(ISNUMBER($J37),IF($B37="",1,$B37)*(1+$U37)*$V37*$W37,"") | Y37: =IF(ISNUMBER($J37),$X37*$N37,"") | Z37: =IF(ISNUMBER($J37),$X37*$O37,"") | AA37: =IF(ISNUMBER($J37),$X37*$P37,"") | AB37: =IF(ISNUMBER($J37),$X37*$Q37,"") | AC37: {=IF(ISNUMBER($J37),INDEX('Cálculos'!$C$332:$F$336,IFERROR(MATCH($T37,'Perfis de buff'!$A$4:$A$8,0),1),$J37),"")} | AD37: {=IF(ISNUMBER($J37),INDEX('Cálculos'!$C$339:$F$343,IFERROR(MATCH($T37,'Perfis de buff'!$A$4:$A$8,0),1),$J37),"")} | AE37: {=IF(ISNUMBER($J37),INDEX('Cálculos'!$C$337:$F$337,$J37),"")} | AF37: {=IF(ISNUMBER($J37),INDEX('Cálculos'!$C$338:$F$338,$J37),"")} | AG37: {=IF(ISNUMBER($J37),IF($S37="Derreter",INDEX('Cálculos'!$C$124:$F$124,$J37)*(1+2.78*$AD37/($AD37+1400)+INDEX('Cálculos'!$C$122:$F$122,$J37)),IF($S37="Vaporizar",INDEX('Cálculos'!$C$125:$F$125,$J37)*(1+2.78*$AD37/($AD37+1400)+INDEX('Cálculos'!$C$123:$F$123,$J37)),1)),"")} | AH37: =IF(ISNUMBER($J37),(($AC37*$N37+$AD37*$O37+$AE37*$P37+$AF37*$Q37)*$X37+$AL37)*$AG37,"") | AI37: {=IF(ISNUMBER($J37),$AH37*(1+INDEX('Cálculos'!$C$331:$F$331,$J37)),"")} | AJ37: {=IF(ISNUMBER($J37),$AH37*(1+MIN(INDEX('Cálculos'!$C$330:$F$330,$J37),1)*INDEX('Cálculos'!$C$331:$F$331,$J37)),"")} | AK37: =IF(ISNUMBER($J37),'Fixo (cálculo)'!$AF37,"") | AL37: =IF(ISNUMBER($J37),$AK37*(1+$U37)*$V37*$W37,"")
D38: Todos | F38: =IF($A38="","",IF(ISNUMBER(MATCH($A38,'Golpes extras'!$A$2:$A$101,0)),"Sim","Não")) | G38: {=IF($A38="","",IF($F38="Sim",INDEX('Golpes extras'!$B$2:$B$101,MATCH($A38,'Golpes extras'!$A$2:$A$101,0))&"",$A38))} | H38: =IF($G38="","",IFERROR(MATCH($G38,L_Golpes!$A$2:$A$6000,0),"")) | I38: {=IF($A38="","",IF(ISNUMBER($H38),INDEX(L_Golpes!$B$2:$B$6000,$H38),IF(IFERROR(INDEX('Golpes extras'!$C$2:$C$101,MATCH($A38,'Golpes extras'!$A$2:$A$101,0))&"","")<>"",INDEX('Golpes extras'!$C$2:$C$101,MATCH($A38,'Golpes extras'!$A$2:$A$101,0))&"","golpe?")))} | J38: =IF(OR($I38="",$I38="golpe?"),"",IFERROR(MATCH($I38,Time!$B$4:$E$4,0),"fora do time")) | K38: {=IF(ISNUMBER($J38),IF(IFERROR(INDEX('Golpes extras'!$D$2:$D$101,MATCH($A38,'Golpes extras'!$A$2:$A$101,0))&"","")<>"",INDEX('Golpes extras'!$D$2:$D$101,MATCH($A38,'Golpes extras'!$A$2:$A$101,0))&"",IF(ISNUMBER($H38),INDEX(L_Golpes!$D$2:$D$6000,$H38),"Outro")),"")} | L38: {=IF(ISNUMBER($J38),IF(ISNUMBER($H38),INDEX(L_Golpes!$C$2:$C$6000,$H38),""),"")} | M38: {=IF(ISNUMBER($J38),IF($L38="Normal",INDEX('Cálculos'!$C$14:$F$14,$J38),IF($L38="Habilidade",INDEX('Cálculos'!$C$15:$F$15,$J38),IF($L38="Supremo",INDEX('Cálculos'!$C$16:$F$16,$J38),""))),"")} | N38: {=IF(ISNUMBER($J38),IF(ISNUMBER($H38),INDEX(L_Golpes!$F$2:$T$6000,$H38,MAX(1,MIN(15,$M38))),0)+IF($F38="Sim",N(INDEX('Golpes extras'!$E$2:$E$101,MATCH($A38,'Golpes extras'!$A$2:$A$101,0))),0),"")} | O38: {=IF(ISNUMBER($J38),IF(ISNUMBER($H38),INDEX(L_Golpes!$U$2:$AI$6000,$H38,MAX(1,MIN(15,$M38))),0)+IF($F38="Sim",N(INDEX('Golpes extras'!$F$2:$F$101,MATCH($A38,'Golpes extras'!$A$2:$A$101,0))),0),"")} | P38: {=IF(ISNUMBER($J38),IF(ISNUMBER($H38),INDEX(L_Golpes!$AJ$2:$AX$6000,$H38,MAX(1,MIN(15,$M38))),0)+IF($F38="Sim",N(INDEX('Golpes extras'!$G$2:$G$101,MATCH($A38,'Golpes extras'!$A$2:$A$101,0))),0),"")} | Q38: {=IF(ISNUMBER($J38),IF(ISNUMBER($H38),INDEX(L_Golpes!$AY$2:$BM$6000,$H38,MAX(1,MIN(15,$M38))),0)+IF($F38="Sim",N(INDEX('Golpes extras'!$H$2:$H$101,MATCH($A38,'Golpes extras'!$A$2:$A$101,0))),0),"")} | R38: {=IF(ISNUMBER($J38),INDEX('Cálculos'!$C$19:$F$19,$J38),"")} | S38: =IF(ISNUMBER($J38),IF(AND($C38="Derreter",OR($R38="Pyro",$R38="Cryo")),"Derreter",IF(AND($C38="Vaporizar",OR($R38="Pyro",$R38="Hydro")),"Vaporizar","Nenhuma")),"") | T38: =IF(ISNUMBER($J38),IF(OR($D38="Não",$D38=FALSE),'Perfis de buff'!$A$8,IF(OR($D38="",$D38="Sim",$D38=TRUE),'Perfis de buff'!$A$4,$D38)),"") | U38: {=IF(ISNUMBER($J38),INDEX('Cálculos'!$C$113:$F$113,$J38)+IF($K38="Normal",INDEX('Cálculos'!$C$114:$F$114,$J38),IF($K38="Carregado",INDEX('Cálculos'!$C$115:$F$115,$J38),IF($K38="Habilidade",INDEX('Cálculos'!$C$116:$F$116,$J38),IF($K38="Supremo",INDEX('Cálculos'!$C$117:$F$117,$J38),0))))+INDEX('Cálculos'!$C$143:$F$147,IFERROR(MATCH($T38,'Perfis de buff'!$A$4:$A$8,0),1),$J38)+IF($K38="Normal",INDEX('Cálculos'!$C$148:$F$152,IFERROR(MATCH($T38,'Perfis de buff'!$A$4:$A$8,0),1),$J38),IF($K38="Carregado",INDEX('Cálculos'!$C$153:$F$157,IFERROR(MATCH($T38,'Perfis de buff'!$A$4:$A$8,0),1),$J38),IF($K38="Habilidade",INDEX('Cálculos'!$C$158:$F$162,IFERROR(MATCH($T38,'Perfis de buff'!$A$4:$A$8,0),1),$J38),IF($K38="Supremo",INDEX('Cálculos'!$C$163:$F$167,IFERROR(MATCH($T38,'Perfis de buff'!$A$4:$A$8,0),1),$J38),0))))+N($E38),"")} | V38: {=IF(ISNUMBER($J38),INDEX('Cálculos'!$C$180:$F$180,$J38),"")} | W38: {=IF(ISNUMBER($J38),INDEX('Cálculos'!$C$182:$F$182,$J38),"")} | X38: =IF(ISNUMBER($J38),IF($B38="",1,$B38)*(1+$U38)*$V38*$W38,"") | Y38: =IF(ISNUMBER($J38),$X38*$N38,"") | Z38: =IF(ISNUMBER($J38),$X38*$O38,"") | AA38: =IF(ISNUMBER($J38),$X38*$P38,"") | AB38: =IF(ISNUMBER($J38),$X38*$Q38,"") | AC38: {=IF(ISNUMBER($J38),INDEX('Cálculos'!$C$332:$F$336,IFERROR(MATCH($T38,'Perfis de buff'!$A$4:$A$8,0),1),$J38),"")} | AD38: {=IF(ISNUMBER($J38),INDEX('Cálculos'!$C$339:$F$343,IFERROR(MATCH($T38,'Perfis de buff'!$A$4:$A$8,0),1),$J38),"")} | AE38: {=IF(ISNUMBER($J38),INDEX('Cálculos'!$C$337:$F$337,$J38),"")} | AF38: {=IF(ISNUMBER($J38),INDEX('Cálculos'!$C$338:$F$338,$J38),"")} | AG38: {=IF(ISNUMBER($J38),IF($S38="Derreter",INDEX('Cálculos'!$C$124:$F$124,$J38)*(1+2.78*$AD38/($AD38+1400)+INDEX('Cálculos'!$C$122:$F$122,$J38)),IF($S38="Vaporizar",INDEX('Cálculos'!$C$125:$F$125,$J38)*(1+2.78*$AD38/($AD38+1400)+INDEX('Cálculos'!$C$123:$F$123,$J38)),1)),"")} | AH38: =IF(ISNUMBER($J38),(($AC38*$N38+$AD38*$O38+$AE38*$P38+$AF38*$Q38)*$X38+$AL38)*$AG38,"") | AI38: {=IF(ISNUMBER($J38),$AH38*(1+INDEX('Cálculos'!$C$331:$F$331,$J38)),"")} | AJ38: {=IF(ISNUMBER($J38),$AH38*(1+MIN(INDEX('Cálculos'!$C$330:$F$330,$J38),1)*INDEX('Cálculos'!$C$331:$F$331,$J38)),"")} | AK38: =IF(ISNUMBER($J38),'Fixo (cálculo)'!$AF38,"") | AL38: =IF(ISNUMBER($J38),$AK38*(1+$U38)*$V38*$W38,"")
D39: Todos | F39: =IF($A39="","",IF(ISNUMBER(MATCH($A39,'Golpes extras'!$A$2:$A$101,0)),"Sim","Não")) | G39: {=IF($A39="","",IF($F39="Sim",INDEX('Golpes extras'!$B$2:$B$101,MATCH($A39,'Golpes extras'!$A$2:$A$101,0))&"",$A39))} | H39: =IF($G39="","",IFERROR(MATCH($G39,L_Golpes!$A$2:$A$6000,0),"")) | I39: {=IF($A39="","",IF(ISNUMBER($H39),INDEX(L_Golpes!$B$2:$B$6000,$H39),IF(IFERROR(INDEX('Golpes extras'!$C$2:$C$101,MATCH($A39,'Golpes extras'!$A$2:$A$101,0))&"","")<>"",INDEX('Golpes extras'!$C$2:$C$101,MATCH($A39,'Golpes extras'!$A$2:$A$101,0))&"","golpe?")))} | J39: =IF(OR($I39="",$I39="golpe?"),"",IFERROR(MATCH($I39,Time!$B$4:$E$4,0),"fora do time")) | K39: {=IF(ISNUMBER($J39),IF(IFERROR(INDEX('Golpes extras'!$D$2:$D$101,MATCH($A39,'Golpes extras'!$A$2:$A$101,0))&"","")<>"",INDEX('Golpes extras'!$D$2:$D$101,MATCH($A39,'Golpes extras'!$A$2:$A$101,0))&"",IF(ISNUMBER($H39),INDEX(L_Golpes!$D$2:$D$6000,$H39),"Outro")),"")} | L39: {=IF(ISNUMBER($J39),IF(ISNUMBER($H39),INDEX(L_Golpes!$C$2:$C$6000,$H39),""),"")} | M39: {=IF(ISNUMBER($J39),IF($L39="Normal",INDEX('Cálculos'!$C$14:$F$14,$J39),IF($L39="Habilidade",INDEX('Cálculos'!$C$15:$F$15,$J39),IF($L39="Supremo",INDEX('Cálculos'!$C$16:$F$16,$J39),""))),"")} | N39: {=IF(ISNUMBER($J39),IF(ISNUMBER($H39),INDEX(L_Golpes!$F$2:$T$6000,$H39,MAX(1,MIN(15,$M39))),0)+IF($F39="Sim",N(INDEX('Golpes extras'!$E$2:$E$101,MATCH($A39,'Golpes extras'!$A$2:$A$101,0))),0),"")} | O39: {=IF(ISNUMBER($J39),IF(ISNUMBER($H39),INDEX(L_Golpes!$U$2:$AI$6000,$H39,MAX(1,MIN(15,$M39))),0)+IF($F39="Sim",N(INDEX('Golpes extras'!$F$2:$F$101,MATCH($A39,'Golpes extras'!$A$2:$A$101,0))),0),"")} | P39: {=IF(ISNUMBER($J39),IF(ISNUMBER($H39),INDEX(L_Golpes!$AJ$2:$AX$6000,$H39,MAX(1,MIN(15,$M39))),0)+IF($F39="Sim",N(INDEX('Golpes extras'!$G$2:$G$101,MATCH($A39,'Golpes extras'!$A$2:$A$101,0))),0),"")} | Q39: {=IF(ISNUMBER($J39),IF(ISNUMBER($H39),INDEX(L_Golpes!$AY$2:$BM$6000,$H39,MAX(1,MIN(15,$M39))),0)+IF($F39="Sim",N(INDEX('Golpes extras'!$H$2:$H$101,MATCH($A39,'Golpes extras'!$A$2:$A$101,0))),0),"")} | R39: {=IF(ISNUMBER($J39),INDEX('Cálculos'!$C$19:$F$19,$J39),"")} | S39: =IF(ISNUMBER($J39),IF(AND($C39="Derreter",OR($R39="Pyro",$R39="Cryo")),"Derreter",IF(AND($C39="Vaporizar",OR($R39="Pyro",$R39="Hydro")),"Vaporizar","Nenhuma")),"") | T39: =IF(ISNUMBER($J39),IF(OR($D39="Não",$D39=FALSE),'Perfis de buff'!$A$8,IF(OR($D39="",$D39="Sim",$D39=TRUE),'Perfis de buff'!$A$4,$D39)),"") | U39: {=IF(ISNUMBER($J39),INDEX('Cálculos'!$C$113:$F$113,$J39)+IF($K39="Normal",INDEX('Cálculos'!$C$114:$F$114,$J39),IF($K39="Carregado",INDEX('Cálculos'!$C$115:$F$115,$J39),IF($K39="Habilidade",INDEX('Cálculos'!$C$116:$F$116,$J39),IF($K39="Supremo",INDEX('Cálculos'!$C$117:$F$117,$J39),0))))+INDEX('Cálculos'!$C$143:$F$147,IFERROR(MATCH($T39,'Perfis de buff'!$A$4:$A$8,0),1),$J39)+IF($K39="Normal",INDEX('Cálculos'!$C$148:$F$152,IFERROR(MATCH($T39,'Perfis de buff'!$A$4:$A$8,0),1),$J39),IF($K39="Carregado",INDEX('Cálculos'!$C$153:$F$157,IFERROR(MATCH($T39,'Perfis de buff'!$A$4:$A$8,0),1),$J39),IF($K39="Habilidade",INDEX('Cálculos'!$C$158:$F$162,IFERROR(MATCH($T39,'Perfis de buff'!$A$4:$A$8,0),1),$J39),IF($K39="Supremo",INDEX('Cálculos'!$C$163:$F$167,IFERROR(MATCH($T39,'Perfis de buff'!$A$4:$A$8,0),1),$J39),0))))+N($E39),"")} | V39: {=IF(ISNUMBER($J39),INDEX('Cálculos'!$C$180:$F$180,$J39),"")} | W39: {=IF(ISNUMBER($J39),INDEX('Cálculos'!$C$182:$F$182,$J39),"")} | X39: =IF(ISNUMBER($J39),IF($B39="",1,$B39)*(1+$U39)*$V39*$W39,"") | Y39: =IF(ISNUMBER($J39),$X39*$N39,"") | Z39: =IF(ISNUMBER($J39),$X39*$O39,"") | AA39: =IF(ISNUMBER($J39),$X39*$P39,"") | AB39: =IF(ISNUMBER($J39),$X39*$Q39,"") | AC39: {=IF(ISNUMBER($J39),INDEX('Cálculos'!$C$332:$F$336,IFERROR(MATCH($T39,'Perfis de buff'!$A$4:$A$8,0),1),$J39),"")} | AD39: {=IF(ISNUMBER($J39),INDEX('Cálculos'!$C$339:$F$343,IFERROR(MATCH($T39,'Perfis de buff'!$A$4:$A$8,0),1),$J39),"")} | AE39: {=IF(ISNUMBER($J39),INDEX('Cálculos'!$C$337:$F$337,$J39),"")} | AF39: {=IF(ISNUMBER($J39),INDEX('Cálculos'!$C$338:$F$338,$J39),"")} | AG39: {=IF(ISNUMBER($J39),IF($S39="Derreter",INDEX('Cálculos'!$C$124:$F$124,$J39)*(1+2.78*$AD39/($AD39+1400)+INDEX('Cálculos'!$C$122:$F$122,$J39)),IF($S39="Vaporizar",INDEX('Cálculos'!$C$125:$F$125,$J39)*(1+2.78*$AD39/($AD39+1400)+INDEX('Cálculos'!$C$123:$F$123,$J39)),1)),"")} | AH39: =IF(ISNUMBER($J39),(($AC39*$N39+$AD39*$O39+$AE39*$P39+$AF39*$Q39)*$X39+$AL39)*$AG39,"") | AI39: {=IF(ISNUMBER($J39),$AH39*(1+INDEX('Cálculos'!$C$331:$F$331,$J39)),"")} | AJ39: {=IF(ISNUMBER($J39),$AH39*(1+MIN(INDEX('Cálculos'!$C$330:$F$330,$J39),1)*INDEX('Cálculos'!$C$331:$F$331,$J39)),"")} | AK39: =IF(ISNUMBER($J39),'Fixo (cálculo)'!$AF39,"") | AL39: =IF(ISNUMBER($J39),$AK39*(1+$U39)*$V39*$W39,"")
D40: Todos | F40: =IF($A40="","",IF(ISNUMBER(MATCH($A40,'Golpes extras'!$A$2:$A$101,0)),"Sim","Não")) | G40: {=IF($A40="","",IF($F40="Sim",INDEX('Golpes extras'!$B$2:$B$101,MATCH($A40,'Golpes extras'!$A$2:$A$101,0))&"",$A40))} | H40: =IF($G40="","",IFERROR(MATCH($G40,L_Golpes!$A$2:$A$6000,0),"")) | I40: {=IF($A40="","",IF(ISNUMBER($H40),INDEX(L_Golpes!$B$2:$B$6000,$H40),IF(IFERROR(INDEX('Golpes extras'!$C$2:$C$101,MATCH($A40,'Golpes extras'!$A$2:$A$101,0))&"","")<>"",INDEX('Golpes extras'!$C$2:$C$101,MATCH($A40,'Golpes extras'!$A$2:$A$101,0))&"","golpe?")))} | J40: =IF(OR($I40="",$I40="golpe?"),"",IFERROR(MATCH($I40,Time!$B$4:$E$4,0),"fora do time")) | K40: {=IF(ISNUMBER($J40),IF(IFERROR(INDEX('Golpes extras'!$D$2:$D$101,MATCH($A40,'Golpes extras'!$A$2:$A$101,0))&"","")<>"",INDEX('Golpes extras'!$D$2:$D$101,MATCH($A40,'Golpes extras'!$A$2:$A$101,0))&"",IF(ISNUMBER($H40),INDEX(L_Golpes!$D$2:$D$6000,$H40),"Outro")),"")} | L40: {=IF(ISNUMBER($J40),IF(ISNUMBER($H40),INDEX(L_Golpes!$C$2:$C$6000,$H40),""),"")} | M40: {=IF(ISNUMBER($J40),IF($L40="Normal",INDEX('Cálculos'!$C$14:$F$14,$J40),IF($L40="Habilidade",INDEX('Cálculos'!$C$15:$F$15,$J40),IF($L40="Supremo",INDEX('Cálculos'!$C$16:$F$16,$J40),""))),"")} | N40: {=IF(ISNUMBER($J40),IF(ISNUMBER($H40),INDEX(L_Golpes!$F$2:$T$6000,$H40,MAX(1,MIN(15,$M40))),0)+IF($F40="Sim",N(INDEX('Golpes extras'!$E$2:$E$101,MATCH($A40,'Golpes extras'!$A$2:$A$101,0))),0),"")} | O40: {=IF(ISNUMBER($J40),IF(ISNUMBER($H40),INDEX(L_Golpes!$U$2:$AI$6000,$H40,MAX(1,MIN(15,$M40))),0)+IF($F40="Sim",N(INDEX('Golpes extras'!$F$2:$F$101,MATCH($A40,'Golpes extras'!$A$2:$A$101,0))),0),"")} | P40: {=IF(ISNUMBER($J40),IF(ISNUMBER($H40),INDEX(L_Golpes!$AJ$2:$AX$6000,$H40,MAX(1,MIN(15,$M40))),0)+IF($F40="Sim",N(INDEX('Golpes extras'!$G$2:$G$101,MATCH($A40,'Golpes extras'!$A$2:$A$101,0))),0),"")} | Q40: {=IF(ISNUMBER($J40),IF(ISNUMBER($H40),INDEX(L_Golpes!$AY$2:$BM$6000,$H40,MAX(1,MIN(15,$M40))),0)+IF($F40="Sim",N(INDEX('Golpes extras'!$H$2:$H$101,MATCH($A40,'Golpes extras'!$A$2:$A$101,0))),0),"")} | R40: {=IF(ISNUMBER($J40),INDEX('Cálculos'!$C$19:$F$19,$J40),"")} | S40: =IF(ISNUMBER($J40),IF(AND($C40="Derreter",OR($R40="Pyro",$R40="Cryo")),"Derreter",IF(AND($C40="Vaporizar",OR($R40="Pyro",$R40="Hydro")),"Vaporizar","Nenhuma")),"") | T40: =IF(ISNUMBER($J40),IF(OR($D40="Não",$D40=FALSE),'Perfis de buff'!$A$8,IF(OR($D40="",$D40="Sim",$D40=TRUE),'Perfis de buff'!$A$4,$D40)),"") | U40: {=IF(ISNUMBER($J40),INDEX('Cálculos'!$C$113:$F$113,$J40)+IF($K40="Normal",INDEX('Cálculos'!$C$114:$F$114,$J40),IF($K40="Carregado",INDEX('Cálculos'!$C$115:$F$115,$J40),IF($K40="Habilidade",INDEX('Cálculos'!$C$116:$F$116,$J40),IF($K40="Supremo",INDEX('Cálculos'!$C$117:$F$117,$J40),0))))+INDEX('Cálculos'!$C$143:$F$147,IFERROR(MATCH($T40,'Perfis de buff'!$A$4:$A$8,0),1),$J40)+IF($K40="Normal",INDEX('Cálculos'!$C$148:$F$152,IFERROR(MATCH($T40,'Perfis de buff'!$A$4:$A$8,0),1),$J40),IF($K40="Carregado",INDEX('Cálculos'!$C$153:$F$157,IFERROR(MATCH($T40,'Perfis de buff'!$A$4:$A$8,0),1),$J40),IF($K40="Habilidade",INDEX('Cálculos'!$C$158:$F$162,IFERROR(MATCH($T40,'Perfis de buff'!$A$4:$A$8,0),1),$J40),IF($K40="Supremo",INDEX('Cálculos'!$C$163:$F$167,IFERROR(MATCH($T40,'Perfis de buff'!$A$4:$A$8,0),1),$J40),0))))+N($E40),"")} | V40: {=IF(ISNUMBER($J40),INDEX('Cálculos'!$C$180:$F$180,$J40),"")} | W40: {=IF(ISNUMBER($J40),INDEX('Cálculos'!$C$182:$F$182,$J40),"")} | X40: =IF(ISNUMBER($J40),IF($B40="",1,$B40)*(1+$U40)*$V40*$W40,"") | Y40: =IF(ISNUMBER($J40),$X40*$N40,"") | Z40: =IF(ISNUMBER($J40),$X40*$O40,"") | AA40: =IF(ISNUMBER($J40),$X40*$P40,"") | AB40: =IF(ISNUMBER($J40),$X40*$Q40,"") | AC40: {=IF(ISNUMBER($J40),INDEX('Cálculos'!$C$332:$F$336,IFERROR(MATCH($T40,'Perfis de buff'!$A$4:$A$8,0),1),$J40),"")} | AD40: {=IF(ISNUMBER($J40),INDEX('Cálculos'!$C$339:$F$343,IFERROR(MATCH($T40,'Perfis de buff'!$A$4:$A$8,0),1),$J40),"")} | AE40: {=IF(ISNUMBER($J40),INDEX('Cálculos'!$C$337:$F$337,$J40),"")} | AF40: {=IF(ISNUMBER($J40),INDEX('Cálculos'!$C$338:$F$338,$J40),"")} | AG40: {=IF(ISNUMBER($J40),IF($S40="Derreter",INDEX('Cálculos'!$C$124:$F$124,$J40)*(1+2.78*$AD40/($AD40+1400)+INDEX('Cálculos'!$C$122:$F$122,$J40)),IF($S40="Vaporizar",INDEX('Cálculos'!$C$125:$F$125,$J40)*(1+2.78*$AD40/($AD40+1400)+INDEX('Cálculos'!$C$123:$F$123,$J40)),1)),"")} | AH40: =IF(ISNUMBER($J40),(($AC40*$N40+$AD40*$O40+$AE40*$P40+$AF40*$Q40)*$X40+$AL40)*$AG40,"") | AI40: {=IF(ISNUMBER($J40),$AH40*(1+INDEX('Cálculos'!$C$331:$F$331,$J40)),"")} | AJ40: {=IF(ISNUMBER($J40),$AH40*(1+MIN(INDEX('Cálculos'!$C$330:$F$330,$J40),1)*INDEX('Cálculos'!$C$331:$F$331,$J40)),"")} | AK40: =IF(ISNUMBER($J40),'Fixo (cálculo)'!$AF40,"") | AL40: =IF(ISNUMBER($J40),$AK40*(1+$U40)*$V40*$W40,"")
... D64: Todos | F64: =IF($A64="","",IF(ISNUMBER(MATCH($A64,'Golpes extras'!$A$2:$A$101,0)),"Sim","Não")) | G64: {=IF($A64="","",IF($F64="Sim",INDEX('Golpes extras'!$B$2:$B$101,MATCH($A64,'Golpes extras'!$A$2:$A$101,0))&"",$A64))} | H64: =IF($G64="","",IFERROR(MATCH($G64,L_Golpes!$A$2:$A$6000,0),"")) | I64: {=IF($A64="","",IF(ISNUMBER($H64),INDEX(L_Golpes!$B$2:$B$6000,$H64),IF(IFERROR(INDEX('Golpes extras'!$C$2:$C$101,MATCH($A64,'Golpes extras'!$A$2:$A$101,0))&"","")<>"",INDEX('Golpes extras'!$C$2:$C$101,MATCH($A64,'Golpes extras'!$A$2:$A$101,0))&"","golpe?")))} | J64: =IF(OR($I64="",$I64="golpe?"),"",IFERROR(MATCH($I64,Time!$B$4:$E$4,0),"fora do time")) | K64: {=IF(ISNUMBER($J64),IF(IFERROR(INDEX('Golpes extras'!$D$2:$D$101,MATCH($A64,'Golpes extras'!$A$2:$A$101,0))&"","")<>"",INDEX('Golpes extras'!$D$2:$D$101,MATCH($A64,'Golpes extras'!$A$2:$A$101,0))&"",IF(ISNUMBER($H64),INDEX(L_Golpes!$D$2:$D$6000,$H64),"Outro")),"")} | L64: {=IF(ISNUMBER($J64),IF(ISNUMBER($H64),INDEX(L_Golpes!$C$2:$C$6000,$H64),""),"")} | M64: {=IF(ISNUMBER($J64),IF($L64="Normal",INDEX('Cálculos'!$C$14:$F$14,$J64),IF($L64="Habilidade",INDEX('Cálculos'!$C$15:$F$15,$J64),IF($L64="Supremo",INDEX('Cálculos'!$C$16:$F$16,$J64),""))),"")} | N64: {=IF(ISNUMBER($J64),IF(ISNUMBER($H64),INDEX(L_Golpes!$F$2:$T$6000,$H64,MAX(1,MIN(15,$M64))),0)+IF($F64="Sim",N(INDEX('Golpes extras'!$E$2:$E$101,MATCH($A64,'Golpes extras'!$A$2:$A$101,0))),0),"")} | O64: {=IF(ISNUMBER($J64),IF(ISNUMBER($H64),INDEX(L_Golpes!$U$2:$AI$6000,$H64,MAX(1,MIN(15,$M64))),0)+IF($F64="Sim",N(INDEX('Golpes extras'!$F$2:$F$101,MATCH($A64,'Golpes extras'!$A$2:$A$101,0))),0),"")} | P64: {=IF(ISNUMBER($J64),IF(ISNUMBER($H64),INDEX(L_Golpes!$AJ$2:$AX$6000,$H64,MAX(1,MIN(15,$M64))),0)+IF($F64="Sim",N(INDEX('Golpes extras'!$G$2:$G$101,MATCH($A64,'Golpes extras'!$A$2:$A$101,0))),0),"")} | Q64: {=IF(ISNUMBER($J64),IF(ISNUMBER($H64),INDEX(L_Golpes!$AY$2:$BM$6000,$H64,MAX(1,MIN(15,$M64))),0)+IF($F64="Sim",N(INDEX('Golpes extras'!$H$2:$H$101,MATCH($A64,'Golpes extras'!$A$2:$A$101,0))),0),"")} | R64: {=IF(ISNUMBER($J64),INDEX('Cálculos'!$C$19:$F$19,$J64),"")} | S64: =IF(ISNUMBER($J64),IF(AND($C64="Derreter",OR($R64="Pyro",$R64="Cryo")),"Derreter",IF(AND($C64="Vaporizar",OR($R64="Pyro",$R64="Hydro")),"Vaporizar","Nenhuma")),"") | T64: =IF(ISNUMBER($J64),IF(OR($D64="Não",$D64=FALSE),'Perfis de buff'!$A$8,IF(OR($D64="",$D64="Sim",$D64=TRUE),'Perfis de buff'!$A$4,$D64)),"") | U64: {=IF(ISNUMBER($J64),INDEX('Cálculos'!$C$113:$F$113,$J64)+IF($K64="Normal",INDEX('Cálculos'!$C$114:$F$114,$J64),IF($K64="Carregado",INDEX('Cálculos'!$C$115:$F$115,$J64),IF($K64="Habilidade",INDEX('Cálculos'!$C$116:$F$116,$J64),IF($K64="Supremo",INDEX('Cálculos'!$C$117:$F$117,$J64),0))))+INDEX('Cálculos'!$C$143:$F$147,IFERROR(MATCH($T64,'Perfis de buff'!$A$4:$A$8,0),1),$J64)+IF($K64="Normal",INDEX('Cálculos'!$C$148:$F$152,IFERROR(MATCH($T64,'Perfis de buff'!$A$4:$A$8,0),1),$J64),IF($K64="Carregado",INDEX('Cálculos'!$C$153:$F$157,IFERROR(MATCH($T64,'Perfis de buff'!$A$4:$A$8,0),1),$J64),IF($K64="Habilidade",INDEX('Cálculos'!$C$158:$F$162,IFERROR(MATCH($T64,'Perfis de buff'!$A$4:$A$8,0),1),$J64),IF($K64="Supremo",INDEX('Cálculos'!$C$163:$F$167,IFERROR(MATCH($T64,'Perfis de buff'!$A$4:$A$8,0),1),$J64),0))))+N($E64),"")} | V64: {=IF(ISNUMBER($J64),INDEX('Cálculos'!$C$180:$F$180,$J64),"")} | W64: {=IF(ISNUMBER($J64),INDEX('Cálculos'!$C$182:$F$182,$J64),"")} | X64: =IF(ISNUMBER($J64),IF($B64="",1,$B64)*(1+$U64)*$V64*$W64,"") | Y64: =IF(ISNUMBER($J64),$X64*$N64,"") | Z64: =IF(ISNUMBER($J64),$X64*$O64,"") | AA64: =IF(ISNUMBER($J64),$X64*$P64,"") | AB64: =IF(ISNUMBER($J64),$X64*$Q64,"") | AC64: {=IF(ISNUMBER($J64),INDEX('Cálculos'!$C$332:$F$336,IFERROR(MATCH($T64,'Perfis de buff'!$A$4:$A$8,0),1),$J64),"")} | AD64: {=IF(ISNUMBER($J64),INDEX('Cálculos'!$C$339:$F$343,IFERROR(MATCH($T64,'Perfis de buff'!$A$4:$A$8,0),1),$J64),"")} | AE64: {=IF(ISNUMBER($J64),INDEX('Cálculos'!$C$337:$F$337,$J64),"")} | AF64: {=IF(ISNUMBER($J64),INDEX('Cálculos'!$C$338:$F$338,$J64),"")} | AG64: {=IF(ISNUMBER($J64),IF($S64="Derreter",INDEX('Cálculos'!$C$124:$F$124,$J64)*(1+2.78*$AD64/($AD64+1400)+INDEX('Cálculos'!$C$122:$F$122,$J64)),IF($S64="Vaporizar",INDEX('Cálculos'!$C$125:$F$125,$J64)*(1+2.78*$AD64/($AD64+1400)+INDEX('Cálculos'!$C$123:$F$123,$J64)),1)),"")} | AH64: =IF(ISNUMBER($J64),(($AC64*$N64+$AD64*$O64+$AE64*$P64+$AF64*$Q64)*$X64+$AL64)*$AG64,"") | AI64: {=IF(ISNUMBER($J64),$AH64*(1+INDEX('Cálculos'!$C$331:$F$331,$J64)),"")} | AJ64: {=IF(ISNUMBER($J64),$AH64*(1+MIN(INDEX('Cálculos'!$C$330:$F$330,$J64),1)*INDEX('Cálculos'!$C$331:$F$331,$J64)),"")} | AK64: =IF(ISNUMBER($J64),'Fixo (cálculo)'!$AF64,"") | AL64: =IF(ISNUMBER($J64),$AK64*(1+$U64)*$V64*$W64,"")
AG66: Total | AH66: =SUM(AH5:AH64) -> 1204976.4 | AI66: =SUM(AI5:AI64) -> 3867780.1 | AJ66: =SUM(AJ5:AJ64) -> 3790496.1

Sheet Perfis de buff
A1: Perfis de buff — quais buffs do time valem em cada parte da rotação
A2: Cada linha da Rotação escolhe um perfil. Marque quais fontes de buff do time estão ativas naquele perfil. 'personagem' = buff do próprio personagem (ex.: ATK fixo do Bennett); 'arma/set' = buffs de time da arma e do set (ex.: Noblesse, Instructor). Rótulos = buffs extras da aba Time com aquele rótulo.
A3: Perfil | B3: =IF(Time!B4="","Slot 1",Time!B4)&": personagem" -> Mavuika: personagem | C3: =IF(Time!B4="","Slot 1",Time!B4)&": arma/set" -> Mavuika: arma/set | D3: =IF(Time!C4="","Slot 2",Time!C4)&": personagem" -> Citlali: personagem | E3: =IF(Time!C4="","Slot 2",Time!C4)&": arma/set" -> Citlali: arma/set | F3: =IF(Time!D4="","Slot 3",Time!D4)&": personagem" -> Iansan: personagem | G3: =IF(Time!D4="","Slot 3",Time!D4)&": arma/set" -> Iansan: arma/set | H3: =IF(Time!E4="","Slot 4",Time!E4)&": personagem" -> Bennett: personagem | I3: =IF(Time!E4="","Slot 4",Time!E4)&": arma/set" -> Bennett: arma/set | J3: Extras sem rótulo | K3: TTDS | L3: Scroll | M3: Rótulo 3 | N3: Rótulo 4
A4: Todos | B4: Sim | C4: Sim | D4: Sim | E4: Sim | F4: Sim | G4: Sim | H4: Sim | I4: Sim | J4: Sim | K4: Sim | L4: Sim | M4: Sim | N4: Sim
A5: Iansan (início) | B5: Sim | C5: Sim | D5: Não | E5: Não | F5: Não | G5: Não | H5: Não | I5: Não | J5: Sim | K5: Não | L5: Não | M5: Não | N5: Não
A6: Pós-Supremo | B6: Sim | C6: Sim | D6: Sim | E6: Sim | F6: Não | G6: Sim | H6: Sim | I6: Sim | J6: Sim | K6: Sim | L6: Sim | M6: Não | N6: Não
A7: Final | B7: Sim | C7: Sim | D7: Sim | E7: Sim | F7: Não | G7: Sim | H7: Sim | I7: Não | J7: Sim | K7: Não | L7: Sim | M7: Não | N7: Não
A8: Nenhum | B8: Não | C8: Não | D8: Não | E8: Não | F8: Não | G8: Não | H8: Não | I8: Não | J8: Não | K8: Não | L8: Não | M8: Não | N8: Não
A10: Auxiliar (não editar)
A11: =A4 -> Todos | B11: =IF(OR(B4="Sim",B4=TRUE),1,0) -> 1 | C11: =IF(OR(C4="Sim",C4=TRUE),1,0) -> 1 | D11: =IF(OR(D4="Sim",D4=TRUE),1,0) -> 1 | E11: =IF(OR(E4="Sim",E4=TRUE),1,0) -> 1 | F11: =IF(OR(F4="Sim",F4=TRUE),1,0) -> 1 | G11: =IF(OR(G4="Sim",G4=TRUE),1,0) -> 1 | H11: =IF(OR(H4="Sim",H4=TRUE),1,0) -> 1 | I11: =IF(OR(I4="Sim",I4=TRUE),1,0) -> 1 | J11: =IF(OR(J4="Sim",J4=TRUE),"_geral","#") -> _geral | K11: =IF(OR(K4="Sim",K4=TRUE),TRIM(K$3),"#") -> TTDS | L11: =IF(OR(L4="Sim",L4=TRUE),TRIM(L$3),"#") -> Scroll | M11: =IF(OR(M4="Sim",M4=TRUE),TRIM(M$3),"#") -> Rótulo 3 | N11: =IF(OR(N4="Sim",N4=TRUE),TRIM(N$3),"#") -> Rótulo 4
A12: =A5 -> Iansan (início) | B12: =IF(OR(B5="Sim",B5=TRUE),1,0) -> 1 | C12: =IF(OR(C5="Sim",C5=TRUE),1,0) -> 1 | D12: =IF(OR(D5="Sim",D5=TRUE),1,0) -> 0 | E12: =IF(OR(E5="Sim",E5=TRUE),1,0) -> 0 | F12: =IF(OR(F5="Sim",F5=TRUE),1,0) -> 0 | G12: =IF(OR(G5="Sim",G5=TRUE),1,0) -> 0 | H12: =IF(OR(H5="Sim",H5=TRUE),1,0) -> 0 | I12: =IF(OR(I5="Sim",I5=TRUE),1,0) -> 0 | J12: =IF(OR(J5="Sim",J5=TRUE),"_geral","#") -> _geral | K12: =IF(OR(K5="Sim",K5=TRUE),TRIM(K$3),"#") -> # | L12: =IF(OR(L5="Sim",L5=TRUE),TRIM(L$3),"#") -> # | M12: =IF(OR(M5="Sim",M5=TRUE),TRIM(M$3),"#") -> # | N12: =IF(OR(N5="Sim",N5=TRUE),TRIM(N$3),"#") -> #
A13: =A6 -> Pós-Supremo | B13: =IF(OR(B6="Sim",B6=TRUE),1,0) -> 1 | C13: =IF(OR(C6="Sim",C6=TRUE),1,0) -> 1 | D13: =IF(OR(D6="Sim",D6=TRUE),1,0) -> 1 | E13: =IF(OR(E6="Sim",E6=TRUE),1,0) -> 1 | F13: =IF(OR(F6="Sim",F6=TRUE),1,0) -> 0 | G13: =IF(OR(G6="Sim",G6=TRUE),1,0) -> 1 | H13: =IF(OR(H6="Sim",H6=TRUE),1,0) -> 1 | I13: =IF(OR(I6="Sim",I6=TRUE),1,0) -> 1 | J13: =IF(OR(J6="Sim",J6=TRUE),"_geral","#") -> _geral | K13: =IF(OR(K6="Sim",K6=TRUE),TRIM(K$3),"#") -> TTDS | L13: =IF(OR(L6="Sim",L6=TRUE),TRIM(L$3),"#") -> Scroll | M13: =IF(OR(M6="Sim",M6=TRUE),TRIM(M$3),"#") -> # | N13: =IF(OR(N6="Sim",N6=TRUE),TRIM(N$3),"#") -> #
A14: =A7 -> Final | B14: =IF(OR(B7="Sim",B7=TRUE),1,0) -> 1 | C14: =IF(OR(C7="Sim",C7=TRUE),1,0) -> 1 | D14: =IF(OR(D7="Sim",D7=TRUE),1,0) -> 1 | E14: =IF(OR(E7="Sim",E7=TRUE),1,0) -> 1 | F14: =IF(OR(F7="Sim",F7=TRUE),1,0) -> 0 | G14: =IF(OR(G7="Sim",G7=TRUE),1,0) -> 1 | H14: =IF(OR(H7="Sim",H7=TRUE),1,0) -> 1 | I14: =IF(OR(I7="Sim",I7=TRUE),1,0) -> 0 | J14: =IF(OR(J7="Sim",J7=TRUE),"_geral","#") -> _geral | K14: =IF(OR(K7="Sim",K7=TRUE),TRIM(K$3),"#") -> # | L14: =IF(OR(L7="Sim",L7=TRUE),TRIM(L$3),"#") -> Scroll | M14: =IF(OR(M7="Sim",M7=TRUE),TRIM(M$3),"#") -> # | N14: =IF(OR(N7="Sim",N7=TRUE),TRIM(N$3),"#") -> #
A15: =A8 -> Nenhum | B15: =IF(OR(B8="Sim",B8=TRUE),1,0) -> 0 | C15: =IF(OR(C8="Sim",C8=TRUE),1,0) -> 0 | D15: =IF(OR(D8="Sim",D8=TRUE),1,0) -> 0 | E15: =IF(OR(E8="Sim",E8=TRUE),1,0) -> 0 | F15: =IF(OR(F8="Sim",F8=TRUE),1,0) -> 0 | G15: =IF(OR(G8="Sim",G8=TRUE),1,0) -> 0 | H15: =IF(OR(H8="Sim",H8=TRUE),1,0) -> 0 | I15: =IF(OR(I8="Sim",I8=TRUE),1,0) -> 0 | J15: =IF(OR(J8="Sim",J8=TRUE),"_geral","#") -> # | K15: =IF(OR(K8="Sim",K8=TRUE),TRIM(K$3),"#") -> # | L15: =IF(OR(L8="Sim",L8=TRUE),TRIM(L$3),"#") -> # | M15: =IF(OR(M8="Sim",M8=TRUE),TRIM(M$3),"#") -> # | N15: =IF(OR(N8="Sim",N8=TRUE),TRIM(N$3),"#") -> #
A18: Dica: 'Todos' e 'Nenhum' equivalem ao antigo Sim/Não. Renomeie os perfis 2–4 (ex.: 'Pós-Supremo') e marque o que ainda está ativo naquele trecho da rotação.

Sheet Resultado
A1: Resultado
A2: Tudo calculado. Os substatus são a melhor distribuição encontrada pelo otimizador.
B4: Slot 1 | C4: Slot 2 | D4: Slot 3 | E4: Slot 4
A5: Personagem | B5: =IF('Cálculos'!C6="","",'Cálculos'!C6) -> Mavuika | C5: =IF('Cálculos'!D6="","",'Cálculos'!D6) -> Citlali | D5: =IF('Cálculos'!E6="","",'Cálculos'!E6) -> Iansan | E5: =IF('Cálculos'!F6="","",'Cálculos'!F6) -> Bennett
A6: Arma | B6: =IF('Cálculos'!C6="","",Time!B5&"") -> A Thousand Blazing Suns | C6: =IF('Cálculos'!D6="","",Time!C5&"") -> Thrilling Tales of Dragon Slayers | D6: =IF('Cálculos'!E6="","",Time!D5&"") -> Engulfing Lightning | E6: =IF('Cálculos'!F6="","",Time!E5&"") -> Absolution
A7: Set | B7: =IF('Cálculos'!C6="","",IF(Time!B7="",Time!B6&" (4p)",Time!B6&" + "&Time!B7&" (2p+2p)")) -> Obsidian Codex (4p) | C7: =IF('Cálculos'!D6="","",IF(Time!C7="",Time!C6&" (4p)",Time!C6&" + "&Time!C7&" (2p+2p)")) -> Instructor (4p) | D7: =IF('Cálculos'!E6="","",IF(Time!D7="",Time!D6&" (4p)",Time!D6&" + "&Time!D7&" (2p+2p)")) -> Scroll of the Hero of Cinder City (4p) | E7: =IF('Cálculos'!F6="","",IF(Time!E7="",Time!E6&" (4p)",Time!E6&" + "&Time!E7&" (2p+2p)")) -> Noblesse Oblige (4p)
A8: Peças 5★ / 4★ | B8: =IF('Cálculos'!C6="","",'Cálculos'!C77&" × 5★ / "&(5-'Cálculos'!C77)&" × 4★") -> 5 × 5★ / 0 × 4★ | C8: =IF('Cálculos'!D6="","",'Cálculos'!D77&" × 5★ / "&(5-'Cálculos'!D77)&" × 4★") -> 1 × 5★ / 4 × 4★ | D8: =IF('Cálculos'!E6="","",'Cálculos'!E77&" × 5★ / "&(5-'Cálculos'!E77)&" × 4★") -> 5 × 5★ / 0 × 4★ | E8: =IF('Cálculos'!F6="","",'Cálculos'!F77&" × 5★ / "&(5-'Cálculos'!F77)&" × 4★") -> 5 × 5★ / 0 × 4★
A9: Areia / Cálice / Tiara | B9: =IF('Cálculos'!C6="","",Time!B8&" / "&Time!B9&" / "&Time!B10) -> EM / DMG% elemental / CD | C9: =IF('Cálculos'!D6="","",Time!C8&" / "&Time!C9&" / "&Time!C10) -> ER / DMG% elemental / CR | D9: =IF('Cálculos'!E6="","",Time!D8&" / "&Time!D9&" / "&Time!D10) -> ATK% / ATK% / CR | E9: =IF('Cálculos'!F6="","",Time!E8&" / "&Time!E9&" / "&Time!E10) -> ER / DMG% elemental / CR
A10: Avisos | B10: =IF('Cálculos'!C6="","",TRIM(IF('Cálculos'!C7=0,"Personagem fora do L_Personagens. ","")&IF(AND(Time!B5<>"",'Cálculos'!C10=0),"Arma sem passiva cadastrada. ","")&IF(AND(Time!B6<>"",'Cálculos'!C11=0),"Set principal sem efeitos cadastrados. ","")&IF(AND(Time!B7<>"",'Cálculos'!C12=0),"Set secundário sem efeitos cadastrados.",""))) | C10: =IF('Cálculos'!D6="","",TRIM(IF('Cálculos'!D7=0,"Personagem fora do L_Personagens. ","")&IF(AND(Time!C5<>"",'Cálculos'!D10=0),"Arma sem passiva cadastrada. ","")&IF(AND(Time!C6<>"",'Cálculos'!D11=0),"Set principal sem efeitos cadastrados. ","")&IF(AND(Time!C7<>"",'Cálculos'!D12=0),"Set secundário sem efeitos cadastrados.",""))) | D10: =IF('Cálculos'!E6="","",TRIM(IF('Cálculos'!E7=0,"Personagem fora do L_Personagens. ","")&IF(AND(Time!D5<>"",'Cálculos'!E10=0),"Arma sem passiva cadastrada. ","")&IF(AND(Time!D6<>"",'Cálculos'!E11=0),"Set principal sem efeitos cadastrados. ","")&IF(AND(Time!D7<>"",'Cálculos'!E12=0),"Set secundário sem efeitos cadastrados.",""))) | E10: =IF('Cálculos'!F6="","",TRIM(IF('Cálculos'!F7=0,"Personagem fora do L_Personagens. ","")&IF(AND(Time!E5<>"",'Cálculos'!F10=0),"Arma sem passiva cadastrada. ","")&IF(AND(Time!E6<>"",'Cálculos'!F11=0),"Set principal sem efeitos cadastrados. ","")&IF(AND(Time!E7<>"",'Cálculos'!F12=0),"Set secundário sem efeitos cadastrados.","")))
A12: Atributos finais
A13: Escala principal | B13: =IF('Cálculos'!C6="","",CHOOSE('Cálculos'!C290,"ATK","HP","DEF")) -> ATK | C13: =IF('Cálculos'!D6="","",CHOOSE('Cálculos'!D290,"ATK","HP","DEF")) -> ATK | D13: =IF('Cálculos'!E6="","",CHOOSE('Cálculos'!E290,"ATK","HP","DEF")) -> ATK | E13: =IF('Cálculos'!F6="","",CHOOSE('Cálculos'!F290,"ATK","HP","DEF")) -> ATK
A14: ATK (perfil Todos) | B14: =IF('Cálculos'!C6="","",'Cálculos'!C332) -> 5791.25 | C14: =IF('Cálculos'!D6="","",'Cálculos'!D332) -> 3241.7343 | D14: =IF('Cálculos'!E6="","",'Cálculos'!E332) -> 4157.3562 | E14: =IF('Cálculos'!F6="","",'Cálculos'!F332) -> 3700.235
A15: HP | B15: =IF('Cálculos'!C6="","",'Cálculos'!C337) -> 19082.648 | C15: =IF('Cálculos'!D6="","",'Cálculos'!D337) -> 20708.65 | D15: =IF('Cálculos'!E6="","",'Cálculos'!E337) -> 17000.043 | E15: =IF('Cálculos'!F6="","",'Cálculos'!F337) -> 18912.303
A16: DEF | B16: =IF('Cálculos'!C6="","",'Cálculos'!C338) -> 929.208 | C16: =IF('Cálculos'!D6="","",'Cálculos'!D338) -> 876.60154 | D16: =IF('Cálculos'!E6="","",'Cálculos'!E338) -> 756.112 | E16: =IF('Cálculos'!F6="","",'Cálculos'!F338) -> 905.604
A17: EM (perfil Todos) | B17: =IF('Cálculos'!C6="","",'Cálculos'!C339) -> 424 | C17: =IF('Cálculos'!D6="","",'Cálculos'!D339) -> 348.49081 | D17: =IF('Cálculos'!E6="","",'Cálculos'!E339) -> 159 | E17: =IF('Cálculos'!F6="","",'Cálculos'!F339) -> 159
A18: Recarga de energia | B18: =IF('Cálculos'!C6="","",'Cálculos'!C328) -> 1.11 | C18: =IF('Cálculos'!D6="","",'Cálculos'!D328) -> 2.0314324 | D18: =IF('Cálculos'!E6="","",'Cálculos'!E328) -> 2.046 | E18: =IF('Cálculos'!F6="","",'Cálculos'!F328) -> 2.005
A19: Taxa crítica | B19: =IF('Cálculos'!C6="","",'Cálculos'!C330) -> 0.989 | C19: =IF('Cálculos'!D6="","",'Cálculos'!D330) -> 0.47803784 | D19: =IF('Cálculos'!E6="","",'Cálculos'!E330) -> 0.592 | E19: =IF('Cálculos'!F6="","",'Cálculos'!F330) -> 0.823
A20: Dano crítico | B20: ='Cálculos'!C331 -> 2.318 | C20: ='Cálculos'!D331 -> 0.94869189 | D20: ='Cálculos'!E331 -> 1.16 | E20: ='Cálculos'!F331 -> 1.669
A21: Bônus de DMG geral (com time) | B21: =IF('Cálculos'!C6="","",'Cálculos'!C344) -> 1.816 | C21: =IF('Cálculos'!D6="","",'Cálculos'!D344) -> 0.348 | D21: =IF('Cálculos'!E6="","",'Cálculos'!E344) -> 0.4 | E21: =IF('Cálculos'!F6="","",'Cálculos'!F344) -> 0.866
A23: Melhor distribuição de substatus (rolls, já contando os mínimos)
A24: Taxa crítica (CR) | B24: =IF('Cálculos'!C6="","",'Cálculos'!C318+Time!$B$27) -> 13 | C24: =IF('Cálculos'!D6="","",'Cálculos'!D318+Time!$B$27) -> 7 | D24: =IF('Cálculos'!E6="","",'Cálculos'!E318+Time!$B$27) -> 7 | E24: =IF('Cálculos'!F6="","",'Cálculos'!F318+Time!$B$27) -> 14
A25: Dano crítico (CD) | B25: ='Cálculos'!C319+Time!$B$27 -> 7 | C25: ='Cálculos'!D319+Time!$B$27 -> 8 | D25: ='Cálculos'!E319+Time!$B$27 -> 10 | E25: ='Cálculos'!F319+Time!$B$27 -> 8
A26: ATK% | B26: =IF('Cálculos'!C6="","",'Cálculos'!C323+Time!$B$27) -> 2 | C26: =IF('Cálculos'!D6="","",'Cálculos'!D323+Time!$B$27) -> 2 | D26: =IF('Cálculos'!E6="","",'Cálculos'!E323+Time!$B$27) -> 2 | E26: =IF('Cálculos'!F6="","",'Cálculos'!F323+Time!$B$27) -> 2
A27: HP% | B27: =IF('Cálculos'!C6="","",'Cálculos'!C324+Time!$B$27) -> 2 | C27: =IF('Cálculos'!D6="","",'Cálculos'!D324+Time!$B$27) -> 2 | D27: =IF('Cálculos'!E6="","",'Cálculos'!E324+Time!$B$27) -> 2 | E27: =IF('Cálculos'!F6="","",'Cálculos'!F324+Time!$B$27) -> 2
A28: DEF% | B28: =IF('Cálculos'!C6="","",'Cálculos'!C325+Time!$B$27) -> 2 | C28: =IF('Cálculos'!D6="","",'Cálculos'!D325+Time!$B$27) -> 2 | D28: =IF('Cálculos'!E6="","",'Cálculos'!E325+Time!$B$27) -> 2 | E28: =IF('Cálculos'!F6="","",'Cálculos'!F325+Time!$B$27) -> 2
A29: EM | B29: =IF('Cálculos'!C6="","",'Cálculos'!C321+Time!$B$27) -> 6 | C29: =IF('Cálculos'!D6="","",'Cálculos'!D321+Time!$B$27) -> 2 | D29: =IF('Cálculos'!E6="","",'Cálculos'!E321+Time!$B$27) -> 2 | E29: =IF('Cálculos'!F6="","",'Cálculos'!F321+Time!$B$27) -> 2
A30: Recarga (ER) | B30: =IF('Cálculos'!C6="","",'Cálculos'!C322+Time!$B$27) -> 2 | C30: =IF('Cálculos'!D6="","",'Cálculos'!D322+Time!$B$27) -> 11 | D30: =IF('Cálculos'!E6="","",'Cálculos'!E322+Time!$B$27) -> 9 | E30: =IF('Cálculos'!F6="","",'Cálculos'!F322+Time!$B$27) -> 4
A31: ATK / HP / DEF fixos (cada) | B31: =IF('Cálculos'!C6="","",Time!$B$27) -> 2 | C31: =IF('Cálculos'!D6="","",Time!$B$27) -> 2 | D31: =IF('Cálculos'!E6="","",Time!$B$27) -> 2 | E31: =IF('Cálculos'!F6="","",Time!$B$27) -> 2
A32: Total de rolls usados | B32: =IF('Cálculos'!C6="","",'Cálculos'!C318+'Cálculos'!C319+'Cálculos'!C320+'Cálculos'!C321+'Cálculos'!C322+10*Time!$B$27) -> 40 | C32: =IF('Cálculos'!D6="","",'Cálculos'!D318+'Cálculos'!D319+'Cálculos'!D320+'Cálculos'!D321+'Cálculos'!D322+10*Time!$B$27) -> 40 | D32: =IF('Cálculos'!E6="","",'Cálculos'!E318+'Cálculos'!E319+'Cálculos'!E320+'Cálculos'!E321+'Cálculos'!E322+10*Time!$B$27) -> 40 | E32: =IF('Cálculos'!F6="","",'Cálculos'!F318+'Cálculos'!F319+'Cálculos'!F320+'Cálculos'!F321+'Cálculos'!F322+10*Time!$B$27) -> 40
A33: Rolls disponíveis | B33: =IF('Cálculos'!C6="","",'Cálculos'!C291) -> 40 | C33: =IF('Cálculos'!D6="","",'Cálculos'!D291) -> 40 | D33: =IF('Cálculos'!E6="","",'Cálculos'!E291) -> 40 | E33: =IF('Cálculos'!F6="","",'Cálculos'!F291) -> 40
A35: Dano na rotação
A36: Dano sem crit | B36: =SUMIFS('Rotação'!$AH$5:$AH$64,'Rotação'!$J$5:$J$64,1) -> 1096752.2 | C36: =SUMIFS('Rotação'!$AH$5:$AH$64,'Rotação'!$J$5:$J$64,2) -> 70298.655 | D36: =SUMIFS('Rotação'!$AH$5:$AH$64,'Rotação'!$J$5:$J$64,3) -> 18580.035 | E36: =SUMIFS('Rotação'!$AH$5:$AH$64,'Rotação'!$J$5:$J$64,4) -> 19345.494
A37: Dano com crit | B37: =SUMIFS('Rotação'!$AI$5:$AI$64,'Rotação'!$J$5:$J$64,1) -> 3639023.7 | C37: =SUMIFS('Rotação'!$AI$5:$AI$64,'Rotação'!$J$5:$J$64,2) -> 136990.42 | D37: =SUMIFS('Rotação'!$AI$5:$AI$64,'Rotação'!$J$5:$J$64,3) -> 40132.876 | E37: =SUMIFS('Rotação'!$AI$5:$AI$64,'Rotação'!$J$5:$J$64,4) -> 51633.124
A38: Dano médio | B38: =SUMIFS('Rotação'!$AJ$5:$AJ$64,'Rotação'!$J$5:$J$64,1) -> 3611058.7 | C38: =SUMIFS('Rotação'!$AJ$5:$AJ$64,'Rotação'!$J$5:$J$64,2) -> 102179.84 | D38: =SUMIFS('Rotação'!$AJ$5:$AJ$64,'Rotação'!$J$5:$J$64,3) -> 31339.317 | E38: =SUMIFS('Rotação'!$AJ$5:$AJ$64,'Rotação'!$J$5:$J$64,4) -> 45918.213
A39: % do dano do time | B39: =IF($B$42=0,0,B38/$B$42) -> 0.95266124 | C39: =IF($B$42=0,0,C38/$B$42) -> 0.026956852 | D39: =IF($B$42=0,0,D38/$B$42) -> 0.0082678668 | E39: =IF($B$42=0,0,E38/$B$42) -> 0.012114038
A41: Time | B41: Valor
A42: Dano total médio (DPR) | B42: =SUM(B38:E38) -> 3790496.1
A43: DPS médio | B43: =B42/Time!$B$28 -> 216599.78
A44: Dano total com crit | B44: =SUM(B37:E37) -> 3867780.1
A45: Dano total sem crit | B45: =SUM(B36:E36) -> 1204976.4

Sheet Golpes extras
A1: Nome do golpe extra | B1: Golpe base (Lunaris) | C1: Personagem (se não houver base) | D1: Tipo (opcional) | E1: + escala ATK | F1: + escala EM | G1: + escala HP | H1: + escala DEF | I1: Por que existe
A2: Mavuika - Carregado no Supremo | B2: Mavuika - Habilidade: Flamestrider Charged Attack Cyclic DMG | E2: 2.04 | F2: 0 | G2: 0 | H2: 0 | I2: Supremo: 200 Fighting Spirit × 1,02% ATK (nv 10 do Supremo, Lunaris). Mude se o nível mudar.
A3: Mavuika - Carregado final no Supremo | B3: Mavuika - Habilidade: Flamestrider Charged Attack Final DMG | E3: 2.04 | F3: 0 | G3: 0 | H3: 0 | I3: Idem.
A4: Mavuika - Supremo (200 FS) | B4: Mavuika - Supremo: Skill DMG | E4: 5.76 | F4: 0 | G4: 0 | H4: 0 | I4: Sunfell Slice: 200 Fighting Spirit × 2,88% ATK (nv 10).
A5: Citlali - Obsidian Tzitzimitl (+EM) | B5: Citlali - Habilidade: Obsidian Tzitzimitl DMG | E5: 0 | F5: 0 | G5: 0 | H5: 0 | I5: Sem bônus de EM: a passiva p2 vale só para Frostfall Storm e Ice Storm (Lunaris).
A6: Citlali - Frostfall Storm (+EM) | B6: Citlali - Habilidade: Frostfall Storm DMG | E6: 0 | F6: 0.9 | G6: 0 | H6: 0 | I6: Bônus de 90% EM da sua planilha (passiva).
A7: Citlali - Ice Storm (+EM) | B7: Citlali - Supremo: Ice Storm DMG | E7: 0 | F7: 12 | G7: 0 | H7: 0 | I7: Bônus de 1200% EM da sua planilha (passiva).

Sheet Dano fixo
A1: Nome do buff | B1: Fonte (quem dá) | C1: Stat da fonte | D1: Coeficiente (por ponto de stat) | E1: Só conta acima de (limiar) | F1: Máximo por hit (vazio = sem) | G1: Alvos (nomes separados por vírgula, ou Todos) | H1: Elementos (vazio = todos) | I1: Tipos de golpe (vazio = todos) | J1: Stacks = nº de hits (vazio = ilimitado) | K1: Ativo? | L1: Valor por hit (calculado) | M1: Observações
A2: Lead Vocal (Vodyanitsa) | B2: Vodyanitsa | C2: HP | D2: 0.14 | E2: 40000 | F2: 3500 | G2: Skirk | H2: Hydro,Cryo | I2: Normal,Carregado,Outro,Habilidade,Supremo | J2: 25 | K2: Sim | L2: {=IF(OR($A2="",$B2="",$K2="Não",$K2=FALSE),0,IFERROR(IF($F2="",N($D2)*MAX(0,INDEX(IF($C2="HP",'Cálculos'!$C$313:$F$313,IF($C2="DEF",'Cálculos'!$C$314:$F$314,IF($C2="EM",'Cálculos'!$C$315:$F$315,'Cálculos'!$C$312:$F$312))),MATCH($B2,Time!$B$4:$E$4,0))-N($E2)),MIN($F2,N($D2)*MAX(0,INDEX(IF($C2="HP",'Cálculos'!$C$313:$F$313,IF($C2="DEF",'Cálculos'!$C$314:$F$314,IF($C2="EM",'Cálculos'!$C$315:$F$315,'Cálculos'!$C$312:$F$312))),MATCH($B2,Time!$B$4:$E$4,0))-N($E2)))),0))} -> 0 | M2: +140 por 1000 HP acima de 40k, máx. 3500. Alvo = personagem em campo.
A3: Chorus (Vodyanitsa) | B3: Vodyanitsa | C3: HP | D3: 0.14 | E3: 40000 | F3: 3500 | G3: Furina,Escoffier | H3: Hydro,Cryo | J3: 10 | K3: Sim | L3: {=IF(OR($A3="",$B3="",$K3="Não",$K3=FALSE),0,IFERROR(IF($F3="",N($D3)*MAX(0,INDEX(IF($C3="HP",'Cálculos'!$C$313:$F$313,IF($C3="DEF",'Cálculos'!$C$314:$F$314,IF($C3="EM",'Cálculos'!$C$315:$F$315,'Cálculos'!$C$312:$F$312))),MATCH($B3,Time!$B$4:$E$4,0))-N($E3)),MIN($F3,N($D3)*MAX(0,INDEX(IF($C3="HP",'Cálculos'!$C$313:$F$313,IF($C3="DEF",'Cálculos'!$C$314:$F$314,IF($C3="EM",'Cálculos'!$C$315:$F$315,'Cálculos'!$C$312:$F$312))),MATCH($B3,Time!$B$4:$E$4,0))-N($E3)))),0))} -> 0 | M3: Igual ao Lead Vocal, para quem está fora de campo (10 stacks no total).
K4: Sim | L4: {=IF(OR($A4="",$B4="",$K4="Não",$K4=FALSE),0,IFERROR(IF($F4="",N($D4)*MAX(0,INDEX(IF($C4="HP",'Cálculos'!$C$313:$F$313,IF($C4="DEF",'Cálculos'!$C$314:$F$314,IF($C4="EM",'Cálculos'!$C$315:$F$315,'Cálculos'!$C$312:$F$312))),MATCH($B4,Time!$B$4:$E$4,0))-N($E4)),MIN($F4,N($D4)*MAX(0,INDEX(IF($C4="HP",'Cálculos'!$C$313:$F$313,IF($C4="DEF",'Cálculos'!$C$314:$F$314,IF($C4="EM",'Cálculos'!$C$315:$F$315,'Cálculos'!$C$312:$F$312))),MATCH($B4,Time!$B$4:$E$4,0))-N($E4)))),0))} -> 0
K5: Sim | L5: {=IF(OR($A5="",$B5="",$K5="Não",$K5=FALSE),0,IFERROR(IF($F5="",N($D5)*MAX(0,INDEX(IF($C5="HP",'Cálculos'!$C$313:$F$313,IF($C5="DEF",'Cálculos'!$C$314:$F$314,IF($C5="EM",'Cálculos'!$C$315:$F$315,'Cálculos'!$C$312:$F$312))),MATCH($B5,Time!$B$4:$E$4,0))-N($E5)),MIN($F5,N($D5)*MAX(0,INDEX(IF($C5="HP",'Cálculos'!$C$313:$F$313,IF($C5="DEF",'Cálculos'!$C$314:$F$314,IF($C5="EM",'Cálculos'!$C$315:$F$315,'Cálculos'!$C$312:$F$312))),MATCH($B5,Time!$B$4:$E$4,0))-N($E5)))),0))} -> 0
K6: Sim | L6: {=IF(OR($A6="",$B6="",$K6="Não",$K6=FALSE),0,IFERROR(IF($F6="",N($D6)*MAX(0,INDEX(IF($C6="HP",'Cálculos'!$C$313:$F$313,IF($C6="DEF",'Cálculos'!$C$314:$F$314,IF($C6="EM",'Cálculos'!$C$315:$F$315,'Cálculos'!$C$312:$F$312))),MATCH($B6,Time!$B$4:$E$4,0))-N($E6)),MIN($F6,N($D6)*MAX(0,INDEX(IF($C6="HP",'Cálculos'!$C$313:$F$313,IF($C6="DEF",'Cálculos'!$C$314:$F$314,IF($C6="EM",'Cálculos'!$C$315:$F$315,'Cálculos'!$C$312:$F$312))),MATCH($B6,Time!$B$4:$E$4,0))-N($E6)))),0))} -> 0
K7: Sim | L7: {=IF(OR($A7="",$B7="",$K7="Não",$K7=FALSE),0,IFERROR(IF($F7="",N($D7)*MAX(0,INDEX(IF($C7="HP",'Cálculos'!$C$313:$F$313,IF($C7="DEF",'Cálculos'!$C$314:$F$314,IF($C7="EM",'Cálculos'!$C$315:$F$315,'Cálculos'!$C$312:$F$312))),MATCH($B7,Time!$B$4:$E$4,0))-N($E7)),MIN($F7,N($D7)*MAX(0,INDEX(IF($C7="HP",'Cálculos'!$C$313:$F$313,IF($C7="DEF",'Cálculos'!$C$314:$F$314,IF($C7="EM",'Cálculos'!$C$315:$F$315,'Cálculos'!$C$312:$F$312))),MATCH($B7,Time!$B$4:$E$4,0))-N($E7)))),0))} -> 0
K8: Sim | L8: {=IF(OR($A8="",$B8="",$K8="Não",$K8=FALSE),0,IFERROR(IF($F8="",N($D8)*MAX(0,INDEX(IF($C8="HP",'Cálculos'!$C$313:$F$313,IF($C8="DEF",'Cálculos'!$C$314:$F$314,IF($C8="EM",'Cálculos'!$C$315:$F$315,'Cálculos'!$C$312:$F$312))),MATCH($B8,Time!$B$4:$E$4,0))-N($E8)),MIN($F8,N($D8)*MAX(0,INDEX(IF($C8="HP",'Cálculos'!$C$313:$F$313,IF($C8="DEF",'Cálculos'!$C$314:$F$314,IF($C8="EM",'Cálculos'!$C$315:$F$315,'Cálculos'!$C$312:$F$312))),MATCH($B8,Time!$B$4:$E$4,0))-N($E8)))),0))} -> 0
K9: Sim | L9: {=IF(OR($A9="",$B9="",$K9="Não",$K9=FALSE),0,IFERROR(IF($F9="",N($D9)*MAX(0,INDEX(IF($C9="HP",'Cálculos'!$C$313:$F$313,IF($C9="DEF",'Cálculos'!$C$314:$F$314,IF($C9="EM",'Cálculos'!$C$315:$F$315,'Cálculos'!$C$312:$F$312))),MATCH($B9,Time!$B$4:$E$4,0))-N($E9)),MIN($F9,N($D9)*MAX(0,INDEX(IF($C9="HP",'Cálculos'!$C$313:$F$313,IF($C9="DEF",'Cálculos'!$C$314:$F$314,IF($C9="EM",'Cálculos'!$C$315:$F$315,'Cálculos'!$C$312:$F$312))),MATCH($B9,Time!$B$4:$E$4,0))-N($E9)))),0))} -> 0
K10: Sim | L10: {=IF(OR($A10="",$B10="",$K10="Não",$K10=FALSE),0,IFERROR(IF($F10="",N($D10)*MAX(0,INDEX(IF($C10="HP",'Cálculos'!$C$313:$F$313,IF($C10="DEF",'Cálculos'!$C$314:$F$314,IF($C10="EM",'Cálculos'!$C$315:$F$315,'Cálculos'!$C$312:$F$312))),MATCH($B10,Time!$B$4:$E$4,0))-N($E10)),MIN($F10,N($D10)*MAX(0,INDEX(IF($C10="HP",'Cálculos'!$C$313:$F$313,IF($C10="DEF",'Cálculos'!$C$314:$F$314,IF($C10="EM",'Cálculos'!$C$315:$F$315,'Cálculos'!$C$312:$F$312))),MATCH($B10,Time!$B$4:$E$4,0))-N($E10)))),0))} -> 0
K11: Sim | L11: {=IF(OR($A11="",$B11="",$K11="Não",$K11=FALSE),0,IFERROR(IF($F11="",N($D11)*MAX(0,INDEX(IF($C11="HP",'Cálculos'!$C$313:$F$313,IF($C11="DEF",'Cálculos'!$C$314:$F$314,IF($C11="EM",'Cálculos'!$C$315:$F$315,'Cálculos'!$C$312:$F$312))),MATCH($B11,Time!$B$4:$E$4,0))-N($E11)),MIN($F11,N($D11)*MAX(0,INDEX(IF($C11="HP",'Cálculos'!$C$313:$F$313,IF($C11="DEF",'Cálculos'!$C$314:$F$314,IF($C11="EM",'Cálculos'!$C$315:$F$315,'Cálculos'!$C$312:$F$312))),MATCH($B11,Time!$B$4:$E$4,0))-N($E11)))),0))} -> 0

Sheet Personagens (efeitos)
A1: Personagem | B1: ATK% (passivas) | C1: DMG% (passivas) | D1: Taxa crit (passivas) | E1: Dano crit (passivas) | F1: EM (passivas) | G1: Buff ATK fixo ao time: coef × ATK base | H1: Buff ATK fixo ao time: coef × ATK total | I1: Limite desse buff | J1: Buff vale para si mesmo? | K1: Redução de RES no inimigo | L1: Elementos afetados | M1: Fonte / observações
A2: Mavuika | B2: 0.3 | C2: 0.4 | D2: 0 | E2: 0 | F2: 0 | G2: 0 | H2: 0 | I2: 0 | J2: Não | K2: 0 | M2: A1 +30% ATK (Lunaris p1); A4 +40% DMG decaindo (use 'Ajuste DMG%' na Rotação).
A3: Citlali | B3: 0 | C3: 0 | D3: 0 | E3: 0 | F3: 0 | G3: 0 | H3: 0 | I3: 0 | J3: Não | K3: 0.2 | L3: Pyro,Hydro | M3: Reduz RES Pyro/Hydro em 20%.
A4: Iansan | B4: 0 | C4: 0 | D4: 0 | E4: 0 | F4: 0 | G4: 0 | H4: 0.37 | I4: 810 | J4: Não | K4: 0 | M4: Supremo: ATK fixo = 37% do ATK dela, máx. 810 (sua planilha).
A5: Bennett | B5: 0 | C5: 0 | D5: 0 | E5: 0 | F5: 0 | G5: 1.39 | H5: 0 | I5: 0 | J5: Sim | K5: 0 | M5: Supremo: 139% do ATK base (nv 13 + C1, sua planilha).
J6: Não
J7: Não
J8: Não
J9: Não
J10: Não
J11: Não
J12: Não
J13: Não
J14: Não
J15: Não
J16: Não
J17: Não
... J200: Não

Sheet Armas (efeitos)
A1: Arma | B1: ATK% (passiva) | C1: DMG% (passiva) | D1: Taxa crit (passiva) | E1: Dano crit (passiva) | F1: EM (passiva) | G1: ER (passiva) | H1: ATK% por ER acima de 100% (coef) | I1: Limite ATK% por ER | J1: Buff ao time: ATK% | K1: Buff ao time: DMG% | L1: Buff ao time: EM | M1: Fonte / observações
A2: A Thousand Blazing Suns | B2: 0.49 | C2: 0 | D2: 0 | E2: 0.35 | F2: 0 | G2: 0 | H2: 0 | I2: 0 | J2: 0 | K2: 0 | L2: 0 | M2: R1 em Nightsoul (×1,75): 28%→49% ATK, 20%→35% CD.
A3: Thrilling Tales of Dragon Slayers | B3: 0 | C3: 0 | D3: 0 | E3: 0 | F3: 0 | G3: 0 | H3: 0 | I3: 0 | J3: 0 | K3: 0 | L3: 0 | M3: Vai só ao PRÓXIMO personagem: use 'Buffs extras' (R5 = 48%).
A4: Engulfing Lightning | B4: 0 | C4: 0 | D4: 0 | E4: 0 | F4: 0 | G4: 0 | H4: 0.28 | I4: 0.8 | J4: 0 | K4: 0 | L4: 0 | M4: R1: ATK% = 28% do ER acima de 100%, máx. 80%.
A5: Absolution | B5: 0 | C5: 0 | D5: 0 | E5: 0.2 | F5: 0 | G5: 0 | H5: 0 | I5: 0 | J5: 0 | K5: 0 | L5: 0 | M5: R1: +20% dano crit (stacks de DMG não incluídos).
A6: Wolf's Gravestone | B6: 0.2 | C6: 0 | D6: 0 | E6: 0 | F6: 0 | G6: 0 | H6: 0 | I6: 0 | J6: 0 | K6: 0 | L6: 0 | M6: R1: +20% ATK (buff condicional de time não incluído).
A7: Serpent Spine | B7: 0 | C7: 0.3 | D7: 0 | E7: 0 | F7: 0 | G7: 0 | H7: 0 | I7: 0 | J7: 0 | K7: 0 | L7: 0 | M7: R1, 5 stacks.
A8: Beacon of the Reed Sea | B8: 0.4 | C8: 0 | D8: 0 | E8: 0 | F8: 0 | G8: 0 | H8: 0 | I8: 0 | J8: 0 | K8: 0 | L8: 0 | M8: R1: 20% + 20%.

Sheet Sets (efeitos)
A1: Set | B1: 2 peças: stat | C1: 2 peças: valor | D1: 4 peças: ATK% | E1: 4 peças: DMG% | F1: 4 peças: Taxa crit | G1: 4 peças: Dano crit | H1: 4 peças: EM | I1: 4 peças: DMG% Normal | J1: 4 peças: DMG% Carregado | K1: 4 peças: DMG% Habilidade | L1: 4 peças: DMG% Supremo | M1: 4 peças: bônus Derreter | N1: 4 peças: bônus Vaporizar | O1: 4 peças → time: ATK% | P1: 4 peças → time: DMG% | Q1: 4 peças → time: EM | R1: Observações
A2: Obsidian Codex | B2: DMG% | C2: 0.15 | D2: 0 | E2: 0 | F2: 0.4 | G2: 0 | H2: 0 | I2: 0 | J2: 0 | K2: 0 | L2: 0 | M2: 0 | N2: 0 | O2: 0 | P2: 0 | Q2: 0
A3: Scroll of the Hero of Cinder City | C3: 0 | D3: 0 | E3: 0 | F3: 0 | G3: 0 | H3: 0 | I3: 0 | J3: 0 | K3: 0 | L3: 0 | M3: 0 | N3: 0 | O3: 0 | P3: 0 | Q3: 0 | R3: 12% + 28% em Nightsoul
A4: Noblesse Oblige | B4: DMG% Supremo | C4: 0.2 | D4: 0 | E4: 0 | F4: 0 | G4: 0 | H4: 0 | I4: 0 | J4: 0 | K4: 0 | L4: 0 | M4: 0 | N4: 0 | O4: 0.2 | P4: 0 | Q4: 0
A5: Instructor | B5: EM | C5: 80 | D5: 0 | E5: 0 | F5: 0 | G5: 0 | H5: 0 | I5: 0 | J5: 0 | K5: 0 | L5: 0 | M5: 0 | N5: 0 | O5: 0 | P5: 0 | Q5: 120
A6: Crimson Witch of Flames | B6: DMG% | C6: 0.15 | D6: 0 | E6: 0.075 | F6: 0 | G6: 0 | H6: 0 | I6: 0 | J6: 0 | K6: 0 | L6: 0 | M6: 0.15 | N6: 0.15 | O6: 0 | P6: 0 | Q6: 0 | R6: 1 stack
A7: Gladiator's Finale | B7: ATK% | C7: 0.18 | D7: 0 | E7: 0 | F7: 0 | G7: 0 | H7: 0 | I7: 0.35 | J7: 0 | K7: 0 | L7: 0 | M7: 0 | N7: 0 | O7: 0 | P7: 0 | Q7: 0
A8: Shimenawa's Reminiscence | B8: ATK% | C8: 0.18 | D8: 0 | E8: 0 | F8: 0 | G8: 0 | H8: 0 | I8: 0.5 | J8: 0.5 | K8: 0 | L8: 0 | M8: 0 | N8: 0 | O8: 0 | P8: 0 | Q8: 0

Sheet Stats
A1: Main stats e substatus
A3: Areia | B3: 5★ | C3: 4★ | E3: Cálice | F3: 5★ | G3: 4★ | I3: Tiara | J3: 5★ | K3: 4★
A4: ATK% | B4: 0.466 | C4: 0.348 | E4: DMG% elemental | F4: 0.466 | G4: 0.348 | I4: CR | J4: 0.311 | K4: 0.232
A5: EM | B5: 187 | C5: 139 | E5: ATK% | F5: 0.466 | G5: 0.348 | I5: CD | J5: 0.622 | K5: 0.464
A6: ER | B6: 0.518 | C6: 0.387 | E6: EM | F6: 187 | G6: 139 | I6: ATK% | J6: 0.466 | K6: 0.348
A7: HP% | B7: 0.466 | C7: 0.348 | E7: HP% | F7: 0.466 | G7: 0.348 | I7: EM | J7: 187 | K7: 139
A8: DEF% | B8: 0.583 | C8: 0.435 | E8: DEF% | F8: 0.583 | G8: 0.435 | I8: HP% | J8: 0.466 | K8: 0.348
I9: DEF% | J9: 0.583 | K9: 0.435
I10: Cura | J10: 0.359 | K10: 0.268
A12: Peça fixa | B12: 5★ | C12: 4★
A13: Flor (HP) | B13: 4780 | C13: 3571
A14: Pena (ATK) | B14: 311 | C14: 232
A16: Substatus | B16: Valor por roll 5★ | C16: Valor por roll 4★
A17: CR | B17: 0.033 | C17: 0.0264
A18: CD | B18: 0.066 | C18: 0.0529
A19: ATK% | B19: 0.0495 | C19: 0.0396
A20: EM | B20: 19.5 | C20: 15.86
A21: ER | B21: 0.055 | C21: 0.044
A22: ATK | B22: 18.5 | C22: 13.23
A23: HP% | B23: 0.0495 | C23: 0.0396
A24: HP | B24: 254 | C24: 203.15
A25: DEF% | B25: 0.062 | C25: 0.0496
A26: DEF | B26: 19.5 | C26: 15.74
A28: Máx. de rolls de um mesmo substat por peça | B28: 6 | C28: 5
A29: Rolls de substatus por peça (iniciais + upgrades) | B29: 9 | C29: 7
A31: Valores por roll = os da sua planilha (média de roll, padrão KQM). 5★: 4 iniciais + 5 upgrades = 9; 4★: 3 iniciais + 4 upgrades = 7.

Sheet Cálculos
A1: Cálculos por personagem (não editar)
A3: Item | B3: Obs | C3: Slot 1 | D3: Slot 2 | E3: Slot 3 | F3: Slot 4
A5: Escolhas
A6: Personagem | C6: =IF(Time!B4="","",Time!B4&"") -> Mavuika | D6: =IF(Time!C4="","",Time!C4&"") -> Citlali | E6: =IF(Time!D4="","",Time!D4&"") -> Iansan | F6: =IF(Time!E4="","",Time!E4&"") -> Bennett
A7: Linha em L_Personagens | C7: =IFERROR(MATCH(C6,L_Personagens!$A$2:$A$400,0),0) -> 4 | D7: =IFERROR(MATCH(D6,L_Personagens!$A$2:$A$400,0),0) -> 2 | E7: =IFERROR(MATCH(E6,L_Personagens!$A$2:$A$400,0),0) -> 3 | F7: =IFERROR(MATCH(F6,L_Personagens!$A$2:$A$400,0),0) -> 1
A8: Linha em Personagens (efeitos) | C8: =IFERROR(MATCH(C6,'Personagens (efeitos)'!$A$2:$A$200,0),0) -> 1 | D8: =IFERROR(MATCH(D6,'Personagens (efeitos)'!$A$2:$A$200,0),0) -> 2 | E8: =IFERROR(MATCH(E6,'Personagens (efeitos)'!$A$2:$A$200,0),0) -> 3 | F8: =IFERROR(MATCH(F6,'Personagens (efeitos)'!$A$2:$A$200,0),0) -> 4
A9: Linha em L_Armas | C9: =IFERROR(MATCH(Time!B5,L_Armas!$A$2:$A$600,0),0) -> 1 | D9: =IFERROR(MATCH(Time!C5,L_Armas!$A$2:$A$600,0),0) -> 7 | E9: =IFERROR(MATCH(Time!D5,L_Armas!$A$2:$A$600,0),0) -> 5 | F9: =IFERROR(MATCH(Time!E5,L_Armas!$A$2:$A$600,0),0) -> 2
A10: Linha em Armas (efeitos) | C10: =IFERROR(MATCH(Time!B5,'Armas (efeitos)'!$A$2:$A$300,0),0) -> 1 | D10: =IFERROR(MATCH(Time!C5,'Armas (efeitos)'!$A$2:$A$300,0),0) -> 2 | E10: =IFERROR(MATCH(Time!D5,'Armas (efeitos)'!$A$2:$A$300,0),0) -> 3 | F10: =IFERROR(MATCH(Time!E5,'Armas (efeitos)'!$A$2:$A$300,0),0) -> 4
A11: Set principal em Sets (efeitos) | C11: =IFERROR(MATCH(Time!B6,'Sets (efeitos)'!$A$2:$A$200,0),0) -> 1 | D11: =IFERROR(MATCH(Time!C6,'Sets (efeitos)'!$A$2:$A$200,0),0) -> 4 | E11: =IFERROR(MATCH(Time!D6,'Sets (efeitos)'!$A$2:$A$200,0),0) -> 2 | F11: =IFERROR(MATCH(Time!E6,'Sets (efeitos)'!$A$2:$A$200,0),0) -> 3
A12: Set secundário em Sets (efeitos) | C12: =IFERROR(MATCH(Time!B7,'Sets (efeitos)'!$A$2:$A$200,0),0) -> 0 | D12: =IFERROR(MATCH(Time!C7,'Sets (efeitos)'!$A$2:$A$200,0),0) -> 0 | E12: =IFERROR(MATCH(Time!D7,'Sets (efeitos)'!$A$2:$A$200,0),0) -> 0 | F12: =IFERROR(MATCH(Time!E7,'Sets (efeitos)'!$A$2:$A$200,0),0) -> 0
A13: Bônus de 4 peças ativo (1/0) | C13: =IF(AND(Time!B6<>"",Time!B7=""),1,0) -> 1 | D13: =IF(AND(Time!C6<>"",Time!C7=""),1,0) -> 1 | E13: =IF(AND(Time!D6<>"",Time!D7=""),1,0) -> 1 | F13: =IF(AND(Time!E6<>"",Time!E7=""),1,0) -> 1
A14: Nível talento normal | C14: =IF(Time!B16="",10,VALUE(Time!B16&"")) -> 10 | D14: =IF(Time!C16="",10,VALUE(Time!C16&"")) -> 10 | E14: =IF(Time!D16="",10,VALUE(Time!D16&"")) -> 10 | F14: =IF(Time!E16="",10,VALUE(Time!E16&"")) -> 10
A15: Nível talento habilidade | C15: =IF(Time!B17="",10,VALUE(Time!B17&"")) -> 10 | D15: =IF(Time!C17="",10,VALUE(Time!C17&"")) -> 10 | E15: =IF(Time!D17="",10,VALUE(Time!D17&"")) -> 13 | F15: =IF(Time!E17="",10,VALUE(Time!E17&"")) -> 13
